Workbook
Name AmortizaciónInterés: -IPMT('Prestamo 10 años'!TasaInterés/12,'Prestamo 10 años'!NúmeroDePago,'Prestamo 10 años'!NúmeroDePagos,'Prestamo 10 años'!CantidadPréstamo)
Name AmortizaciónInterés: -IPMT('Prestamo 15 años'!TasaInterés/12,'Prestamo 15 años'!NúmeroDePago,'Prestamo 15 años'!NúmeroDePagos,'Prestamo 15 años'!CantidadPréstamo)
Name AmortizaciónInterés: -IPMT(TasaInterés/12,NúmeroDePago,NúmeroDePagos,CantidadPréstamo)
Name AñosPréstamo: 'Prestamo 10 años'!$D$6
Name AñosPréstamo: 'Prestamo 15 años'!$D$6
Name AñosPréstamo: 'Prestamo 5 años'!$D$6
Name ÁreaImpresión_ESTABLECIDA: OFFSET('Prestamo 10 años'!$B$1,,,'Prestamo 10 años'!ÚltimaFila,'Prestamo 10 años'!ÚltimaColumna)
Name ÁreaImpresión_ESTABLECIDA: OFFSET('Prestamo 15 años'!$B$1,,,'Prestamo 15 años'!ÚltimaFila,'Prestamo 15 años'!ÚltimaColumna)
Name ÁreaImpresión_ESTABLECIDA: OFFSET('Prestamo 5 años'!$B$1,,,ÚltimaFila,ÚltimaColumna)
Name CantidadPréstamo: 'Prestamo 10 años'!$D$4
Name CantidadPréstamo: 'Prestamo 15 años'!$D$4
Name CantidadPréstamo: 'Prestamo 5 años'!$D$4
Name Capital: -PPMT('Prestamo 10 años'!TasaInterés/12,'Prestamo 10 años'!NúmeroDePago,'Prestamo 10 años'!NúmeroDePagos,'Prestamo 10 años'!CantidadPréstamo)
Name Capital: -PPMT('Prestamo 15 años'!TasaInterés/12,'Prestamo 15 años'!NúmeroDePago,'Prestamo 15 años'!NúmeroDePagos,'Prestamo 15 años'!CantidadPréstamo)
Name Capital: -PPMT(TasaInterés/12,NúmeroDePago,NúmeroDePagos,CantidadPréstamo)
Name CosteTotalPréstamo: 'Prestamo 10 años'!$H$7
Name CosteTotalPréstamo: 'Prestamo 15 años'!$H$7
Name CosteTotalPréstamo: 'Prestamo 5 años'!$H$7
Name FechaDePago: DATE(YEAR('Prestamo 10 años'!FechaInicioPréstamo),MONTH('Prestamo 10 años'!FechaInicioPréstamo)+'Prestamo 10 años'!NúmeroDePago,DAY('Prestamo 10 años'!FechaInicioPréstamo))
Name FechaDePago: DATE(YEAR('Prestamo 15 años'!FechaInicioPréstamo),MONTH('Prestamo 15 años'!FechaInicioPréstamo)+'Prestamo 15 años'!NúmeroDePago,DAY('Prestamo 15 años'!FechaInicioPréstamo))
Name FechaDePago: DATE(YEAR(FechaInicioPréstamo),MONTH(FechaInicioPréstamo)+NúmeroDePago,DAY(FechaInicioPréstamo))
Name FechaInicioPréstamo: 'Prestamo 10 años'!$D$7
Name FechaInicioPréstamo: 'Prestamo 15 años'!$D$7
Name FechaInicioPréstamo: 'Prestamo 5 años'!$D$7
Name FilaEncabezados: ROW('Prestamo 10 años'!$9:$9)
Name FilaEncabezados: ROW('Prestamo 15 años'!$9:$9)
Name FilaEncabezados: ROW('Prestamo 5 años'!$9:$9)
Name Intereses_Total: 'Prestamo 10 años'!$H$6
Name Intereses_Total: 'Prestamo 15 años'!$H$6
Name Intereses_Total: 'Prestamo 5 años'!$H$6
Name NúmeroDePago: ROW()-'Prestamo 10 años'!FilaEncabezados
Name NúmeroDePago: ROW()-'Prestamo 15 años'!FilaEncabezados
Name NúmeroDePago: ROW()-FilaEncabezados
Name NúmeroDePagos: 'Prestamo 10 años'!$H$5
Name NúmeroDePagos: 'Prestamo 15 años'!$H$5
Name NúmeroDePagos: 'Prestamo 5 años'!$H$5
Name PagoMensual: -PMT('Prestamo 10 años'!TasaInterés/12,'Prestamo 10 años'!NúmeroDePagos,'Prestamo 10 años'!CantidadPréstamo)
Name PagoMensual: -PMT('Prestamo 15 años'!TasaInterés/12,'Prestamo 15 años'!NúmeroDePagos,'Prestamo 15 años'!CantidadPréstamo)
Name PagoMensual: -PMT(TasaInterés/12,NúmeroDePagos,CantidadPréstamo)
Name PréstamoNoPagado: IF('Prestamo 10 años'!NúmeroDePago<='Prestamo 10 años'!NúmeroDePagos,1,0)
Name PréstamoNoPagado: IF('Prestamo 15 años'!NúmeroDePago<='Prestamo 15 años'!NúmeroDePagos,1,0)
Name PréstamoNoPagado: IF(NúmeroDePago<=NúmeroDePagos,1,0)
Name PréstamoPagado: IF('Prestamo 10 años'!CantidadPréstamo*'Prestamo 10 años'!TasaInterés*'Prestamo 10 años'!AñosPréstamo*'Prestamo 10 años'!FechaInicioPréstamo>0,1,0)
Name PréstamoPagado: IF('Prestamo 15 años'!CantidadPréstamo*'Prestamo 15 años'!TasaInterés*'Prestamo 15 años'!AñosPréstamo*'Prestamo 15 años'!FechaInicioPréstamo>0,1,0)
Name PréstamoPagado: IF(CantidadPréstamo*TasaInterés*AñosPréstamo*FechaInicioPréstamo>0,1,0)
Name SaldoFinal: -FV('Prestamo 10 años'!TasaInterés/12,'Prestamo 10 años'!NúmeroDePago,-'Prestamo 10 años'!PagoMensual,'Prestamo 10 años'!CantidadPréstamo)
Name SaldoFinal: -FV('Prestamo 15 años'!TasaInterés/12,'Prestamo 15 años'!NúmeroDePago,-'Prestamo 15 años'!PagoMensual,'Prestamo 15 años'!CantidadPréstamo)
Name SaldoFinal: -FV(TasaInterés/12,NúmeroDePago,-PagoMensual,CantidadPréstamo)
Name TasaInterés: 'Prestamo 10 años'!$D$5
Name TasaInterés: 'Prestamo 15 años'!$D$5
Name TasaInterés: 'Prestamo 5 años'!$D$5
Name TítuloDeColumna1: Préstamo[[#Headers],[N.° de pago]]
Name TítuloDeColumna1: Préstamo[[#Headers],[N.° de pago]]
Name TítuloDeColumna1: Préstamo[[#Headers],[N.° de pago]]
Name TítuloDeColumna1: Préstamo[[#Headers],[N.° de pago]]
Name TítuloDeColumna1: Préstamo[[#Headers],[N.° de pago]]
Name TítuloDeColumna1: Préstamo[[#Headers],[N.° de pago]]
Name TítuloDeColumna1: Préstamo[[#Headers],[N.° de pago]]
Name TítuloDeColumna1: Préstamo[[#Headers],[N.° de pago]]
Name TítuloDeFilaRegión2..H6: 'Prestamo 10 años'!$F$4

Sheet Cuadro de cargas
A1: Cantidad | B1: Descripción | C1: BTU | D1: Watt | E1: No. Horas día | F1: Energía diaria Wh/d | G1: Factor carga | H1: Energía diaria Wh/d | I1: No. Dias | J1: Energía mensual kWh/mes | K1: Cargas críticas | L1: Energía diaria Wh/d | O1: Wh | P1: 1 | Q1: 2 | R1: 3 | S1: 4 | T1: 5 | U1: 6 | V1: 7 | W1: 8 | X1: 9 | Y1: 10 | Z1: 11 | AA1: 12 | AB1: 13 | AC1: 14 | AD1: 15 | AE1: 16 | AF1: 17 | AG1: 18 | AH1: 19 | AI1: 20 | AJ1: 21 | AK1: 22 | AL1: 23 | AM1: 24 | AN1: Total
A2: 1 | B2: AC principal | C2: 24 | D2: 2000 | E2: 24 | F2: =+D2*E2*A2 -> 48000 | G2: 0.6 | H2: =+F2*G2 -> 28800 | I2: 30 | J2: =+(H2*I2)/1000 -> 864 | K2: 1 | L2: =+H2*K2 -> 28800 | O2: AC cuarto ppal | P2: =+D2*G2 -> 1200 | Q2: =+P2 -> 1200 | R2: =+Q2 -> 1200 | S2: =+R2 -> 1200 | T2: =+S2 -> 1200 | U2: =+T2 -> 1200 | V2: =+U2 -> 1200 | W2: =+V2 -> 1200 | X2: =+W2 -> 1200 | ... AM2: =+AL2 -> 1200 | AN2: =+SUM(P2:AM2) -> 28800
A3: 1 | B3: AC closet principal | C3: 18 | D3: 1500 | E3: 18 | F3: =+D3*E3*A3 -> 27000 | G3: 0.6 | H3: =+F3*G3 -> 16200 | I3: 30 | J3: =+(H3*I3)/1000 -> 486 | L3: =+H3*K3 -> 0 | O3: TV | P3: 0 | Q3: =+P3 -> 0 | R3: =+Q3 -> 0 | S3: =+R3 -> 0 | AH3: =+D13*G13*A13 -> 0 | AI3: =+AH3 -> 0 | AJ3: =+AI3 -> 0 | AK3: =+AJ3 -> 0 | AN3: =+SUM(P3:AM3) -> 0
A4: 5 | B4: Luces | D4: 30 | E4: 12 | F4: =+D4*E4*A4 -> 1800 | G4: 0.3 | H4: =+F4*G4 -> 540 | I4: 30 | J4: =+(H4*I4)/1000 -> 16.2 | K4: 1 | L4: =+H4*K4 -> 540 | O4: Luces | S4: =+D4*G4 -> 9 | T4: =+S4 -> 9 | U4: =+T4 -> 9 | AG4: =+S4 -> 9 | AH4: =+AG4 -> 9 | AI4: =+AH4 -> 9 | AJ4: =+AI4 -> 9 | AK4: =+AJ4 -> 9 | AN4: =+SUM(P4:AM4) -> 72
A5: 1 | B5: Nevera | D5: 250 | E5: 24 | F5: =+D5*E5*A5 -> 6000 | G5: 0.3 | H5: =+F5*G5 -> 1800 | I5: 30 | J5: =+(H5*I5)/1000 -> 54 | K5: 1 | L5: =+H5*K5 -> 1800 | O5: NEVECON | P5: =+D5*G5 -> 75 | Q5: =+$P$5 -> 75 | R5: =+$P$5 -> 75 | S5: =+$P$5 -> 75 | T5: =+$P$5 -> 75 | U5: =+$P$5 -> 75 | V5: =+$P$5 -> 75 | W5: =+$P$5 -> 75 | X5: =+$P$5 -> 75 | ... AM5: =+$P$5 -> 75 | AN5: =+SUM(P5:AM5) -> 1800
O7: Total | P7: =+SUM(P2:P6) -> 1275 | Q7: =+SUM(Q2:Q6) -> 1275 | R7: =+SUM(R2:R6) -> 1275 | S7: =+SUM(S2:S6) -> 1284 | T7: =+SUM(T2:T6) -> 1284 | U7: =+SUM(U2:U6) -> 1284 | V7: =+SUM(V2:V6) -> 1275 | W7: =+SUM(W2:W6) -> 1275 | ... AM7: =+SUM(AM2:AM6) -> 1275 | AN7: =+SUM(P7:AM7) -> 30672
A9: 1 | B9: Lavadora | D9: 200 | E9: 4 | F9: =+D9*E9*A9 -> 800 | G9: 0.5 | H9: =+F9*G9 -> 400 | I9: 20 | J9: =+(H9*I9)/1000 -> 8 | L9: =+H9*K9 -> 0
A10: 1 | B10: Secadora | D10: 2000 | E10: 4 | F10: =+D10*E10*A10 -> 8000 | G10: 0.5 | H10: =+F10*G10 -> 4000 | I10: 20 | J10: =+(H10*I10)/1000 -> 80 | L10: =+H10*K10 -> 0
A11: 1 | B11: Máquina de hielo | D11: 200 | E11: 2 | F11: =+D11*E11*A11 -> 400 | G11: 0.3 | H11: =+F11*G11 -> 120 | I11: 30 | J11: =+(H11*I11)/1000 -> 3.6 | L11: =+H11*K11 -> 0
A14: 1 | B14: Impresora | D14: 100 | E14: 2 | F14: =+D14*E14*A14 -> 200 | G14: 0.3 | H14: =+F14*G14 -> 60 | I14: 20 | J14: =+(H14*I14)/1000 -> 1.2 | L14: =+H14*K14 -> 0
A15: 1 | B15: Monitor | D15: 100 | E15: 4 | F15: =+D15*E15*A15 -> 400 | G15: 0.3 | H15: =+F15*G15 -> 120 | I15: 30 | J15: =+(H15*I15)/1000 -> 3.6 | L15: =+H15*K15 -> 0
A18: 10 | B18: Luces piscina | D18: 20 | E18: 8 | F18: =+D18*E18*A18 -> 1600 | G18: 0.3 | H18: =+F18*G18 -> 480 | I18: 30 | J18: =+(H18*I18)/1000 -> 14.4 | K18: 0 | L18: =+H18*K18 -> 0
A19: 1 | B19: Cargador volvo | D19: 7000 | E19: 4 | F19: =+D19*E19*A19 -> 28000 | G19: 0.3 | H19: =+F19*G19 -> 8400 | I19: 20 | J19: =+(H19*I19)/1000 -> 168 | L19: =+H19*K19 -> 0
A20: 1 | B20: Cargador carro golf | D20: 7000 | E20: 4 | F20: =+D20*E20*A20 -> 28000 | G20: 0.3 | H20: =+F20*G20 -> 8400 | I20: 20 | J20: =+(H20*I20)/1000 -> 168 | L20: =+H20*K20 -> 0
A22: 1 | B22: Sistema sonido sala | D22: 500 | E22: 4 | F22: =+D22*E22*A22 -> 2000 | G22: 0.3 | H22: =+F22*G22 -> 600 | I22: 15 | J22: =+(H22*I22)/1000 -> 9 | L22: =+H22*K22 -> 0
A23: 1 | B23: Nevera de vinos 12 botellas | D23: 100 | E23: 24 | F23: =+D23*E23*A23 -> 2400 | G23: 0.3 | H23: =+F23*G23 -> 720 | I23: 30 | J23: =+(H23*I23)/1000 -> 21.6 | L23: =+H23*K23 -> 0
F26: =+SUM(F2:F2) -> 48000 | H26: =+SUM(H2:H23) -> 70640 | J26: =+SUM(J2:J23) -> 1897.6 | L26: =+SUM(L2:L23) -> 31140
D27: =+#REF!+D4+D5+D8+(A12*D12)+(A13*D13)+(A16*D16)+(A17*D17)+(A21*D21) -> #REF! | F27: =+F26/1000 -> 48 | H27: =+H26/1000 -> 70.64 | J27: =+J26/30 -> 63.253333 | L27: =+L26/1000 -> 31.14
H28: Adicional | J28: 0.1 | L28: 0.1
H29: Energía diaria final | J29: =+J27*(1+J28) -> 69.578667 | K29: kWh-dia | L29: =+L27*(1+L28) -> 34.254
E30: =14000/(51.2) -> 273.4375 | H30: Energía mensual final | J30: =+J29*30 -> 2087.36 | K30: kWh-mes
E31: =+E30*1.25 -> 341.79688
B33: Área m2 | D33: =+D34*D35 -> 14.884
B34: Largo m | D34: 6.1 | G34: Pp= | H34: =+(H37/(H38*H39))*1000 -> 16136.054 | I34: Wp | K34: Ficha Técnica Panel
B35: Ancho m | D35: 2.44 | G35: Np= | H35: =+ROUNDUP(H34/L36,0) -> 24
G36: I = | H36: =+H37/H40 -> 1.4495556 | I36: Ah | K36: Pm= | L36: 700 | M36: W
B37: Área del Panel | D37: =+D38*D39 -> 3.106352 | G37: Ed | H37: =+J29 -> 69.578667 | I37: kWhd | K37: Vmp= | L37: 40.99 | M37: V
B38: Largo m | D38: 2.384 | G38: HSP | H38: 5.39 | I38: horas | K38: Imp= | L38: 13.54 | M38: A
B39: Ancho m | D39: 1.303 | G39: PR | H39: 0.8 | K39: Voc= | L39: 49.72 | M39: V
G40: V= | H40: 48 | I40: V | K40: Isc= | L40: 14.12 | M40: A
B41: No paneles | D41: =+D33/D37 -> 4.7914724 | G41: Potencia de los paneles | H41: =+H35*L36 -> 16800 | I41: Wp | K41: Dimensiones
B42: Potencia Panel | D42: 700 | G42: Potencia en DC inversores | H42: =+H43*1.4 -> 8400 | I42: Wp | K42: Largo | L42: 2.3 | M42: m
B43: Pp | D43: =+D42*4 -> 2800 | G43: Potencia en AC inversores | H43: 6000 | I43: w | K43: Espesor | L43: 31 | M43: mm
K44: Ancho | L44: =1.134+0.02 -> 1.154 | M44: m
K45: Área | L45: =+(L42*(L44+0.03+0.03)) -> 2.7922 | M45: m2

Sheet Datos2
A1: 1. Calcular el promedio de consumo eléctrico mensual | C1: NIC | D1: 6826712
A2: Mes kWh-mes
B4: =+D1 -> 6826712 | C4: Total
A5: 45870 | B5: 2142 | C5: =+B5 -> 2142 | N5: 45870 | O5: 45901 | P5: 45931 | Q5: 45962 | R5: 45992 | S5: 46023 | T5: 46054 | U5: 46082 | V5: 46113 | W5: 46143 | X5: 46174 | Y5: 46204 | Z5: 46235 | AA5: Promedio mes | AB5: Promedio dia
A6: 45901 | B6: 2063 | C6: =+B6 -> 2063 | G6: 12hrs | I6: Consumo Actual | M6: Consumo actual | N6: 2142 | O6: 2063 | P6: 1931 | Q6: 1439 | R6: 1428 | S6: 1562 | T6: 1231 | U6: 1361 | V6: 1712 | W6: 1565 | X6: 2143 | Y6: 2131 | Z6: 2409 | AA6: =+AVERAGE(N6:Z6) -> 1778.2308 | AB6: =+AA6/30 -> 59.274359
A7: 45931 | B7: 1931 | C7: =+B7 -> 1931 | M7: Costo energía | N7: =+(N6*Tarifas!X7)/1000*1.2 -> 2331.9183 | O7: =+(O6*Tarifas!Y7)/1000*1.2 -> 2335.6296 | P7: =+(P6*Tarifas!Z7)/1000*1.2 -> 2186.2782 | Q7: =+(Q6*Tarifas!AA7)/1000*1.2 -> 1629.1667 | R7: =+(R6*Tarifas!AB7)/1000*1.2 -> 1616.7131 | S7: =+(S6*Tarifas!AC7)/1000*1.2 -> 1758.4871 | T7: =+(T6*Tarifas!AD7)/1000*1.2 -> 1308.3708 | U7: =+(U6*Tarifas!AE7)/1000*1.2 -> 1446.5252 | ... Z7: =+(Z6*Tarifas!AJ7)/1000*1.2 -> 2300.8744
A8: 45962 | B8: 1439 | C8: =+B8 -> 1439 | M8: Consumo a cubrir con energía solar | N8: =+Producción!J8 -> 2150.5786 | O8: =+Producción!K8 -> 1982.636 | P8: =+Producción!L8 -> 2360.8296 | Q8: =+Producción!M8 -> 2144.5576 | R8: =+Producción!N8 -> 2079.2997 | S8: =+Producción!O8 -> 2090.0679 | T8: =+Producción!P8 -> 2224.0865 | U8: =+Producción!Q8 -> 2191.452 | ... Z8: =+Producción!V8 -> 2146.1897 | AA8: =+AVERAGE(P8:Z8) -> 2070.1202
A9: 45992 | B9: 1428 | C9: =+B9 -> 1428 | M9: % consumo cubierto con energía solar | N9: =+N8/N6 -> 1.004005 | O9: =+O8/O6 -> 0.9610451 | P9: =+P8/P6 -> 1.2225943 | Q9: =+Q8/Q6 -> 1.490311 | R9: =+R8/R6 -> 1.4560922 | S9: =+S8/S6 -> 1.3380716 | T9: =+T8/T6 -> 1.8067315 | U9: =+U8/U6 -> 1.6101778 | ... AA9: =+AA8/AA6 -> 1.164146
A10: 46023 | B10: 1562 | C10: =+B10 -> 1562
A11: 46054 | B11: 1231 | C11: =+B11 -> 1231
A12: 46082 | B12: 1361 | C12: =+B12 -> 1361
A13: 46113 | B13: 1712 | C13: =+B13 -> 1712
A14: 46143 | B14: 1565 | C14: =+B14 -> 1565
A15: 46174 | B15: 2143 | C15: =+B15 -> 2143
A16: 46204 | B16: 2131 | C16: =+B16 -> 2131
A17: 46235 | B17: 2409 | C17: =+B17 -> 2409
A18: Promedio mensual (kWh-mes) | B18: =+AVERAGE(B7:B17) -> 1719.2727 | C18: 1849.3077
A19: Promedio diario (kWh-dia) | B19: =+B18/30 -> 57.309091 | C19: =+C18/30 -> 61.64359
A20: Límite de producción | B20: 1.2 | C20: 1.2
A21: Pp | B21: =+(B19*B20*1000)/(J44*Cálculos!D6) -> 15943.797 | C21: =+(C20*1000)/(J44*Cálculos!D6) -> 278.20711 | H21: I
A22: Inversor kW | C22: 10 | H22: Imax
H23: Rtamb=
H24: R20°C=
H25: Calibre
B26: Local | H26: Total
B27: Cap instalada AC | H27: =+SUM(C27:G27) -> 0
B28: PP instalada | H28: =+SUM(C28:G28) -> 0
A29: 2. Escoger el nivel de voltaje del módulo fotovoltáico | B29: Pot exportación | H29: =+SUM(C29:G29) -> 0
C30: =12*610 -> 7320 | D30: =24*610 -> 14640 | E30: =+E28/610 -> 0 | F30: =12*610 -> 7320 | G30: =+G28/610 -> 0 | H30: =+H28/610 -> 0
A31: Potencia demandada (W) | B31: Tension (V) | C31: Nivel de voltaje seleccionado
A32: Menor de 1500 W | B32: 12, 24 o 48
A33: 1500 - 5000 W | B33: 24 o 48 | C33: 48
A34: Mayor de 5000 W | B34: 120 o 300
A37: 3. Ubicación del sistema solar fotovoltáico
A39: Latitud | B39: 10.5831
A40: Longitud | B40: -74.4821
A43: 4. Horas Sol Pico
I44: Promedio | J44: =+AVERAGE(A56:O56) -> 5.3916667
I45: Máx | J45: =+MAX(A56:O56) -> 6.04
I46: Mín | J46: =+MIN(A56:O56) -> 4.72
I47: PR | J47: 0.8
I50: Latitud | J50: 10.5831
I51: Longitud | J51: -74.4821
A55: Ene | B55: Feb | C55: Mar | D55: Abr | E55: May | F55: Jun | G55: Jul | H55: Ago | I55: Sep | J55: Oct | K55: Nov | L55: Dic
A56: 5.69 | B56: 6.04 | C56: 5.87 | D56: 5.51 | E56: 5.17 | F56: 5.37 | G56: 5.53 | H56: 5.46 | I56: 5.28 | J56: 4.84 | K56: 4.72 | L56: 5.22

Sheet Cálculos
A1: 1. | B1: Hallar potencia Paneles Solares | C1: Pp= | D1: =+(D4/(D5*D6))*1000 -> 15943.797 | E1: Wp | G1: Ficha Técnica Panel | M1: Ficha Técnica Batería
C2: Np= | D2: =+ROUND(D1/H3,0) -> 22 | E2: =+D1/H3 -> 21.991444 | F2: =43*730 -> 31390
C3: I = | D3: =+D4/D7 -> 1.4327273 | E3: Ah | G3: Pm= | H3: 725 | I3: W | M3: Pdmaxe | N3: 0.7
C4: Ed | D4: =+Datos2!B19*Datos2!B20 -> 68.770909 | E4: kWhd | G4: Vmp= | H4: 40.99 | I4: V | M4: Pdmaxd | N4: 0.15
C5: HSP | D5: =+Datos2!J44 -> 5.3916667 | E5: horas | G5: Imp= | H5: 13.54 | I5: A | M5: V | N5: 6 | O5: V
C6: PR | D6: 0.8 | G6: Voc= | H6: 49.72 | I6: V | M6: I | N6: 300 | O6: Ah
C7: V= | D7: =+Datos2!C33 -> 48 | E7: V | G7: Isc= | H7: 14.12 | I7: A | M7: FCT (Factor de corrección de Temperatura) | N7: 1
C8: Potencia de los paneles Wp | D8: =+D2*H3 -> 15950 | E8: =+E2*H3 -> 15943.797 | G8: Dimensiones
C9: Potencia en DC inversores Wp | D9: =+(D22*B24) -> 15600 | G9: Largo | H9: 2.3 | I9: m
C10: Potencia en AC inversores W | D10: =+(D23*B24) -> 12000 | G10: Espesor | H10: 31 | I10: mm
G11: Ancho | H11: =1.134+0.02 -> 1.154 | I11: m
B12: Pp= Potencia del Panel | G12: Área | H12: 3.1 | I12: m2 | M12: Pdmaxe= Profundidad de descarga max estacionaria (FT) | N12: Valor constante
B13: Ed, max= Energia diaria + 15% | M13: Pdmaxd= Profundidad de descarga max diaria (FT) | N13: Valor constante
B14: HSP= Horas de sol pico, tomados del software de la NASA
B15: PR = performance Ratio
B16: Pm= Potencia del modulo solar (Tomado de la FT) | G16: Corrección por temperatura
B17: Np= No de paneles requerido | G17: Temp max amb | H17: 75
G18: Temp STC | H18: 25
G19: Delta Temp | H19: =+H17-H18 -> 50
G20: Potencia
A21: 2. | B21: Calcular el inversor | C21: % Sobredimensionamiento | D21: 0.3 | G21: Coef Pmax | H21: -0.0035
B22: Inversor 1 | C22: Pmax= | D22: =+D23*(1+D21) -> 15600 | E22: W | G22: Delta Pot | H22: =+H21*H19 -> -0.175
B23: Cantidad | C23: Pnom= | D23: 12000 | E23: W | G23: Pmc= | H23: =+H3*(100%+H22) -> 598.125 | I23: W
B24: 1 | C24: Imax DC= | D24: 30 | E24: A | G24: Voc
B25: No Paneles aproximados por MPPT | C25: IscDC= | D25: 37.5 | E25: A | G25: Coef Voc | H25: -0.00275
B26: =+ROUND(D2/(D30*B24),0) -> 4 | C26: VnomDC= | D26: 370 | E26: V | G26: Delta Voc | H26: =+H25*H19 -> -0.1375
C27: Inom AC= | D27: =D23/(D29*1.732) -> 31.492757 | E27: A | G27: Voc= | H27: =+H6*(100%+H26) -> 42.8835 | I27: V | J27: Vmp= | K27: =+H4*(100%+H26) -> 35.353875 | L27: V
C28: I max AC= | D28: 96 | E28: A
C29: Vac= | D29: 220 | E29: V | G29: Isc
C30: MPPT | D30: 6 | E30: A | G30: Coef Isc | H30: 0.00045
C31: String | D31: 2 | G31: Delta Isc | H31: =+H30*H19 -> 0.0225
G32: Isc= | H32: =+H7*(100%+H31) -> 14.4377 | I32: Amp | J32: Imp= | K32: =+H5*(100%+H31) -> 13.84465
C33: % Sobredimensionamiento | D33: 0.35
B34: Inversor 2 | C34: Pmax= | D34: =+D35*(1+D33) -> 8100 | E34: W
B35: Cantidad | C35: Pnom= | D35: 6000 | E35: W
B36: 1 | C36: Imax DC= | D36: 0 | E36: A
B37: No Paneles aproximados por MPPT | C37: IscDC= | D37: 0 | E37: A
B38: 0 | C38: VnomDC= | D38: 0 | E38: V
C39: Inom AC= | D39: 0 | E39: A
C40: I max AC= | D40: 0 | E40: A
C41: Vac= | D41: 0 | E41: V
C42: MPPT | D42: 0 | E42: A
C43: String | D43: 0
A45: 3. | B45: Área requerida para el montaje
B47: Atotal= | C47: =+H12*D2 -> 68.2 | D47: m2
L48: A
A49: 4. | B49: Arreglo de módulos
B50: String 1, 2 y 15- Inversor 1 | C50: Voc | D50: =+B52*H27 -> 85.767 | E50: V
B51: No Paneles Serie | C51: Isc | D51: =+H32 -> 14.4377 | E51: A
B52: =+ROUND(D2/(D30*D31*B24),0) -> 2 | C52: Potencia | D52: =+D50*D51 -> 1238.2782 | E52: W
B54: String 4 y 5 - Inversor 2 | C54: Voltaje | D54: =+B56*H27 -> 0 | E54: V
B55: No Paneles Serie | C55: Corriente | D55: =+H32 -> 14.4377 | E55: A
B56: =+B38 -> 0 | C56: Potencia | D56: =+D54*D55 -> 0 | E56: W
B58: Arreglo Final - Inversor 1 | C58: Voltaje | D58: =+D50 -> 85.767 | E58: V
B59: No String Paralelo | C59: Corriente | D59: =+D51*B60 -> 173.2524 | E59: A
B60: =+D30*D31*B24 -> 12 | C60: Potencia | D60: =+D58*D59 -> 14859.339 | E60: W
B62: Arreglo Final - Inversor 2 | C62: Voltaje | D62: =+D54 -> 0 | E62: V
B63: No String Paralelo | C63: Corriente | D63: =+D55*B64 -> 0 | E63: A
B64: =+D42*B36 -> 0 | C64: Potencia | D64: =+D62*D63 -> 0 | E64: W
A66: 5. | B66: Cálculo de Protecciones
B67: DC
B68: Fusibles | C68: Cantidad | D68: =2*B64+2*B60 -> 24 | G68: Dos por cada string
B69: VFGV= 1,2*Nms*VModOCSTC | C69: VFGV= | D69: =1.2*B56*H6 -> 0 | E69: V | F69: Buscar ref comercial por encima
B70: In= 1,56*IModscSTC | C70: In= | D70: =1.56*H7 -> 22.0272 | E70: A | F70: Certificado de conformidad y RETIE
B72: DPS | C72: Cantidad | D72: =1*B64+1*B60 -> 12 | F72: Bipolar-verificar datasheet para validar conexión | G72: Uno por cada string
B73: VDPS= 1,1*Nms*Vmod,oc,stc | C73: VDps= | D73: =1.1*B52*H6 -> 109.384 | E73: V | F73: Buscar ref comercial por encima
F74: Certificado de conformidad y RETIE
B76: Interruptor principal DC | C76: Cantidad | D76: =+D30*B24+D42*B36 -> 6 | F76: Bipolar | G76: Uno por cada string
B77: Vint=1,2*Nms*Vmod,oc,stc | C77: Vint= | D77: =1.2*B52*H6 -> 119.328 | E77: V | G77: Se escoge fusible o interruptor DC
B78: Imax= 1,25*Isc*Nmp | C78: Imax= | D78: =1.25*H7 -> 17.65 | E78: A
B79: In=1,25*Imax | C79: In= | D79: =1.25*D78 -> 22.0625 | E79: A
B81: AC
B82: Breaker termomagnético | C82: Protección de tensión y de corriente
B83: Vint= 1,2 VAC | C83: Vint= | D83: =1.2*D29 -> 264 | E83: V
B84: Imax= 1,25*Imax | C84: Imax= | D84: =1.15*D28 -> 110.4 | E84: A | F84: Debe ser inferior a la corriente deI cable, ya que 1ro dispara breaker antes que se queme el cable
B87: DPS - Falla de puesta de tierra
B88: VDPS= 1,1*Vinv | D88: =1.1*D29 -> 242 | E88: V | F88: Buscar ref comercial por encima
B90: Pararrayos depende de la estructura
B93: Medidor Bidireccional
B95: Cableado DC | D95: Por panel | E95: Total
B96: Tipo PV | C96: Cable positivo (No 12 AWG) | D96: =3*D2 -> 66 | E96: =+D96*1.1 -> 72.6
C97: Cable negativo (No 12 AWG) | D97: =3*D2 -> 66 | E97: =+D97*1.1 -> 72.6
B98: Por String a inversor | C98: Cable Tierra No 10 o 12 | D98: =2.5*D2 -> 55 | E98: =+D98*1.1 -> 60.5
B99: Inom= 1,25*(1,25*Isc)
B100: RTamb= Delta V/(2*L*Isc)
B101: R20°C= Rtamb/(1+p(delta T))
B103: Tamb= Temperatura max ambiente= | C103: =+H17 -> 75 | D103: °C
B104: Caida tensión requerida | C104: 0.022
B105: Delta V= | C105: =+D50*C104 -> 1.886874 | D105: V
B106: L= | C106: 0.03 | D106: Km
B107: Inom= | C107: =1.25*(1.25*D51) -> 22.558906 | D107: A
B108: Rtamb= | C108: =+(C105)/(2*C106*C107) -> 1.3940348 | D108: ohm/Km
B109: pCu= | C109: 0.00323
B110: Detla T= | C110: =+C103-20 -> 55 | D110: °C
B111: R20°C= | C111: =+(C108)/(1+(C109*C110)) -> 1.1837429 | D111: ohm/Km
B112: Calibre conductor | C112: 12
B113: Conectores MC4 | C113: =2*B64+2*B60 -> 24
B115: Del Inversor al tablero de protecciones
B116: Cable AC
B117: Inom= 1,25*Imax
...

Sheet Área

Sheet SIGO GoodWe
A3: Detallw Servicio llave en mano | B3: Precio de venta antes IVA | C3: Precio de Venta Iva Incluido | D3: PV antes de Iva | E3: PV Iva incluido | G3: Descripción | H3: Precio de venta antes IVA | I3: Precio de Venta Iva Incluido
A4: Suministro de equipos de energía renovable | B4: 19286571 | C4: 19370171 | D4: =+B4 -> 19286571 | E4: =D4 -> 19286571 | G4: Grupo generador | H4: =+#REF! -> #REF! | I4: =+#REF! -> #REF! | K4: 12176683
A5: Suministro de materiales y equipos | B5: 8206074.6 | C5: 9278591.5 | D5: =+B5 -> 8206074.6 | E5: =+C5 -> 9278591.5 | F5: =B5/2 -> 4103037.3 | G5: Descripción | H5: Precio de venta antes IVA | I5: Precio de Venta Iva Incluido | K5: =E4-K4 -> 7109888
A6: Servicio de diseño | B6: 5151515.2 | C6: 6130303 | D6: =C6/1.19 -> 5151515.2 | E6: =D6*1.19 -> 6130303 | G6: Total | H6: =+D13+H4 -> #REF! | I6: =+E13+I4 -> #REF!
A7: Servicio de instalación | B7: 4909090.9 | C7: 4969401.5 | D7: =+B7 -> 4909090.9 | E7: =+C22 -> 4950730.5
A8: Suministro de estructura | B8: 3576900 | C8: 4256511 | D8: =+B8 -> 3576900 | E8: =D8*1.19 -> 4256511
A9: Certificación Retie | B9: 1969697 | C9: 2343939.4 | D9: =+B9 -> 1969697 | E9: =D9*1.19 -> 2343939.4 | G9: =E12-D12 -> 3636191.7
A10: Suministro de medidor bidireccional | B10: 1666666.7 | C10: 1983333.3 | D10: =+B10 -> 1666666.7 | E10: =D10*1.19 -> 1983333.3 | G10: =D12/2 -> 22837803
A11: Trámites ante entidades | B11: 909090.91 | C11: 1081818.2 | D11: =+B11 -> 909090.91 | E11: =D11*1.19 -> 1081818.2 | G11: =D12/5 -> 9135121.2
A12: Total general | B12: 45675606 | C12: 49414069 | D12: =+SUM(D3:D11) -> 45675606 | E12: =+SUM(E3:E11) -> 49311798
F13: =E14/4 -> 0
A16: Servicio de instalación | C16: =+B7 -> 4909090.9
A17: Costo Directo | B17: =+SUM(B18:B20) -> 0.12 | C17: =+C16/(1+SUM(B18:B20)) -> 4383116.9
A18: Administración | B18: 0.05 | C18: =+C17*B18 -> 219155.84 | F18: Flujo de caja | G18: Porcentaje | H18: Valor antes de IVA | I18: Valor con IVA
A19: Imprevistos | B19: 0.02 | C19: =+C17*B19 -> 87662.338 | F19: Anticipo | G19: 0.35 | H19: =+$D$12*G19 -> 15986462 | I19: =$E$12*G19 -> 17259129
A20: Utilidad | B20: 0.05 | C20: =+C17*B20 -> 219155.84 | F20: Con llegada de paneles | G20: 0.25 | H20: =+$D$12*G20 -> 11418902 | I20: =$E$12*G20 -> 12327949
A21: Iva | B21: 0.19 | C21: =+C20*B21 -> 41639.61 | F21: Con llegada de inversor | G21: 0.2 | H21: =+$D$12*G21 -> 9135121.2 | I21: =$E$12*G21 -> 9862359.6
C22: =+SUM(C17:C21) -> 4950730.5 | F22: Instalacion aprobada | G22: 0.2 | H22: =+$D$12*G22 -> 9135121.2 | I22: =$E$12*G22 -> 9862359.6
E25: =E14-D14 -> 0 | F25: =+SUM(I19:I22) -> 49311798
E26: =D14/2 -> 0
E27: =D14/5 -> 0
B28: 25384068
B29: 20513846
B30: 14948373
B31: 9200000
B32: 3962104.6
B33: 2738461.5
B34: 2615384.6
B35: 2000000
B36: 1846153.8
B37: =SUM(B28:B36) -> 83208392

Sheet Capex GoodWe
C1: Margen | D1: Factor | Q1: Tiempo reposición | S1: =10*12 -> 120 | T1: meses
B2: Equipos renovable | C2: 0.34 | D2: =1-C2 -> 0.66
B3: Planta eléctrica | C3: 0.34 | D3: =1-C3 -> 0.66 | F3: =12000/(1.73*220) -> 31.529164 | G3: =F3*1.25 -> 39.411456 | H3: =360000/730 -> 493.15068
B4: Instalación | C4: 0.34 | D4: =1-C4 -> 0.66 | J4: 4000
B5: Diseños y trámites | C5: 0.34 | D5: =1-C5 -> 0.66 | F5: =I26+I30+I41+I54+I83 -> 2839947.5
B6: Obra civil | C6: 0.34 | D6: =1-C6 -> 0.66
A8: Item | B8: Descripción | C8: Un | D8: Inv 1 | E8: Inv 2 | F8: Cant total | G8: IVA | H8: CU | I8: CT antes IVA | J8: CT Iva Incluido | K8: PV | L8: PV antes IVA | M8: PV Iva Incluido | N8: Categoría Sigo | O8: Pareto | P8: Costo/Winstalado | Q8: Precio/Winstalado | R8: Tiempo de reposición | S8: Reposición Empresa | T8: Reposición Cliente
A9: 1 | B9: Equipos principales | I9: =+SUM(I10:I15) -> 13333037 | J9: =+SUM(J10:J15) -> 13502954 | L9: =+SUM(L10:L15) -> 20201571 | M9: =+SUM(M10:M15) -> 20459021 | O9: =+K9/$K$117 -> 0 | P9: =+H9/$C$180 -> 0 | Q9: =+K9/$C$180 -> 0 | V9: V.U. Antes IVA | W9: V.U | X9: Cantidad/panel | Y9: V.T. antes IVA | Z9: V.T./panel | AA9: =+M9 -> 20459021 | AB9: =+J9 -> 13502954
A10: 1.1 | B10: PANEL SOLAR 725 W | C10: Un | D10: =+Cálculos!D2 -> 22 | E10: 0 | F10: =+D10+E10 -> 22 | G10: 0 | H10: =370000 -> 370000 | I10: =+H10*F10 -> 8140000 | J10: =+I10*(1+G10) -> 8140000 | K10: =+H10/$D$2 -> 560606.06 | L10: =+K10*F10 -> 12333333 | M10: =+L10*(1+G10) -> 12333333 | N10: Suministro de equipos de energía renovable | R10: =20*12 -> 240 | S10: =+IF(R10=0,0,H10/R10) -> 1541.6667 | T10: =+IF(R10=0,0,K10/R10) -> 2335.8586 | U10: Riel AS-DR-01A-5100 | V10: 123655 | W10: =+V10*1.19 -> 147149.45 | X10: 0.52 | Y10: =+V10*X10 -> 64300.6 | Z10: =+W10*X10 -> 76517.714
A11: 1.2 | B11: [GW12KLV-MT] Inversor trifásico 12kw 208-240Vac 3 MPPT con DC switch y Wifi GoodWe | C11: Un | D11: 1 | E11: 0 | F11: =+D11+E11 -> 1 | G11: 0 | H11: 4298736.9 | I11: =+H11*F11 -> 4298736.9 | J11: =+I11*(1+G11) -> 4298736.9 | K11: =+H11/$D$2 -> 6513237.7 | L11: =+K11*F11 -> 6513237.7 | M11: =+L11*(1+G11) -> 6513237.7 | N11: Suministro de equipos de energía renovable | R11: =20*12 -> 240 | S11: =+IF(R11=0,0,H11/R11) -> 17911.404 | T11: =+IF(R11=0,0,K11/R11) -> 27138.49 | U11: Middle clamp AS-DMC / 30 mm | V11: 5668 | W11: =+V11*1.19 -> 6744.92 | X11: 2.017 | Y11: =+V11*X11 -> 11432.356 | Z11: =+W11*X11 -> 13604.504
A12: 1.3 | B12: Smart Meter | C12: Un | D12: 1 | E12: 0 | F12: =+D12+E12 -> 1 | G12: 0.19 | H12: =88*3300 -> 290400 | I12: =+H12*F12 -> 290400 | J12: =+I12*(1+G12) -> 345576 | K12: =+H12/$D$2 -> 440000 | L12: =+K12*F12 -> 440000 | M12: =+L12*(1+G12) -> 523600 | N12: Suministro de equipos de energía renovable | R12: =20*12 -> 240 | S12: =+IF(R12=0,0,H12/R12) -> 1210 | T12: =+IF(R12=0,0,K12/R12) -> 1833.3333
A13: 1.4 | B13: [GW14.3-BAT-LV-G10] Batería LFP(LiFePO4) 51.2 Vdc 280 Ah [with aerosol] Goodwe | C13: Un | D13: 0 | E13: 0 | F13: =+D13+E13 -> 0 | G13: 0.19 | H13: 6667000 | I13: =+H13*F13 -> 0 | J13: =+I13*(1+G13) -> 0 | K13: =+H13/$D$2 -> 10101515 | L13: =+K13*F13 -> 0 | M13: =+L13*(1+G13) -> 0 | N13: Suministro de equipos de almacenamiento | R13: =20*12 -> 240 | S13: =+IF(R13=0,0,H13/R13) -> 27779.167 | T13: =+IF(R13=0,0,K13/R13) -> 42089.646 | U13: Enclamp AS-DEC / 30 mm | V13: 5668 | W13: =+V13*1.19 -> 6744.92 | X13: 0.367 | Y13: =+V13*X13 -> 2080.156 | Z13: =+W13*X13 -> 2475.3856
A14: 1.5 | B14: HV418100 12S Gabinete | C14: Un | D14: 0 | E14: 0 | F14: =+D14+E14 -> 0 | G14: 0.19 | H14: 4784000 | I14: =+H14*F14 -> 0 | J14: =+I14*(1+G14) -> 0 | K14: =+H14/$D$2 -> 7248484.8 | L14: =+K14*F14 -> 0 | M14: =+L14*(1+G14) -> 0 | N14: Suministro de materiales y equipos | R14: =20*12 -> 240 | S14: =+IF(R14=0,0,H14/R14) -> 19933.333 | T14: =+IF(R14=0,0,K14/R14) -> 30202.02 | U14: Clip tierra | V14: 1030 | W14: =+V14*1.19 -> 1225.7 | X14: 0.5 | Y14: =+V14*X14 -> 515 | Z14: =+W14*X14 -> 612.85
A15: 1.6 | B15: EQUIPOS DE MEDIDA TC´S | C15: Un | D15: 3 | E15: 0 | F15: =+D15+E15 -> 3 | G15: 0.19 | H15: =61*3300 -> 201300 | I15: =+H15*F15 -> 603900 | J15: =+I15*(1+G15) -> 718641 | K15: =+H15/$D$2 -> 305000 | L15: =+K15*F15 -> 915000 | M15: =+L15*(1+G15) -> 1088850 | N15: Suministro de materiales y equipos
A16: 2 | B16: Estructura Metálica | I16: =+SUM(I17:I25) -> 2360754 | J16: =+SUM(J17:J25) -> 2809297.3 | K16: 0 | L16: =+SUM(L17:L25) -> 3576900 | M16: =+SUM(M17:M25) -> 4256511 | O16: =+K16/$K$117 -> 0 | P16: =+H16/$C$180 -> 0 | Q16: =+K16/$C$180 -> 0 | S16: =+IF(R16=0,0,H16/R16) -> 0 | T16: =+IF(R16=0,0,K16/R16) -> 0 | U16: Ground Clamp | V16: 5744 | W16: =+V16*1.19 -> 6835.36 | X16: 0.183 | Y16: =+V16*X16 -> 1051.152 | Z16: =+W16*X16 -> 1250.8709 | AA16: =+M16 -> 4256511 | AB16: =+J16 -> 2809297.3
A17: 2.1 | B17: Riel de soporte aluminio anodizado 4,7 | C17: Un | D17: =0.61*D10 -> 13.42 | E17: =0.61*E10 -> 0 | F17: =+D17+E17 -> 13.42 | G17: 0.19 | H17: 100000 | I17: =+H17*F17 -> 1342000 | J17: =+I17*(1+G17) -> 1596980 | K17: =+H17/$D$2 -> 151515.15 | L17: =+K17*F17 -> 2033333.3 | M17: =+L17*(1+G17) -> 2419666.7 | N17: Suministro de estructura | R17: 0 | S17: =+IF(R17=0,0,H17/R17) -> 0 | T17: =+IF(R17=0,0,K17/R17) -> 0 | U17: Autoperforante | V17: 15457 | W17: =+V17*1.19 -> 18393.83 | X17: 0.5 | Y17: =+V17*X17 -> 7728.5 | Z17: =+W17*X17 -> 9196.915
A18: 2.2 | B18: Union de riel | C18: Un | D18: =0.33*D10 -> 7.26 | E18: =0.33*E10 -> 0 | F18: =+D18+E18 -> 7.26 | G18: 0.19 | H18: 6900 | I18: =+H18*F18 -> 50094 | J18: =+I18*(1+G18) -> 59611.86 | K18: =+H18/$D$2 -> 10454.545 | L18: =+K18*F18 -> 75900 | M18: =+L18*(1+G18) -> 90321 | N18: Suministro de estructura | P18: =+H18/$C$180 -> 0.4327702 | Q18: =+K18/$C$180 -> 0.65571242 | R18: 0 | S18: =+IF(R18=0,0,H18/R18) -> 0 | T18: =+IF(R18=0,0,K18/R18) -> 0 | U18: Unión de Riel | V18: 5733 | W18: =+V18*1.19 -> 6822.27 | X18: 0.46 | Y18: =+V18*X18 -> 2637.18 | Z18: =+W18*X18 -> 3138.2442
A19: 2.3 | B19: Mid Clamp | C19: Un | D19: =1.5*D10 -> 33 | E19: =2*E10 -> 0 | F19: =+D19+E19 -> 33 | G19: 0.19 | H19: 3500 | I19: =+H19*F19 -> 115500 | J19: =+I19*(1+G19) -> 137445 | K19: =+H19/$D$2 -> 5303.0303 | L19: =+K19*F19 -> 175000 | M19: =+L19*(1+G19) -> 208250 | N19: Suministro de estructura | R19: 0 | S19: =+IF(R19=0,0,H19/R19) -> 0 | T19: =+IF(R19=0,0,K19/R19) -> 0 | U19: Inclinación paneles | V19: 123655 | W19: =+V19*1.19 -> 147149.45 | X19: 0.8 | Y19: =+V19*X19 -> 98924 | Z19: =+W19*X19 -> 117719.56
A20: 2.4 | B20: End Clamp | C20: Un | D20: =1*D10 -> 22 | E20: =0.94*E10 -> 0 | F20: =+D20+E20 -> 22 | G20: 0.19 | H20: 3500 | I20: =+H20*F20 -> 77000 | J20: =+I20*(1+G20) -> 91630 | K20: =+H20/$D$2 -> 5303.0303 | L20: =+K20*F20 -> 116666.67 | M20: =+L20*(1+G20) -> 138833.33 | N20: Suministro de estructura | R20: 0 | S20: =+IF(R20=0,0,H20/R20) -> 0 | T20: =+IF(R20=0,0,K20/R20) -> 0 | U20: Dado | V20: 50000 | W20: =+V20*1.19 -> 59500 | X20: =8/5 -> 1.6 | Y20: =+V20*X20 -> 80000 | Z20: =+W20*X20 -> 95200 | AD20: CT ANTES IVA | AE20: =+I26+I30+I41+I54+I83+I134 -> 2889947.5 | AG20: 6715625
A21: 2.5 | B21: Chapa de tierra (Mid clamp) | C21: Un | D21: =+D19 -> 33 | E21: =0.5*E10 -> 0 | F21: =+D21+E21 -> 33 | G21: 0.19 | H21: 700 | I21: =+H21*F21 -> 23100 | J21: =+I21*(1+G21) -> 27489 | K21: =+H21/$D$2 -> 1060.6061 | L21: =+K21*F21 -> 35000 | M21: =+L21*(1+G21) -> 41650 | N21: Suministro de estructura | R21: 0 | S21: =+IF(R21=0,0,H21/R21) -> 0 | T21: =+IF(R21=0,0,K21/R21) -> 0 | Y21: =+SUM(Y10:Y20) -> 268668.94 | Z21: =+SUM(Z10:Z20) -> 319716.04 | AD21: CT IVA INCLUIDO | AE21: =+J26+J30+J41+J54+J83+J134 -> 3439037.6 | AG21: 7991595
A22: 2.6 | B22: Ground Lug | C22: Un | D22: =0.5*D10 -> 11 | E22: =0.94*E10 -> 0 | F22: =0.94*F10 -> 20.68 | G22: 0.19 | H22: 4500 | I22: =+H22*F22 -> 93060 | J22: =+I22*(1+G22) -> 110741.4 | K22: =+H22/$D$2 -> 6818.1818 | L22: =+K22*F22 -> 141000 | M22: =+L22*(1+G22) -> 167790 | N22: Suministro de estructura | P22: =+H22/$C$180 -> 0.28224143 | Q22: =+K22/$C$180 -> 0.42763854 | R22: 0 | S22: =+IF(R22=0,0,H22/R22) -> 0 | T22: =+IF(R22=0,0,K22/R22) -> 0 | X22: Imprevisto | Y22: 1 | Z22: 1
A23: 2.7 | B23: L Foot 85 mm | C23: Un | D23: =2*D10 -> 44 | E23: =1.79*E10 -> 0 | F23: =+D23+E23 -> 44 | G23: 0.19 | H23: 15000 | I23: =+H23*F23 -> 660000 | J23: =+I23*(1+G23) -> 785400 | K23: =+H23/$D$2 -> 22727.273 | L23: =+K23*F23 -> 1000000 | M23: =+L23*(1+G23) -> 1190000 | N23: Suministro de estructura | R23: 0 | S23: =+IF(R23=0,0,H23/R23) -> 0 | T23: =+IF(R23=0,0,K23/R23) -> 0 | Y23: =+Y21*Y22 -> 268668.94 | Z23: =+Z21*Z22 -> 319716.04
A24: 2.8 | B24: Dados | C24: Un | D24: 0 | E24: =1.8*E11 -> 0 | F24: =+D24+E24 -> 0 | G24: 0.19 | H24: 25000 | I24: =+H24*F24 -> 0 | J24: =+I24*(1+G24) -> 0 | K24: =+H24/$D$2 -> 37878.788 | L24: =+K24*F24 -> 0 | M24: =+L24*(1+G24) -> 0 | N24: Suministro de estructura
A25: 2.9 | B25: Riel de soporte aluminio anodizado 4,7 | C25: Un | D25: 0 | E25: =0.61*E18 -> 0 | F25: =+D25+E25 -> 0 | G25: 0.19 | H25: 115141 | I25: =+H25*F25 -> 0 | J25: =+I25*(1+G25) -> 0 | K25: =+H25/$D$2 -> 174456.06 | L25: =+K25*F25 -> 0 | M25: =+L25*(1+G25) -> 0 | N25: Suministro de estructura
A26: 3 | B26: Protecciones en DC | G26: 0.19 | I26: =+SUM(I27:I29) -> 344000 | J26: =+SUM(J27:J29) -> 409360 | L26: =+SUM(L27:L29) -> 521212.12 | M26: =+SUM(M27:M29) -> 620242.42 | P26: =+I26+I30+I41+I47+I54+I83 -> 2839947.5 | R26: 0 | S26: =+IF(R26=0,0,H26/R26) -> 0 | T26: =+IF(R26=0,0,K26/R26) -> 0 | AA26: =+M26 -> 620242.42 | AB26: =+J26 -> 409360
A27: 3.1 | B27: TABLERO BIFÁSICO TIPO RIEL DIN 18 PUESTOS SOBREPONER | C27: Un | D27: 1 | E27: 0 | F27: =+D27+E27 -> 1 | G27: 0.19 | H27: 150000 | I27: =+H27*F27 -> 150000 | J27: =+I27*(1+G27) -> 178500 | K27: =+H27/$D$3 -> 227272.73 | L27: =+K27*D27 -> 227272.73 | M27: =+L27*(1+G27) -> 270454.55 | N27: Suministro de materiales y equipos | R27: 0 | S27: =+IF(R27=0,0,H27/R27) -> 0 | T27: =+IF(R27=0,0,K27/R27) -> 0
A28: 3.2 | B28: DPS SOLAR 1000V TIPO RIEL DIN | C28: Un | D28: 2 | E28: 0 | F28: =+D28+E28 -> 2 | G28: 0.19 | H28: 60000 | I28: =+H28*F28 -> 120000 | J28: =+I28*(1+G28) -> 142800 | K28: =+H28/$D$3 -> 90909.091 | L28: =+K28*D28 -> 181818.18 | M28: =+L28*(1+G28) -> 216363.64 | N28: Suministro de materiales y equipos | P28: =+H28/$C$180 -> 3.7632191 | Q28: =+K28/$C$180 -> 5.7018472 | R28: 0 | S28: =+IF(R28=0,0,H28/R28) -> 0 | T28: =+IF(R28=0,0,K28/R28) -> 0
A29: 3.3 | B29: MINIBREAKERS 32A | C29: Un | D29: 2 | E29: 0 | F29: =+D29+E29 -> 2 | G29: 0.19 | H29: 37000 | I29: =+H29*F29 -> 74000 | J29: =+I29*(1+G29) -> 88060 | K29: =+H29/$D$3 -> 56060.606 | L29: =+K29*D29 -> 112121.21 | M29: =+L29*(1+G29) -> 133424.24 | N29: Suministro de materiales y equipos | R29: 0 | S29: =+IF(R29=0,0,H29/R29) -> 0 | T29: =+IF(R29=0,0,K29/R29) -> 0
A30: 4 | B30: Protecciones en AC | G30: 0.19 | I30: =+SUM(I31:I40) -> 397400 | J30: =+SUM(J31:J40) -> 472906 | L30: =+SUM(L31:L40) -> 602121.21 | M30: =+SUM(M31:M40) -> 716524.24 | S30: =+IF(R30=0,0,H30/R30) -> 0 | T30: =+IF(R30=0,0,K30/R30) -> 0 | AA30: =+M30 -> 716524.24 | AB30: =+J30 -> 472906
A31: 4.1 | B31: TABLERO BIFÁSICO TIPO RIEL DIN 18 PUESTOS SOBREPONER | C31: Un | D31: 1 | E31: 0 | F31: =+D31+E31 -> 1 | G31: 0.19 | H31: 150000 | I31: =+H31*F31 -> 150000 | J31: =+I31*(1+G31) -> 178500 | K31: =+H31/$D$3 -> 227272.73 | L31: =+K31*F31 -> 227272.73 | M31: =+L31*(1+G31) -> 270454.55 | N31: Suministro de materiales y equipos
A32: 4.2 | B32: FUSIBLE Y PORTA FUSIBLE DE BATERIAS | C32: Un | D32: 0 | E32: 0 | F32: =+D32+E32 -> 0 | G32: 0.19 | H32: 195000 | I32: =+H32*F32 -> 0 | J32: =+I32*(1+G32) -> 0 | K32: =+H32/$D$3 -> 295454.55 | L32: =+K32*F32 -> 0 | M32: =+L32*(1+G32) -> 0 | N32: Suministro de materiales y equipos | O32: =+K32/$K$117 -> 4.7305985 | R32: 0 | S32: =+IF(R32=0,0,H32/R32) -> 0 | T32: =+IF(R32=0,0,K32/R32) -> 0
A33: 4.3 | B33: MINIBREAKER AC 2X32A TIPO RIEL DIN | C33: Un | D33: 0 | E33: 0 | F33: =+D33+E33 -> 0 | G33: 0.19 | H33: 21439 | I33: =+H33*F33 -> 0 | J33: =+I33*(1+G33) -> 0 | K33: =+H33/$D$3 -> 32483.333 | L33: =+K33*F33 -> 0 | M33: =+L33*(1+G33) -> 0 | N33: Suministro de materiales y equipos | P33: =+H33/$C$180 -> 1.3446609 | Q33: =+K33/$C$180 -> 2.037365 | R33: 0 | S33: =+IF(R33=0,0,H33/R33) -> 0 | T33: =+IF(R33=0,0,K33/R33) -> 0
A34: 4.4 | B34: MINIBREAKER AC3X50A TIPO RIEL DIN | C34: Un | D34: 1 | E34: 0 | F34: =+D34+E34 -> 1 | G34: 0.19 | H34: 19000 | I34: =+H34*F34 -> 19000 | J34: =+I34*(1+G34) -> 22610 | K34: =+H34/$D$3 -> 28787.879 | L34: =+K34*F34 -> 28787.879 | M34: =+L34*(1+G34) -> 34257.576 | N34: Suministro de materiales y equipos | R34: 0 | S34: =+IF(R34=0,0,H34/R34) -> 0 | T34: =+IF(R34=0,0,K34/R34) -> 0
A35: 4.5 | B35: MINIBREAKER AC 3x200A TIPO RIEL DIN | C35: Un | D35: 0 | E35: 0 | F35: =+D35+E35 -> 0 | G35: 0.19 | H35: 396000 | I35: =+H35*F35 -> 0 | J35: =+I35*(1+G35) -> 0 | K35: =+H35/$D$3 -> 600000 | L35: =+K35*F35 -> 0 | M35: =+L35*(1+G35) -> 0 | N35: Suministro de materiales y equipos | R35: 0 | S35: =+IF(R35=0,0,H35/R35) -> 0 | T35: =+IF(R35=0,0,K35/R35) -> 0
A36: 4.6 | B36: DPS CLASE 2 TIPO RIEL DIN AC | C36: Un | D36: 1 | E36: 0 | F36: =+D36+E36 -> 1 | G36: 0.19 | H36: 147000 | I36: =+H36*F36 -> 147000 | J36: =+I36*(1+G36) -> 174930 | K36: =+H36/$D$3 -> 222727.27 | L36: =+K36*F36 -> 222727.27 | M36: =+L36*(1+G36) -> 265045.45 | N36: Suministro de materiales y equipos | O36: =+K36/$K$117 -> 3.5661435 | R36: 0 | S36: =+IF(R36=0,0,H36/R36) -> 0 | T36: =+IF(R36=0,0,K36/R36) -> 0
A37: 4.7 | B37: PROTECCIÓN ENCHUFABLE 2X32A | C37: Un | D37: 0 | E37: 0 | F37: =+D37+E37 -> 0 | G37: 0.19 | H37: 58824 | I37: =+H37*F37 -> 0 | J37: =+I37*(1+G37) -> 0 | K37: =+H37/$D$3 -> 89127.273 | L37: =+K37*F37 -> 0 | M37: =+L37*(1+G37) -> 0 | N37: Suministro de materiales y equipos | R37: 0 | S37: =+IF(R37=0,0,H37/R37) -> 0 | T37: =+IF(R37=0,0,K37/R37) -> 0
A38: 4.8 | B38: PROTECCIÓN ENCHUFABLE 3X50A | C38: Un | D38: 1 | E38: 0 | F38: =+D38+E38 -> 1 | G38: 0.19 | H38: 50000 | I38: =+H38*F38 -> 50000 | J38: =+I38*(1+G38) -> 59500 | K38: =+H38/$D$3 -> 75757.576 | L38: =+K38*F38 -> 75757.576 | M38: =+L38*(1+G38) -> 90151.515 | N38: Suministro de materiales y equipos | R38: 0 | S38: =+IF(R38=0,0,H38/R38) -> 0 | T38: =+IF(R38=0,0,K38/R38) -> 0
A39: 4.9 | B39: TABLERO GENERAL BAJA TENSION 24 CTOS TIPO ENCHUFABLE (Incluye 4 breaker 2x20 + 8 1x16 + 2 1x20) | C39: Un | D39: 0 | E39: 0 | F39: 0 | G39: 0.19 | I39: =+H39*F39 -> 0 | J39: =+I39*(1+G39) -> 0 | K39: =+H39/$D$3 -> 0 | L39: =+K39*F39 -> 0 | M39: =+L39*(1+G39) -> 0 | N39: Suministro de materiales y equipos | R39: 0 | S39: =+IF(R39=0,0,H39/R39) -> 0 | T39: =+IF(R39=0,0,K39/R39) -> 0
A40: 4.10 | B40: MINIBREAKER DE 1X2A TIPO RIEL DIN | C40: Un | D40: 1 | E40: 0 | F40: =+D40+E40 -> 1 | G40: 0.19 | H40: 31400 | I40: =+H40*F40 -> 31400 | J40: =+I40*(1+G40) -> 37366 | K40: =+H40/$D$3 -> 47575.758 | L40: =+K40*F40 -> 47575.758 | M40: =+L40*(1+G40) -> 56615.152 | N40: Suministro de materiales y equipos | R40: 0 | S40: =+IF(R40=0,0,H40/R40) -> 0 | T40: =+IF(R40=0,0,K40/R40) -> 0
A41: 5 | B41: Canalizaciones - registros | I41: =+SUM(I42:I46) -> 127300 | J41: =+SUM(J42:J46) -> 151487 | K41: 115842.86 | L41: =+SUM(L42:L46) -> 192878.79 | M41: =+SUM(M42:M46) -> 229525.76 | R41: 0 | S41: =+IF(R41=0,0,H41/R41) -> 0 | T41: =+IF(R41=0,0,K41/R41) -> 0 | AA41: =+M41 -> 229525.76 | AB41: =+J41 -> 151487
A42: 5.1 | B42: CAJA DE PASO PLASTICA 30*30*15 | C42: Un | D42: 0 | E42: 0 | F42: =+D42+E42 -> 0 | G42: 0.19 | H42: 47899 | I42: =+H42*F42 -> 0 | J42: =+I42*(1+G42) -> 0 | K42: =+H42/$D$3 -> 72574.242 | L42: =+K42*F42 -> 0 | M42: =+L42*(1+G42) -> 0 | N42: Suministro de materiales y equipos | R42: 0 | S42: =+IF(R42=0,0,H42/R42) -> 0 | T42: =+IF(R42=0,0,K42/R42) -> 0
A43: 5.2 | B43: CAJA DE PASO PLASTICA 20*15 | C43: mt | D43: 2 | E43: 0 | F43: =+D43+E43 -> 2 | G43: 0.19 | H43: 35000 | I43: =+H43*F43 -> 70000 | J43: =+I43*(1+G43) -> 83300 | K43: =+H43/$D$3 -> 53030.303 | L43: =+K43*F43 -> 106060.61 | M43: =+L43*(1+G43) -> 126212.12 | N43: Suministro de materiales y equipos | R43: 0 | S43: =+IF(R43=0,0,H43/R43) -> 0 | T43: =+IF(R43=0,0,K43/R43) -> 0
A44: 5.3 | B44: CAJA RAWELT 4X4 DE 1" | C44: Un | D44: 2 | E44: 0 | F44: =+D44+E44 -> 2 | G44: 0.19 | H44: 26400 | I44: =+H44*F44 -> 52800 | J44: =+I44*(1+G44) -> 62832 | K44: =+H44/$D$3 -> 40000 | L44: =+K44*F44 -> 80000 | M44: =+L44*(1+G44) -> 95200 | N44: Suministro de materiales y equipos | R44: 0 | S44: =+IF(R44=0,0,H44/R44) -> 0 | T44: =+IF(R44=0,0,K44/R44) -> 0
A45: 5.4 | B45: PRENSA ESTOPA DE 1/2" | C45: Un | D45: 2 | E45: 0 | F45: =+D45+E45 -> 2 | G45: 0.19 | H45: 2250 | I45: =+H45*F45 -> 4500 | J45: =+I45*(1+G45) -> 5355 | K45: =+H45/$D$3 -> 3409.0909 | L45: =+K45*F45 -> 6818.1818 | M45: =+L45*(1+G45) -> 8113.6364 | N45: Suministro de materiales y equipos | P45: =+H45/$C$180 -> 0.14112072 | Q45: =+K45/$C$180 -> 0.21381927 | R45: 0 | S45: =+IF(R45=0,0,H45/R45) -> 0 | T45: =+IF(R45=0,0,K45/R45) -> 0
A46: 5.5 | B46: PRENSA ESTOPA DE 3/4" | C46: Un | D46: 0 | E46: 0 | F46: =+D46+E46 -> 0 | G46: 0.19 | H46: 3300 | I46: =+H46*F46 -> 0 | J46: =+I46*(1+G46) -> 0 | K46: =+H46/$D$3 -> 5000 | L46: =+K46*F46 -> 0 | M46: =+L46*(1+G46) -> 0 | N46: Suministro de materiales y equipos | O46: =+K46/$K$117 -> 0.080056282 | R46: 0 | S46: =+IF(R46=0,0,H46/R46) -> 0 | T46: =+IF(R46=0,0,K46/R46) -> 0
A47: 6 | B47: Sistema de puesta a tierra | I47: =+SUM(I48:I53) -> 0 | J47: =+SUM(J48:J53) -> 0 | L47: =+SUM(L48:L53) -> 0 | M47: =+SUM(M48:M53) -> 0 | R47: 0 | S47: =+IF(R47=0,0,H47/R47) -> 0 | T47: =+IF(R47=0,0,K47/R47) -> 0
A48: 6.1 | B48: Varilla Coperweld de tierra | C48: Un | D48: 0 | F48: =+D48+E48 -> 0 | G48: 0.19 | H48: 96000 | I48: =+H48*F48 -> 0 | J48: =+I48*(1+G48) -> 0 | K48: =+H48/$D$3 -> 145454.55 | L48: =+K48*F48 -> 0 | M48: =+L48*(1+G48) -> 0 | N48: Suministro de materiales y equipos | P48: =+H48/$C$180 -> 6.0211506 | Q48: =+K48/$C$180 -> 9.1229554 | R48: 0 | S48: =+IF(R48=0,0,H48/R48) -> 0 | T48: =+IF(R48=0,0,K48/R48) -> 0
A49: 6.2 | B49: Perno varilla - cable | C49: Un | D49: 0 | F49: =+D49+E49 -> 0 | G49: 0.19 | H49: 14000 | I49: =+H49*F49 -> 0 | J49: =+I49*(1+G49) -> 0 | K49: =+H49/$D$3 -> 21212.121 | L49: =+K49*F49 -> 0 | M49: =+L49*(1+G49) -> 0 | N49: Suministro de materiales y equipos | O49: =+K49/$K$117 -> 0.33963271 | R49: 0 | S49: =+IF(R49=0,0,H49/R49) -> 0 | T49: =+IF(R49=0,0,K49/R49) -> 0
A50: 6.3 | B50: Cable No. 8 desnudo | C50: ml | D50: 0 | F50: =+D50+E50 -> 0 | G50: 0.19 | H50: =133994/1.19/20 -> 5630 | I50: =+H50*F50 -> 0 | J50: =+I50*(1+G50) -> 0 | K50: =+H50/$D$3 -> 8530.303 | L50: =+K50*F50 -> 0 | M50: =+L50*(1+G50) -> 0 | N50: Suministro de materiales y equipos | P50: =+H50/$C$180 -> 0.35311539 | Q50: =+K50/$C$180 -> 0.53502332 | R50: 0 | S50: =+IF(R50=0,0,H50/R50) -> 0 | T50: =+IF(R50=0,0,K50/R50) -> 0
A51: 6.4 | B51: registro de tierra de 30 x 30 | C51: Un | D51: 0 | F51: =+D51+E51 -> 0 | G51: 0.19 | H51: 101031 | I51: =+H51*F51 -> 0 | J51: =+I51*(1+G51) -> 0 | K51: =+H51/$D$3 -> 153077.27 | L51: =+K51*F51 -> 0 | M51: =+L51*(1+G51) -> 0 | N51: Suministro de materiales y equipos | R51: 0 | S51: =+IF(R51=0,0,H51/R51) -> 0 | T51: =+IF(R51=0,0,K51/R51) -> 0
A52: 6.5 | B52: Suelo artificial (5 kilos) | C52: Kg | D52: 0 | F52: =+D52+E52 -> 0 | G52: 0.19 | H52: 12000 | I52: =+H52*F52 -> 0 | J52: =+I52*(1+G52) -> 0 | K52: =+H52/$D$3 -> 18181.818 | L52: =+K52*F52 -> 0 | M52: =+L52*(1+G52) -> 0 | N52: Suministro de materiales y equipos | R52: 0 | S52: =+IF(R52=0,0,H52/R52) -> 0 | T52: =+IF(R52=0,0,K52/R52) -> 0
A53: 6.6 | B53: Tuberia SCH 40 1/2" 3 metros | C53: Un | D53: 0 | F53: =+D53+E53 -> 0 | G53: 0.19 | H53: 12500 | I53: =+H53*F53 -> 0 | J53: =+I53*(1+G53) -> 0 | K53: =+H53/$D$3 -> 18939.394 | L53: =+K53*F53 -> 0 | M53: =+L53*(1+G53) -> 0 | N53: Suministro de materiales y equipos | R53: 0 | S53: =+IF(R53=0,0,H53/R53) -> 0 | T53: =+IF(R53=0,0,K53/R53) -> 0
A54: 6 | B54: Cable AC - DC | I54: =+SUM(I55:I82) -> 1251183 | J54: =+SUM(J55:J82) -> 1488907.8 | K54: 148081.43 | L54: =+SUM(L55:L82) -> 1895731.8 | M54: =+SUM(M55:M82) -> 2255920.9 | R54: 0 | S54: =+IF(R54=0,0,H54/R54) -> 0 | T54: =+IF(R54=0,0,K54/R54) -> 0 | AA54: =+M54 -> 2255920.9 | AB54: =+J54 -> 1488907.8
A55: 6.1 | B55: Suministro cable fotovoltaico 4 mm2 color rojo | C55: mt | D55: =+D10*3 -> 66 | E55: =((3.5*E10)) -> 0 | F55: =+D55+E55 -> 66 | G55: 0.19 | H55: 3500 | I55: =+H55*F55 -> 231000 | J55: =+I55*(1+G55) -> 274890 | K55: =+H55/$D$3 -> 5303.0303 | L55: =+K55*F55 -> 350000 | M55: =+L55*(1+G55) -> 416500 | N55: Suministro de materiales y equipos | P55: =+H55/$C$180 -> 0.21952112 | Q55: =+K55/$C$180 -> 0.33260775 | R55: 0 | S55: =+IF(R55=0,0,H55/R55) -> 0 | T55: =+IF(R55=0,0,K55/R55) -> 0
A56: 6.2 | B56: Suministro cable fotovoltaico 4 mm2 color negro | C56: mt | D56: =+D10*3 -> 66 | E56: =((3.5*E10)) -> 0 | F56: =+D56+E56 -> 66 | G56: 0.19 | H56: 3500 | I56: =+H56*F56 -> 231000 | J56: =+I56*(1+G56) -> 274890 | K56: =+H56/$D$3 -> 5303.0303 | L56: =+K56*F56 -> 350000 | M56: =+L56*(1+G56) -> 416500 | N56: Suministro de materiales y equipos | R56: 0 | S56: =+IF(R56=0,0,H56/R56) -> 0 | T56: =+IF(R56=0,0,K56/R56) -> 0
A57: 6.3 | B57: JUEGO TERMINALES MC4 4 mm2 | C57: Un | D57: 8 | E57: =+E29 -> 0 | F57: =+D57+E57 -> 8 | G57: 0.19 | H57: 5042 | I57: =+H57*F57 -> 40336 | J57: =+I57*(1+G57) -> 47999.84 | K57: =+H57/$D$3 -> 7639.3939 | L57: =+K57*F57 -> 61115.152 | M57: =+L57*(1+G57) -> 72727.03 | N57: Suministro de materiales y equipos | R57: 0 | S57: =+IF(R57=0,0,H57/R57) -> 0 | T57: =+IF(R57=0,0,K57/R57) -> 0
A58: 6.4 | B58: Cable Cu # 14 AWG THHN/THWN-2 | C58: mt | D58: 0 | F58: =+D58+E58 -> 0 | G58: 0.19 | I58: =+H58*F58 -> 0 | J58: =+I58*(1+G58) -> 0 | K58: =+H58/$D$3 -> 0 | L58: =+K58*F58 -> 0 | M58: =+L58*(1+G58) -> 0 | N58: Suministro de materiales y equipos | P58: =+H58/$C$180 -> 0 | Q58: =+K58/$C$180 -> 0 | R58: 0 | S58: =+IF(R58=0,0,H58/R58) -> 0 | T58: =+IF(R58=0,0,K58/R58) -> 0
A59: 6.5 | B59: Cable Cu # 12 AWG THHN/THWN-2 | C59: mt | D59: 0 | F59: =+D59+E59 -> 0 | G59: 0.19 | H59: 0 | I59: =+H59*F59 -> 0 | J59: =+I59*(1+G59) -> 0 | K59: =+H59/$D$3 -> 0 | L59: =+K59*F59 -> 0 | M59: =+L59*(1+G59) -> 0 | N59: Suministro de materiales y equipos | R59: 0 | S59: =+IF(R59=0,0,H59/R59) -> 0 | T59: =+IF(R59=0,0,K59/R59) -> 0
A60: 6.6 | B60: Cable Cu # 10 AWG THHN/THWN-2 | C60: mt | D60: 45 | E60: 0 | F60: =+D60+E60 -> 45 | G60: 0.19 | H60: 3781 | I60: =+H60*F60 -> 170145 | J60: =+I60*(1+G60) -> 202472.55 | K60: =+H60/$D$3 -> 5728.7879 | L60: =+K60*F60 -> 257795.45 | M60: =+L60*(1+G60) -> 306776.59 | N60: Suministro de materiales y equipos | R60: 0 | S60: =+IF(R60=0,0,H60/R60) -> 0 | T60: =+IF(R60=0,0,K60/R60) -> 0
A61: 6.7 | B61: Cable Cu # 8 AWG THHN/THWN-2 | C61: mt | D61: =10*3+15 -> 45 | E61: 0 | F61: =+D61+E61 -> 45 | G61: 0.19 | H61: 5630 | I61: =+H61*F61 -> 253350 | J61: =+I61*(1+G61) -> 301486.5 | K61: =+H61/$D$3 -> 8530.303 | L61: =+K61*F61 -> 383863.64 | M61: =+L61*(1+G61) -> 456797.73 | N61: Suministro de materiales y equipos | R61: 0 | S61: =+IF(R61=0,0,H61/R61) -> 0 | T61: =+IF(R61=0,0,K61/R61) -> 0
A62: 6.8 | B62: Cable Cu # 6 AWG THHN/THWN-2 | C62: mt | D62: 0 | E62: 0 | F62: =+D62+E62 -> 0 | G62: 0.19 | H62: 7741 | I62: =+H62*F62 -> 0 | J62: =+I62*(1+G62) -> 0 | K62: =+H62/$D$3 -> 11728.788 | L62: =+K62*F62 -> 0 | M62: =+L62*(1+G62) -> 0 | N62: Suministro de materiales y equipos | R62: 0 | S62: =+IF(R62=0,0,H62/R62) -> 0 | T62: =+IF(R62=0,0,K62/R62) -> 0
A63: 6.9 | B63: Cable Cu # 4 AWG THHN/THWN-2 Tierra | C63: mt | D63: 0 | E63: 0 | F63: =+D63+E63 -> 0 | G63: 0.19 | I63: =+H63*F63 -> 0 | J63: =+I63*(1+G63) -> 0 | K63: =+H63/$D$3 -> 0 | L63: =+K63*F63 -> 0 | M63: =+L63*(1+G63) -> 0 | N63: Suministro de materiales y equipos | R63: 0 | S63: =+IF(R63=0,0,H63/R63) -> 0 | T63: =+IF(R63=0,0,K63/R63) -> 0
A64: 6.10 | B64: Cable Cu # 2 AWG THHN/THWN-2 | C64: mt | D64: 0 | E64: 0 | F64: =+D64+E64 -> 0 | G64: 0.19 | H64: 18100 | I64: =+H64*F64 -> 0 | J64: =+I64*(1+G64) -> 0 | K64: =+H64/$D$3 -> 27424.242 | L64: =+K64*F64 -> 0 | M64: =+L64*(1+G64) -> 0 | N64: Suministro de materiales y equipos | P64: =+H64/$C$180 -> 1.1352378 | Q64: =+K64/$C$180 -> 1.7200572 | R64: 0 | S64: =+IF(R64=0,0,H64/R64) -> 0 | T64: =+IF(R64=0,0,K64/R64) -> 0 | V64: Simulación Davivienda
A65: 6.11 | B65: Cable Cu # 1/0 AWG THHN/THWN-2 | C65: mt | D65: 0 | E65: 0 | F65: =+D65+E65 -> 0 | G65: 0.19 | H65: 0 | I65: =+H65*F65 -> 0 | J65: =+I65*(1+G65) -> 0 | K65: =+H65/$D$3 -> 0 | L65: =+K65*F65 -> 0 | M65: =+L65*(1+G65) -> 0 | N65: Suministro de materiales y equipos | R65: 0 | S65: =+IF(R65=0,0,H65/R65) -> 0 | T65: =+IF(R65=0,0,K65/R65) -> 0
A66: 6.12 | B66: Cable Cu # 2/0 AWG THHN/THWN-2 | C66: mt | D66: 0 | E66: 0 | F66: =+D66+E66 -> 0 | G66: 0.19 | I66: =+H66*F66 -> 0 | J66: =+I66*(1+G66) -> 0 | K66: =+H66/$D$3 -> 0 | L66: =+K66*F66 -> 0 | M66: =+L66*(1+G66) -> 0 | N66: Suministro de materiales y equipos | R66: 0 | S66: =+IF(R66=0,0,H66/R66) -> 0 | T66: =+IF(R66=0,0,K66/R66) -> 0
A67: 6.13 | B67: Cable Cu # 250 AWG THHN/THWN-2 | C67: mt | D67: 0 | E67: 0 | F67: =+D67+E67 -> 0 | G67: 0.19 | H67: 95000 | I67: =+H67*F67 -> 0 | J67: =+I67*(1+G67) -> 0 | K67: =+H67/$D$3 -> 143939.39 | L67: =+K67*F67 -> 0 | M67: =+L67*(1+G67) -> 0 | N67: Suministro de materiales y equipos | R67: 0 | S67: =+IF(R67=0,0,H67/R67) -> 0 | T67: =+IF(R67=0,0,K67/R67) -> 0
A68: 6.14 | B68: Cable Cu # 10 AWG THHN/THWN-2 Tierra | C68: mt | D68: =+D55 -> 66 | E68: 0 | F68: =+D68+E68 -> 66 | G68: 0.19 | H68: 3781 | I68: =+H68*F68 -> 249546 | J68: =+I68*(1+G68) -> 296959.74 | K68: =+H68/$D$3 -> 5728.7879 | L68: =+K68*F68 -> 378100 | M68: =+L68*(1+G68) -> 449939 | N68: Suministro de materiales y equipos | R68: 0 | S68: =+IF(R68=0,0,H68/R68) -> 0 | T68: =+IF(R68=0,0,K68/R68) -> 0
A69: 6.15 | B69: Cable utp Cap 5 | C69: mt | D69: 10 | E69: 0 | F69: =+D69+E69 -> 10 | G69: 0.19 | H69: 1500 | I69: =+H69*F69 -> 15000 | J69: =+I69*(1+G69) -> 17850 | K69: =+H69/$D$3 -> 2272.7273 | L69: =+K69*F69 -> 22727.273 | M69: =+L69*(1+G69) -> 27045.455 | N69: Suministro de materiales y equipos | R69: 0 | S69: =+IF(R69=0,0,H69/R69) -> 0 | T69: =+IF(R69=0,0,K69/R69) -> 0
A70: 6.16 | B70: CABLE SOLDADOR No. 2 | C70: mt | D70: 0 | E70: 0 | F70: =+D70+E70 -> 0 | G70: 0.19 | H70: 25704 | I70: =+H70*F70 -> 0 | J70: =+I70*(1+G70) -> 0 | K70: =+H70/$D$3 -> 38945.455 | L70: =+K70*F70 -> 0 | M70: =+L70*(1+G70) -> 0 | N70: Suministro de materiales y equipos | R70: 0 | S70: =+IF(R70=0,0,H70/R70) -> 0 | T70: =+IF(R70=0,0,K70/R70) -> 0
A71: 6.17 | B71: Cable 2x 22 apantallado | C71: mt | D71: 0 | E71: 0 | F71: =+D71+E71 -> 0 | G71: 0.19 | H71: =(161840/1.19)/80 -> 1700 | I71: =+H71*F71 -> 0 | J71: =+I71*(1+G71) -> 0 | K71: =+H71/$D$3 -> 2575.7576 | L71: =+K71*F71 -> 0 | M71: =+L71*(1+G71) -> 0 | N71: Suministro de materiales y equipos | R71: 0 | S71: =+IF(R71=0,0,H71/R71) -> 0 | T71: =+IF(R71=0,0,K71/R71) -> 0
A72: 6.18 | B72: Cable No. 18 negro | C72: mt | D72: 30 | E72: 0 | F72: =+D72+E72 -> 30 | G72: 0.19 | H72: 1785 | I72: =+H72*F72 -> 53550 | J72: =+I72*(1+G72) -> 63724.5 | K72: =+H72/$D$3 -> 2704.5455 | L72: =+K72*F72 -> 81136.364 | M72: =+L72*(1+G72) -> 96552.273 | N72: Suministro de materiales y equipos | R72: 0 | S72: =+IF(R72=0,0,H72/R72) -> 0 | T72: =+IF(R72=0,0,K72/R72) -> 0
A73: 6.19 | B73: BORNAS CU 14 AWG | C73: Un | D73: 0 | F73: =+D73+E73 -> 0 | G73: 0.19 | H73: 2000 | I73: =+H73*F73 -> 0 | J73: =+I73*(1+G73) -> 0 | K73: =+H73/$D$3 -> 3030.303 | L73: =+K73*F73 -> 0 | M73: =+L73*(1+G73) -> 0 | N73: Suministro de materiales y equipos | R73: 0 | S73: =+IF(R73=0,0,H73/R73) -> 0 | T73: =+IF(R73=0,0,K73/R73) -> 0
A74: 6.20 | B74: BORNAS CU 12 AWG | C74: Un | D74: 0 | F74: =+D74+E74 -> 0 | G74: 0.19 | H74: 0 | I74: =+H74*F74 -> 0 | J74: =+I74*(1+G74) -> 0 | K74: =+H74/$D$3 -> 0 | L74: =+K74*F74 -> 0 | M74: =+L74*(1+G74) -> 0 | N74: Suministro de materiales y equipos | O74: =+K74/$K$117 -> 0 | R74: 0 | S74: =+IF(R74=0,0,H74/R74) -> 0 | T74: =+IF(R74=0,0,K74/R74) -> 0
A75: 6.21 | B75: BORNAS CU 10 AWG | C75: Un | D75: 2 | E75: 0 | F75: =+D75+E75 -> 2 | G75: 0.19 | H75: 1428 | I75: =+H75*F75 -> 2856 | J75: =+I75*(1+G75) -> 3398.64 | K75: =+H75/$D$3 -> 2163.6364 | L75: =+K75*F75 -> 4327.2727 | M75: =+L75*(1+G75) -> 5149.4545 | N75: Suministro de materiales y equipos | R75: 0 | S75: =+IF(R75=0,0,H75/R75) -> 0 | T75: =+IF(R75=0,0,K75/R75) -> 0
A76: 6.22 | B76: BORNAS CU 8 AWG | C76: Un | D76: 0 | E76: 0 | F76: =+D76+E76 -> 0 | G76: 0.19 | H76: 1400 | I76: =+H76*F76 -> 0 | J76: =+I76*(1+G76) -> 0 | K76: =+H76/$D$3 -> 2121.2121 | L76: =+K76*F76 -> 0 | M76: =+L76*(1+G76) -> 0 | N76: Suministro de materiales y equipos | R76: 0 | S76: =+IF(R76=0,0,H76/R76) -> 0 | T76: =+IF(R76=0,0,K76/R76) -> 0
A77: 6.23 | B77: BORNAS CU 6 AWG | C77: Un | D77: 2 | E77: 0 | F77: =+D77+E77 -> 2 | G77: 0.19 | H77: 2200 | I77: =+H77*F77 -> 4400 | J77: =+I77*(1+G77) -> 5236 | K77: =+H77/$D$3 -> 3333.3333 | L77: =+K77*F77 -> 6666.6667 | M77: =+L77*(1+G77) -> 7933.3333 | N77: Suministro de materiales y equipos | R77: 0 | S77: =+IF(R77=0,0,H77/R77) -> 0 | T77: =+IF(R77=0,0,K77/R77) -> 0
A78: 6.24 | B78: BORNAS CU 4 AWG | C78: Un | D78: 0 | E78: 0 | F78: =+D78+E78 -> 0 | G78: 0.19 | H78: 4600 | I78: =+H78*F78 -> 0 | J78: =+I78*(1+G78) -> 0 | K78: =+H78/$D$3 -> 6969.697 | L78: =+K78*F78 -> 0 | M78: =+L78*(1+G78) -> 0 | N78: Suministro de materiales y equipos | R78: 0 | S78: =+IF(R78=0,0,H78/R78) -> 0 | T78: =+IF(R78=0,0,K78/R78) -> 0
A79: 6.25 | B79: BORNAS CU 2 AWG | C79: Un | D79: 0 | E79: 0 | F79: =+D79+E79 -> 0 | G79: 0.19 | H79: 3500 | I79: =+H79*F79 -> 0 | J79: =+I79*(1+G79) -> 0 | K79: =+H79/$D$3 -> 5303.0303 | L79: =+K79*F79 -> 0 | M79: =+L79*(1+G79) -> 0 | N79: Suministro de materiales y equipos | R79: 0 | S79: =+IF(R79=0,0,H79/R79) -> 0 | T79: =+IF(R79=0,0,K79/R79) -> 0
A80: 6.26 | B80: BORNAS CU 1/0 AWG | C80: Un | D80: 0 | E80: 0 | F80: =+D80+E80 -> 0 | G80: 0.19 | I80: =+H80*F80 -> 0 | J80: =+I80*(1+G80) -> 0 | K80: =+H80/$D$3 -> 0 | L80: =+K80*F80 -> 0 | M80: =+L80*(1+G80) -> 0 | N80: Suministro de materiales y equipos | R80: 0 | S80: =+IF(R80=0,0,H80/R80) -> 0 | T80: =+IF(R80=0,0,K80/R80) -> 0
A81: 6.27 | B81: BORNAS CU 2/0 AWG | C81: Un | D81: 0 | E81: 0 | F81: =+D81+E81 -> 0 | G81: 0.19 | I81: =+H81*F81 -> 0 | J81: =+I81*(1+G81) -> 0 | K81: =+H81/$D$3 -> 0 | L81: =+K81*F81 -> 0 | M81: =+L81*(1+G81) -> 0 | N81: Suministro de materiales y equipos | R81: 0 | S81: =+IF(R81=0,0,H81/R81) -> 0 | T81: =+IF(R81=0,0,K81/R81) -> 0
A82: 6.28 | B82: BORNAS CU 4/0 AWG | C82: Un | D82: 0 | E82: 0 | F82: =+D82+E82 -> 0 | G82: 0.19 | H82: 4600 | I82: =+H82*F82 -> 0 | J82: =+I82*(1+G82) -> 0 | K82: =+H82/$D$3 -> 6969.697 | L82: =+K82*F82 -> 0 | M82: =+L82*(1+G82) -> 0 | N82: Suministro de materiales y equipos | R82: 0 | S82: =+IF(R82=0,0,H82/R82) -> 0 | T82: =+IF(R82=0,0,K82/R82) -> 0
A83: 7 | B83: Tuberia - Ductos y Accesorios | I83: =+SUM(I84:I133) -> 720064.54 | J83: =+SUM(J84:J133) -> 856876.8 | K83: 345862.86 | L83: =+SUM(L84:L133) -> 1091006.9 | M83: =+SUM(M84:M133) -> 1298298.2 | R83: 0 | S83: =+IF(R83=0,0,H83/R83) -> 0 | T83: =+IF(R83=0,0,K83/R83) -> 0 | AA83: =+M83 -> 1298298.2 | AB83: =+J83 -> 856876.8
A84: 7.1 | B84: CORAZA METÁLICA 1" | C84: mt | D84: =0.2*D10 -> 4.4 | F84: =+D84+E84 -> 4.4 | G84: 0.19 | H84: =280800/24/1.19 -> 9831.9328 | I84: =+H84*F84 -> 43260.504 | J84: =+I84*(1+G84) -> 51480 | K84: =+H84/$D$3 -> 14896.868 | L84: =+K84*F84 -> 65546.218 | M84: =+L84*(1+G84) -> 78000 | N84: Suministro de materiales y equipos | R84: 0 | S84: =+IF(R84=0,0,H84/R84) -> 0 | T84: =+IF(R84=0,0,K84/R84) -> 0
A85: 7.2 | B85: CONECTORES RECTOS PARA CORAZA 1" | C85: mt | D85: =+D84 -> 4.4 | F85: =+D85+E85 -> 4.4 | G85: 0.19 | H85: =211728/24/1.19 -> 7413.4454 | I85: =+H85*F85 -> 32619.16 | J85: =+I85*(1+G85) -> 38816.8 | K85: =+H85/$D$3 -> 11232.493 | L85: =+K85*F85 -> 49422.969 | M85: =+L85*(1+G85) -> 58813.333 | N85: Suministro de materiales y equipos | R85: 0 | S85: =+IF(R85=0,0,H85/R85) -> 0 | T85: =+IF(R85=0,0,K85/R85) -> 0
A86: 7.3 | B86: CORAZA METÁLICA 1" 1/2 | C86: mt | D86: 0 | E86: =+E10*3.5 -> 0 | F86: =+D86+E86 -> 0 | G86: 0.19 | H86: 14900 | I86: =+H86*F86 -> 0 | J86: =+I86*(1+G86) -> 0 | K86: =+H86/$D$3 -> 22575.758 | L86: =+K86*F86 -> 0 | M86: =+L86*(1+G86) -> 0 | N86: Suministro de materiales y equipos | R86: 0 | S86: =+IF(R86=0,0,H86/R86) -> 0 | T86: =+IF(R86=0,0,K86/R86) -> 0
A87: 7.4 | B87: CONECTORES RECTOS PARA CORAZA 1" 1/2 | C87: mt | D87: 0 | E87: =+E86/3 -> 0 | F87: =+D87+E87 -> 0 | G87: 0.19 | H87: 13550 | I87: =+H87*F87 -> 0 | J87: =+I87*(1+G87) -> 0 | K87: =+H87/$D$3 -> 20530.303 | L87: =+K87*F87 -> 0 | M87: =+L87*(1+G87) -> 0 | N87: Suministro de materiales y equipos | R87: 0 | S87: =+IF(R87=0,0,H87/R87) -> 0 | T87: =+IF(R87=0,0,K87/R87) -> 0
A88: 7.5 | B88: CORAZA METÁLICA 2" | C88: mt | D88: 0 | F88: =+D88+E88 -> 0 | G88: 0.19 | H88: 19450 | I88: =+H88*F88 -> 0 | J88: =+I88*(1+G88) -> 0 | K88: =+H88/$D$3 -> 29469.697 | L88: =+K88*F88 -> 0 | M88: =+L88*(1+G88) -> 0 | N88: Suministro de materiales y equipos | R88: 0 | S88: =+IF(R88=0,0,H88/R88) -> 0 | T88: =+IF(R88=0,0,K88/R88) -> 0
A89: 7.6 | B89: CONECTORES RECTOS PARA CORAZA 2" | C89: Un | D89: 0 | F89: =+D89+E89 -> 0 | G89: 0.19 | H89: 13150 | I89: =+H89*F89 -> 0 | J89: =+I89*(1+G89) -> 0 | K89: =+H89/$D$3 -> 19924.242 | L89: =+K89*F89 -> 0 | M89: =+L89*(1+G89) -> 0 | N89: Suministro de materiales y equipos | R89: 0 | S89: =+IF(R89=0,0,H89/R89) -> 0 | T89: =+IF(R89=0,0,K89/R89) -> 0
A90: 7.7 | B90: TUBERÍA IMC 1" x 3metros | C90: Un | D90: 4 | E90: 0 | F90: =+D90+E90 -> 4 | G90: 0.19 | H90: =78450/1.19 -> 65924.37 | I90: =+H90*F90 -> 263697.48 | J90: =+I90*(1+G90) -> 313800 | K90: =+H90/$D$3 -> 99885.409 | L90: =+K90*F90 -> 399541.63 | M90: =+L90*(1+G90) -> 475454.55 | N90: Suministro de materiales y equipos | R90: 0 | S90: =+IF(R90=0,0,H90/R90) -> 0 | T90: =+IF(R90=0,0,K90/R90) -> 0
A91: 7.8 | B91: CURVA IMC 1" | C91: Un | D91: 4 | E91: 0 | F91: =+D91+E91 -> 4 | G91: 0.19 | H91: =17400/1.19 -> 14621.849 | I91: =+H91*F91 -> 58487.395 | J91: =+I91*(1+G91) -> 69600 | K91: =+H91/$D$3 -> 22154.316 | L91: =+K91*F91 -> 88617.265 | M91: =+L91*(1+G91) -> 105454.55 | N91: Suministro de materiales y equipos | R91: 0 | S91: =+IF(R91=0,0,H91/R91) -> 0 | T91: =+IF(R91=0,0,K91/R91) -> 0
A92: 7.9 | B92: UNIONES IMC 1" | C92: Un | D92: 4 | E92: 0 | F92: =+D92+E92 -> 4 | G92: 0.19 | H92: =2856/1.19 -> 2400 | I92: =+H92*F92 -> 9600 | J92: =+I92*(1+G92) -> 11424 | K92: =+H92/$D$3 -> 3636.3636 | L92: =+K92*F92 -> 14545.455 | M92: =+L92*(1+G92) -> 17309.091 | N92: Suministro de materiales y equipos | R92: 0 | S92: =+IF(R92=0,0,H92/R92) -> 0 | T92: =+IF(R92=0,0,K92/R92) -> 0
A93: 7.10 | B93: TUBERÍA IMC 1" 1/2 x 3metros | C93: Un | D93: 0 | E93: 0 | F93: =+D93+E93 -> 0 | G93: 0.19 | H93: 127550 | I93: =+H93*F93 -> 0 | J93: =+I93*(1+G93) -> 0 | K93: =+H93/$D$3 -> 193257.58 | L93: =+K93*F93 -> 0 | M93: =+L93*(1+G93) -> 0 | N93: Suministro de materiales y equipos | R93: 0 | S93: =+IF(R93=0,0,H93/R93) -> 0 | T93: =+IF(R93=0,0,K93/R93) -> 0
A94: 7.11 | B94: CURVA IMC 1" 1/2 | C94: Un | D94: 0 | E94: 0 | F94: =+D94+E94 -> 0 | G94: 0.19 | H94: 18300 | I94: =+H94*F94 -> 0 | J94: =+I94*(1+G94) -> 0 | K94: =+H94/$D$3 -> 27727.273 | L94: =+K94*F94 -> 0 | M94: =+L94*(1+G94) -> 0 | N94: Suministro de materiales y equipos | R94: 0 | S94: =+IF(R94=0,0,H94/R94) -> 0 | T94: =+IF(R94=0,0,K94/R94) -> 0
A95: 7.12 | B95: UNIONES IMC 1" 1/2 | C95: Un | D95: 0 | E95: 0 | F95: =+D95+E95 -> 0 | G95: 0.19 | H95: 3850 | I95: =+H95*F95 -> 0 | J95: =+I95*(1+G95) -> 0 | K95: =+H95/$D$3 -> 5833.3333 | L95: =+K95*F95 -> 0 | M95: =+L95*(1+G95) -> 0 | N95: Suministro de materiales y equipos | R95: 0 | S95: =+IF(R95=0,0,H95/R95) -> 0 | T95: =+IF(R95=0,0,K95/R95) -> 0
A96: 7.13 | B96: TUBERÍA IMC 2" x 3metros | C96: Un | D96: 0 | F96: =+D96+E96 -> 0 | G96: 0.19 | H96: 160600 | I96: =+H96*F96 -> 0 | J96: =+I96*(1+G96) -> 0 | K96: =+H96/$D$3 -> 243333.33 | L96: =+K96*F96 -> 0 | M96: =+L96*(1+G96) -> 0 | N96: Suministro de materiales y equipos | R96: 0 | S96: =+IF(R96=0,0,H96/R96) -> 0 | T96: =+IF(R96=0,0,K96/R96) -> 0
A97: 7.14 | B97: CURVA IMC 2" 1/2 | C97: Un | D97: 0 | E97: 0 | F97: =+D97+E97 -> 0 | G97: 0.19 | H97: 28350 | I97: =+H97*F97 -> 0 | J97: =+I97*(1+G97) -> 0 | K97: =+H97/$D$3 -> 42954.545 | L97: =+K97*F97 -> 0 | M97: =+L97*(1+G97) -> 0 | N97: Suministro de materiales y equipos | R97: 0 | S97: =+IF(R97=0,0,H97/R97) -> 0 | T97: =+IF(R97=0,0,K97/R97) -> 0
A98: 7.15 | B98: UNIONES IMC 2" 1/2 | C98: Un | D98: 0 | E98: 0 | F98: =+D98+E98 -> 0 | G98: 0.19 | H98: 5400 | I98: =+H98*F98 -> 0 | J98: =+I98*(1+G98) -> 0 | K98: =+H98/$D$3 -> 8181.8182 | L98: =+K98*F98 -> 0 | M98: =+L98*(1+G98) -> 0 | N98: Suministro de materiales y equipos | O98: =+K98/$K$117 -> 0.13100119 | S98: =+IF(R98=0,0,H98/R98) -> 0 | T98: =+IF(R98=0,0,K98/R98) -> 0
A99: 7.16 | B99: TUBERÍA EMT 1" x 3metros | C99: Un | D99: 4 | E99: 0 | F99: =+D99+E99 -> 4 | G99: 0.19 | H99: 39850 | I99: =+H99*F99 -> 159400 | J99: =+I99*(1+G99) -> 189686 | K99: =+H99/$D$3 -> 60378.788 | L99: =+K99*F99 -> 241515.15 | M99: =+L99*(1+G99) -> 287403.03 | N99: Suministro de materiales y equipos | S99: =+IF(R99=0,0,H99/R99) -> 0 | T99: =+IF(R99=0,0,K99/R99) -> 0
A100: 7.17 | B100: CURVA EMT 1" | C100: Un | D100: 4 | E100: 0 | F100: =+D100+E100 -> 4 | G100: 0.19 | H100: 3150 | I100: =+H100*F100 -> 12600 | J100: =+I100*(1+G100) -> 14994 | K100: =+H100/$D$3 -> 4772.7273 | L100: =+K100*F100 -> 19090.909 | M100: =+L100*(1+G100) -> 22718.182 | N100: Suministro de materiales y equipos | O100: =+K100/$K$117 -> 0.07641736 | S100: =+IF(R100=0,0,H100/R100) -> 0 | T100: =+IF(R100=0,0,K100/R100) -> 0
A101: 7.18 | B101: UNIONES EMT 1" | C101: Un | D101: 4 | E101: 0 | F101: =+D101+E101 -> 4 | G101: 0.19 | H101: 1850 | I101: =+H101*F101 -> 7400 | J101: =+I101*(1+G101) -> 8806 | K101: =+H101/$D$3 -> 2803.0303 | L101: =+K101*F101 -> 11212.121 | M101: =+L101*(1+G101) -> 13342.424 | N101: Suministro de materiales y equipos | S101: =+IF(R101=0,0,H101/R101) -> 0 | T101: =+IF(R101=0,0,K101/R101) -> 0
...

Sheet Ejecución
C2: Sem 1 | D2: Sem 2 | E2: Sem 3 | F2: Sem 4 | G2: Sem 5 | H2: Sem 6 | I2: Sem 7 | J2: Sem 8 | K2: Sem 9 | L2: Sem 10 | M2: Sem 11 | N2: Sem 12 | O2: Sem 13
B3: Orden de compra
B4: Diseño
B5: Compra de estructuras y materiales
B6: Instalación de estructura y materiales
B7: Compra de paneles e inversores
B8: Instalación de paneles e inversores
B9: Compra e instalación de bateria 1
B10: Compra e instalación de bateria 2
B11: Compra e instalación de bateria 3

Sheet Cronograma
B2: Descripción | C2: Sem 1 | D2: Sem 2 | E2: Sem 3 | F2: Sem 4 | G2: Sem 5 | H2: Sem 6
B3: Diseño
B4: Adquisición estructura
B5: Adquisición materiales
B6: Adquisición paneles
B7: Adquisición inversores
B8: Adquisición baterías
B9: Instalación estructura
B10: Instalación materiales
B11: Instalación de paneles
B12: Instalación de inversores
B13: Puesta en servicio sistema sin baterias
B14: Instalación de baterías
B15: Puesta en servicio sistema con baterías

Sheet Instalación
A1: Rendimiento
A2: No Paneles CCPP | B2: =+#REF! -> #REF! | C2: Horas Requeridas | D2: No Personas | E2: Horas Disponibles diarias | F2: No Días
A3: Horas por panel incluye cableado | B3: 3.5 | C3: =+B2*B3 -> #REF! | D3: 2 | E3: =8*D3 -> 16 | F3: =+C3/E3 -> #REF! | H3: No horas semanales | I3: =44*4.3 -> 189.2
A4: Sistema Eléctrico | B4: =+B2 -> #REF! | C4: Horas Requeridas | D4: No Personas | E4: Horas Disponibles diarias | F4: No Días
A5: Sistema AC CCPP | C5: =+F5*8*D5 -> 32 | D5: 2 | F5: 2
A6: Puesta en servicio CCPP | C6: =+F6*8*D6 -> 16 | D6: 2 | F6: 1
A7: Total Horas | C7: =+C3+C5+C6 -> #REF! | D7: 3 | E7: 8 | F7: =+(C7)/(D7*E7) -> #REF!
B9: Sueldo | C9: k | D9: Salario | E9: Salario horario/Diario | F9: No horas/No Días | G9: Total
A10: Técnicos fijos | B10: =2200000+250000+300000 -> 2750000 | C10: 1.5 | D10: =+B10*C10 -> 4125000 | E10: =+D10/I3 -> 21802.326 | F10: =+C7 -> #REF! | G10: =+E10*F10 -> #REF! | I10: 150000
A11: Técnicos por obra labor | B11: 0 | C11: 1.47 | D11: =+B11*C11 -> 0 | E11: =+D11/I3 -> 0 | F11: =+C8 -> 0 | G11: =+E11*F11 -> 0 | I11: =114*3 -> 342
A12: Ayudante | B12: 0 | C12: 1.47 | D12: =+B12*C12 -> 0 | E12: =+D12/I3 -> 0 | F12: 1.5 | G12: =+E12*F12 -> 0 | I12: =+I10/I11 -> 438.59649
A13: Supervisor | B13: 3300000 | C13: 1.5 | D13: =+B13*C13 -> 4950000 | E13: =+D13/I3 -> 26162.791 | F13: =+F10*40% -> #REF! | G13: =+E13*F13 -> #REF! | I13: =+I12*277 -> 121491.23
A14: Alimentacion | B14: 25000 | C14: =+D7 -> 3 | D14: =+B14*C14 -> 75000 | E14: =+D14 -> 75000 | F14: =+F7 -> #REF! | G14: =+E14*F14 -> #REF!
A15: Herramientas | B15: =4000000/12 -> 333333.33 | C15: 1 | D15: =+B15*C15 -> 333333.33 | E15: =+D15/I3 -> 1761.8041 | F15: =+F10 -> #REF! | G15: =+E15*F15 -> #REF!
A16: Peajes | B16: =9*20000 -> 180000 | C16: 0 | D16: =+B16*C16 -> 0 | E16: =+D16 -> 0 | F16: 1 | G16: =+E16*F16 -> 0
A17: Apartamento | B17: 200000 | C17: 0 | D17: =+B17*C17 -> 0 | E17: 0 | F17: 5 | G17: =+D17*F17 -> 0
A18: Transporte | B18: 60000 | C18: 1 | D18: =+B18*C18 -> 60000 | E18: =+D18 -> 60000 | F18: =+F7 -> #REF! | G18: =+E18*F18 -> #REF!
A19: Hidratación | B19: 10000 | C19: =+D7 -> 3 | D19: =+B19*C19 -> 30000 | E19: =+D19 -> 30000 | F19: =+F7 -> #REF! | G19: =+E19*F19 -> #REF!
A20: Dotación | B20: 355000 | C20: 1 | D20: =+B20*C20 -> 355000 | E20: =+D20/(6*180) -> 328.7037 | F20: =+F10 -> #REF! | G20: =+E20*F20 -> #REF!
A21: Andamios | B21: 350000 | C21: 1 | D21: =+B21*C21 -> 350000 | G21: =+D21 -> 350000
A22: Moto | G22: =+D22*E22*F22 -> 0
A23: Elementos para trabajo en altura | B23: 1642850 | C23: 18 | D23: =+B23/C23 -> 91269.444 | E23: =+D23/I3 -> 482.39664 | F23: =+F10 -> #REF! | G23: =+E23*F23 -> #REF!
G25: =+SUM(G10:G24) -> #REF!
G26: =+#REF! -> #REF!
G27: =+G25/G26 -> #REF!

Sheet Prestamo 5 años
B1: Calculadora de préstamos simple
L2: {=+TRANSPOSE(B10:B69)} -> 1 | M2: 2 | N2: 3 | O2: 4 | P2: 5 | Q2: 6 | R2: 7 | S2: 8 | T2: 9 | U2: 10 | V2: 11 | W2: 12 | X2: 13 | Y2: 14 | Z2: 15 | AA2: 16 | AB2: 17 | AC2: 18 | AD2: 19 | AE2: 20 | AF2: 21 | AG2: 22 | AH2: 23 | AI2: 24 | AJ2: 25 | AK2: 26 | AL2: 27 | AM2: 28 | AN2: 29 | AO2: 30 | AP2: 31 | AQ2: 32 | AR2: 33 | AS2: 34 | AT2: 35 | AU2: 36 | AV2: 37 | AW2: 38 | AX2: 39 | AY2: 40 | AZ2: 41 | BA2: 42 | BB2: 43 | BC2: 44 | BD2: 45 | BE2: 46 | BF2: 47 | BG2: 48 | BH2: 49 | BI2: 50 | BJ2: 51 | BK2: 52 | BL2: 53 | BM2: 54 | BN2: 55 | BO2: 56 | BP2: 57 | BQ2: 58 | BR2: 59 | BS2: 60
B3: Valores del préstamo | F3: Resumen del préstamo | K3: Capital | L3: {=+TRANSPOSE(F10:F69)} -> 420908.55 | M3: 429677.48 | N3: 438629.09 | O3: 447767.2 | P3: 457095.68 | Q3: 466618.51 | R3: 476339.72 | S3: 486263.47 | T3: 496393.96 | U3: 506735.5 | V3: 517292.49 | W3: 528069.41 | X3: 539070.86 | Y3: 550301.5 | Z3: 561766.12 | AA3: 573469.58 | AB3: 585416.86 | AC3: 597613.05 | AD3: 610063.32 | AE3: 622772.97 | AF3: 635747.41 | AG3: 648992.15 | AH3: 662512.82 | AI3: 676315.17 | AJ3: 690405.06 | AK3: 704788.5 | AL3: 719471.6 | AM3: 734460.59 | AN3: 749761.85 | AO3: 765381.89 | AP3: 781327.35 | AQ3: 797605 | AR3: 814221.77 | AS3: 831184.72 | AT3: 848501.07 | AU3: 866178.18 | AV3: 884223.56 | AW3: 902644.88 | AX3: 921449.98 | AY3: 940646.86 | AZ3: 960243.67 | BA3: 980248.74 | BB3: 1000670.6 | BC3: 1021517.9 | BD3: 1042799.5 | BE3: 1064524.5 | BF3: 1086702.1 | BG3: 1109341.7 | BH3: 1132453 | BI3: 1156045.8 | BJ3: 1180130.1 | BK3: 1204716.1 | BL3: 1229814.4 | BM3: 1255435.5 | BN3: 1281590.4 | BO3: 1308290.2 | BP3: 1335546.3 | BQ3: 1363370.1 | BR3: 1391773.7 | BS3: 1420769
B4: Importe del préstamo | D4: =+'Capex GoodWe'!M152 -> 49414069 | F4: Pago mensual | H4: =IFERROR(IF(PréstamoPagado,PagoMensual,""), "") -> 1450368.3 | K4: Intereses | L4: {=+TRANSPOSE(G10:G69)} -> 1029459.8 | M4: 1020690.8 | N4: 1011739.2 | O4: 1002601.1 | P4: 993272.64 | Q4: 983749.81 | R4: 974028.59 | S4: 964104.85 | T4: 953974.36 | U4: 943632.82 | V4: 933075.83 | W4: 922298.9 | X4: 911297.46 | Y4: 900066.81 | Z4: 888602.2 | AA4: 876898.74 | AB4: 864951.46 | AC4: 852755.27 | AD4: 840305 | AE4: 827595.35 | AF4: 814620.91 | AG4: 801376.17 | AH4: 787855.5 | AI4: 774053.15 | AJ4: 759963.25 | AK4: 745579.81 | AL4: 730896.72 | AM4: 715907.73 | AN4: 700606.47 | AO4: 684986.43 | AP4: 669040.97 | AQ4: 652763.32 | AR4: 636146.55 | AS4: 619183.59 | AT4: 601867.25 | AU4: 584190.14 | AV4: 566144.76 | AW4: 547723.44 | AX4: 528918.34 | AY4: 509721.46 | AZ4: 490124.65 | BA4: 470119.57 | BB4: 449697.73 | BC4: 428850.42 | BD4: 407568.8 | BE4: 385843.81 | BF4: 363666.22 | BG4: 341026.59 | BH4: 317915.3 | BI4: 294322.53 | BJ4: 270238.24 | BK4: 245652.2 | BL4: 220553.95 | BM4: 194932.82 | BN4: 168777.91 | BO4: 142078.11 | BP4: 114822.06 | BQ4: 86998.183 | BR4: 58594.638 | BS4: 29599.353
B5: Tasa de interés anual | D5: 0.25 | F5: Número de pagos | H5: =IFERROR(IF(PréstamoPagado,AñosPréstamo*12,""), "") -> 60 | K5: Saldo Capital | L5: {=+TRANSPOSE(H10:H69)} -> 48993160 | M5: 48563483 | N5: 48124854 | O5: 47677087 | P5: 47219991 | Q5: 46753372 | R5: 46277033 | S5: 45790769 | T5: 45294375 | U5: 44787640 | V5: 44270347 | W5: 43742278 | X5: 43203207 | Y5: 42652906 | Z5: 42091139 | AA5: 41517670 | AB5: 40932253 | AC5: 40334640 | AD5: 39724577 | AE5: 39101804 | AF5: 38466056 | AG5: 37817064 | AH5: 37154551 | AI5: 36478236 | AJ5: 35787831 | AK5: 35083043 | AL5: 34363571 | AM5: 33629110 | AN5: 32879349 | AO5: 32113967 | AP5: 31332639 | AQ5: 30535034 | AR5: 29720812 | AS5: 28889628 | AT5: 28041127 | AU5: 27174949 | AV5: 26290725 | AW5: 25388080 | AX5: 24466630 | AY5: 23525983 | AZ5: 22565740 | BA5: 21585491 | BB5: 20584820 | BC5: 19563302 | BD5: 18520503 | BE5: 17455978 | BF5: 16369276 | BG5: 15259935 | BH5: 14127481 | BI5: 12971436 | BJ5: 11791306 | BK5: 10586590 | BL5: 9356775.1 | BM5: 8101339.6 | BN5: 6819749.2 | BO5: 5511459 | BP5: 4175912.8 | BQ5: 2812542.6 | BR5: 1420769 | BS5: 4.7683716e-07
B6: Periodo del préstamo en años | D6: 5 | F6: Importe total de los intereses | H6: =IFERROR(IF(PréstamoPagado,CosteTotalPréstamo-CantidadPréstamo,""), "") -> 37608030 | J6: 1159 | K6: Seguros | L6: =+(L5/1000000)*$J$6 -> 56783.073 | M6: =+(M5/1000000)*$J$6 -> 56285.077 | N6: =+(N5/1000000)*$J$6 -> 55776.706 | O6: =+(O5/1000000)*$J$6 -> 55257.743 | P6: =+(P5/1000000)*$J$6 -> 54727.97 | Q6: =+(Q5/1000000)*$J$6 -> 54187.159 | R6: =+(R5/1000000)*$J$6 -> 53635.081 | S6: =+(S5/1000000)*$J$6 -> 53071.502 | ... BS6: =+(BS5/1000000)*$J$6 -> 5.5265427e-10
B7: Fecha de inicio del préstamo | D7: =TODAY() -> 46301 | F7: Coste total del préstamo | H7: =IFERROR(IF(PréstamoPagado,PagoMensual*NúmeroDePagos,""), "") -> 87022099 | K7: Total | L7: =+L3+L4+L6 -> 1507151.4 | M7: =+M3+M4+M6 -> 1506653.4 | N7: =+N3+N4+N6 -> 1506145 | O7: =+O3+O4+O6 -> 1505626.1 | P7: =+P3+P4+P6 -> 1505096.3 | Q7: =+Q3+Q4+Q6 -> 1504555.5 | R7: =+R3+R4+R6 -> 1504003.4 | S7: =+S3+S4+S6 -> 1503439.8 | ... BS7: =+BS3+BS4+BS6 -> 1450368.3
B9: N.° de pago | C9: Fecha de pago | D9: Saldo inicial | E9: Pago | F9: Capital | G9: Intereses | H9: Saldo final
B10: =IFERROR(IF(PréstamoNoPagado*PréstamoPagado,NúmeroDePago,""), "") -> 1 | C10: =IFERROR(IF(PréstamoNoPagado*PréstamoPagado,FechaDePago,""), "") -> 46332 | D10: =IFERROR(IF(PréstamoNoPagado*PréstamoPagado,ValorPréstamo,""), "") -> 49414069 | E10: =IFERROR(IF(PréstamoNoPagado*PréstamoPagado,PagoMensual,""), "") -> 1450368.3 | F10: =IFERROR(IF(PréstamoNoPagado*PréstamoPagado,Capital,""), "") -> 420908.55 | G10: =IFERROR(IF(PréstamoNoPagado*PréstamoPagado,AmortizaciónInterés,""), "") -> 1029459.8 | H10: =IFERROR(IF(PréstamoNoPagado*PréstamoPagado,SaldoFinal,""), "") -> 48993160
B11: =IFERROR(IF(PréstamoNoPagado*PréstamoPagado,NúmeroDePago,""), "") -> 2 | C11: =IFERROR(IF(PréstamoNoPagado*PréstamoPagado,FechaDePago,""), "") -> 46362 | D11: =IFERROR(IF(PréstamoNoPagado*PréstamoPagado,ValorPréstamo,""), "") -> 48993160 | E11: =IFERROR(IF(PréstamoNoPagado*PréstamoPagado,PagoMensual,""), "") -> 1450368.3 | F11: =IFERROR(IF(PréstamoNoPagado*PréstamoPagado,Capital,""), "") -> 429677.48 | G11: =IFERROR(IF(PréstamoNoPagado*PréstamoPagado,AmortizaciónInterés,""), "") -> 1020690.8 | H11: =IFERROR(IF(PréstamoNoPagado*PréstamoPagado,SaldoFinal,""), "") -> 48563483
B12: =IFERROR(IF(PréstamoNoPagado*PréstamoPagado,NúmeroDePago,""), "") -> 3 | C12: =IFERROR(IF(PréstamoNoPagado*PréstamoPagado,FechaDePago,""), "") -> 46393 | D12: =IFERROR(IF(PréstamoNoPagado*PréstamoPagado,ValorPréstamo,""), "") -> 48563483 | E12: =IFERROR(IF(PréstamoNoPagado*PréstamoPagado,PagoMensual,""), "") -> 1450368.3 | F12: =IFERROR(IF(PréstamoNoPagado*PréstamoPagado,Capital,""), "") -> 438629.09 | G12: =IFERROR(IF(PréstamoNoPagado*PréstamoPagado,AmortizaciónInterés,""), "") -> 1011739.2 | H12: =IFERROR(IF(PréstamoNoPagado*PréstamoPagado,SaldoFinal,""), "") -> 48124854
B13: =IFERROR(IF(PréstamoNoPagado*PréstamoPagado,NúmeroDePago,""), "") -> 4 | C13: =IFERROR(IF(PréstamoNoPagado*PréstamoPagado,FechaDePago,""), "") -> 46424 | D13: =IFERROR(IF(PréstamoNoPagado*PréstamoPagado,ValorPréstamo,""), "") -> 48124854 | E13: =IFERROR(IF(PréstamoNoPagado*PréstamoPagado,PagoMensual,""), "") -> 1450368.3 | F13: =IFERROR(IF(PréstamoNoPagado*PréstamoPagado,Capital,""), "") -> 447767.2 | G13: =IFERROR(IF(PréstamoNoPagado*PréstamoPagado,AmortizaciónInterés,""), "") -> 1002601.1 | H13: =IFERROR(IF(PréstamoNoPagado*PréstamoPagado,SaldoFinal,""), "") -> 47677087
B14: =IFERROR(IF(PréstamoNoPagado*PréstamoPagado,NúmeroDePago,""), "") -> 5 | C14: =IFERROR(IF(PréstamoNoPagado*PréstamoPagado,FechaDePago,""), "") -> 46452 | D14: =IFERROR(IF(PréstamoNoPagado*PréstamoPagado,ValorPréstamo,""), "") -> 47677087 | E14: =IFERROR(IF(PréstamoNoPagado*PréstamoPagado,PagoMensual,""), "") -> 1450368.3 | F14: =IFERROR(IF(PréstamoNoPagado*PréstamoPagado,Capital,""), "") -> 457095.68 | G14: =IFERROR(IF(PréstamoNoPagado*PréstamoPagado,AmortizaciónInterés,""), "") -> 993272.64 | H14: =IFERROR(IF(PréstamoNoPagado*PréstamoPagado,SaldoFinal,""), "") -> 47219991
B15: =IFERROR(IF(PréstamoNoPagado*PréstamoPagado,NúmeroDePago,""), "") -> 6 | C15: =IFERROR(IF(PréstamoNoPagado*PréstamoPagado,FechaDePago,""), "") -> 46483 | D15: =IFERROR(IF(PréstamoNoPagado*PréstamoPagado,ValorPréstamo,""), "") -> 47219991 | E15: =IFERROR(IF(PréstamoNoPagado*PréstamoPagado,PagoMensual,""), "") -> 1450368.3 | F15: =IFERROR(IF(PréstamoNoPagado*PréstamoPagado,Capital,""), "") -> 466618.51 | G15: =IFERROR(IF(PréstamoNoPagado*PréstamoPagado,AmortizaciónInterés,""), "") -> 983749.81 | H15: =IFERROR(IF(PréstamoNoPagado*PréstamoPagado,SaldoFinal,""), "") -> 46753372
B16: =IFERROR(IF(PréstamoNoPagado*PréstamoPagado,NúmeroDePago,""), "") -> 7 | C16: =IFERROR(IF(PréstamoNoPagado*PréstamoPagado,FechaDePago,""), "") -> 46513 | D16: =IFERROR(IF(PréstamoNoPagado*PréstamoPagado,ValorPréstamo,""), "") -> 46753372 | E16: =IFERROR(IF(PréstamoNoPagado*PréstamoPagado,PagoMensual,""), "") -> 1450368.3 | F16: =IFERROR(IF(PréstamoNoPagado*PréstamoPagado,Capital,""), "") -> 476339.72 | G16: =IFERROR(IF(PréstamoNoPagado*PréstamoPagado,AmortizaciónInterés,""), "") -> 974028.59 | H16: =IFERROR(IF(PréstamoNoPagado*PréstamoPagado,SaldoFinal,""), "") -> 46277033
B17: =IFERROR(IF(PréstamoNoPagado*PréstamoPagado,NúmeroDePago,""), "") -> 8 | C17: =IFERROR(IF(PréstamoNoPagado*PréstamoPagado,FechaDePago,""), "") -> 46544 | D17: =IFERROR(IF(PréstamoNoPagado*PréstamoPagado,ValorPréstamo,""), "") -> 46277033 | E17: =IFERROR(IF(PréstamoNoPagado*PréstamoPagado,PagoMensual,""), "") -> 1450368.3 | F17: =IFERROR(IF(PréstamoNoPagado*PréstamoPagado,Capital,""), "") -> 486263.47 | G17: =IFERROR(IF(PréstamoNoPagado*PréstamoPagado,AmortizaciónInterés,""), "") -> 964104.85 | H17: =IFERROR(IF(PréstamoNoPagado*PréstamoPagado,SaldoFinal,""), "") -> 45790769
B18: =IFERROR(IF(PréstamoNoPagado*PréstamoPagado,NúmeroDePago,""), "") -> 9 | C18: =IFERROR(IF(PréstamoNoPagado*PréstamoPagado,FechaDePago,""), "") -> 46574 | D18: =IFERROR(IF(PréstamoNoPagado*PréstamoPagado,ValorPréstamo,""), "") -> 45790769 | E18: =IFERROR(IF(PréstamoNoPagado*PréstamoPagado,PagoMensual,""), "") -> 1450368.3 | F18: =IFERROR(IF(PréstamoNoPagado*PréstamoPagado,Capital,""), "") -> 496393.96 | G18: =IFERROR(IF(PréstamoNoPagado*PréstamoPagado,AmortizaciónInterés,""), "") -> 953974.36 | H18: =IFERROR(IF(PréstamoNoPagado*PréstamoPagado,SaldoFinal,""), "") -> 45294375
B19: =IFERROR(IF(PréstamoNoPagado*PréstamoPagado,NúmeroDePago,""), "") -> 10 | C19: =IFERROR(IF(PréstamoNoPagado*PréstamoPagado,FechaDePago,""), "") -> 46605 | D19: =IFERROR(IF(PréstamoNoPagado*PréstamoPagado,ValorPréstamo,""), "") -> 45294375 | E19: =IFERROR(IF(PréstamoNoPagado*PréstamoPagado,PagoMensual,""), "") -> 1450368.3 | F19: =IFERROR(IF(PréstamoNoPagado*PréstamoPagado,Capital,""), "") -> 506735.5 | G19: =IFERROR(IF(PréstamoNoPagado*PréstamoPagado,AmortizaciónInterés,""), "") -> 943632.82 | H19: =IFERROR(IF(PréstamoNoPagado*PréstamoPagado,SaldoFinal,""), "") -> 44787640
B20: =IFERROR(IF(PréstamoNoPagado*PréstamoPagado,NúmeroDePago,""), "") -> 11 | C20: =IFERROR(IF(PréstamoNoPagado*PréstamoPagado,FechaDePago,""), "") -> 46636 | D20: =IFERROR(IF(PréstamoNoPagado*PréstamoPagado,ValorPréstamo,""), "") -> 44787640 | E20: =IFERROR(IF(PréstamoNoPagado*PréstamoPagado,PagoMensual,""), "") -> 1450368.3 | F20: =IFERROR(IF(PréstamoNoPagado*PréstamoPagado,Capital,""), "") -> 517292.49 | G20: =IFERROR(IF(PréstamoNoPagado*PréstamoPagado,AmortizaciónInterés,""), "") -> 933075.83 | H20: =IFERROR(IF(PréstamoNoPagado*PréstamoPagado,SaldoFinal,""), "") -> 44270347
B21: =IFERROR(IF(PréstamoNoPagado*PréstamoPagado,NúmeroDePago,""), "") -> 12 | C21: =IFERROR(IF(PréstamoNoPagado*PréstamoPagado,FechaDePago,""), "") -> 46666 | D21: =IFERROR(IF(PréstamoNoPagado*PréstamoPagado,ValorPréstamo,""), "") -> 44270347 | E21: =IFERROR(IF(PréstamoNoPagado*PréstamoPagado,PagoMensual,""), "") -> 1450368.3 | F21: =IFERROR(IF(PréstamoNoPagado*PréstamoPagado,Capital,""), "") -> 528069.41 | G21: =IFERROR(IF(PréstamoNoPagado*PréstamoPagado,AmortizaciónInterés,""), "") -> 922298.9 | H21: =IFERROR(IF(PréstamoNoPagado*PréstamoPagado,SaldoFinal,""), "") -> 43742278
... B369: =IFERROR(IF(PréstamoNoPagado*PréstamoPagado,NúmeroDePago,""), "") | C369: =IFERROR(IF(PréstamoNoPagado*PréstamoPagado,FechaDePago,""), "") | D369: =IFERROR(IF(PréstamoNoPagado*PréstamoPagado,ValorPréstamo,""), "") | E369: =IFERROR(IF(PréstamoNoPagado*PréstamoPagado,PagoMensual,""), "") | F369: =IFERROR(IF(PréstamoNoPagado*PréstamoPagado,Capital,""), "") | G369: =IFERROR(IF(PréstamoNoPagado*PréstamoPagado,AmortizaciónInterés,""), "") | H369: =IFERROR(IF(PréstamoNoPagado*PréstamoPagado,SaldoFinal,""), "")

Sheet Prestamo 10 años
B1: Calculadora de préstamos simple
L2: {=+TRANSPOSE(B10:B129)}
B3: Valores del préstamo | F3: Resumen del préstamo | K3: Capital | L3: {=+TRANSPOSE(F10:F129)}
B4: Importe del préstamo | D4: =+#REF! -> #REF! | F4: Pago mensual | H4: =IFERROR(IF(PréstamoPagado,PagoMensual,""), "") | K4: Intereses | L4: {=+TRANSPOSE(G10:G129)}
B5: Tasa de interés anual | D5: 0.13 | F5: Número de pagos | H5: =IFERROR(IF(PréstamoPagado,AñosPréstamo*12,""), "") | K5: Saldo Capital | L5: {=+TRANSPOSE(H10:H129)}
B6: Periodo del préstamo en años | D6: 10 | F6: Importe total de los intereses | H6: =IFERROR(IF(PréstamoPagado,CosteTotalPréstamo-CantidadPréstamo,""), "") | J6: 1159 | K6: Seguros | L6: =+(L5/1000000)*$J$6 -> #VALUE! | M6: =+(M5/1000000)*$J$6 -> #VALUE! | N6: =+(N5/1000000)*$J$6 -> #VALUE! | O6: =+(O5/1000000)*$J$6 -> #VALUE! | P6: =+(P5/1000000)*$J$6 -> #VALUE! | Q6: =+(Q5/1000000)*$J$6 -> #VALUE! | R6: =+(R5/1000000)*$J$6 -> #VALUE! | S6: =+(S5/1000000)*$J$6 -> #VALUE! | ... EA6: =+(EA5/1000000)*$J$6 -> #VALUE!
B7: Fecha de inicio del préstamo | D7: =TODAY() -> 46301 | F7: Coste total del préstamo | H7: =IFERROR(IF(PréstamoPagado,PagoMensual*NúmeroDePagos,""), "") | K7: Total | L7: =+L3+L4+L6 -> #VALUE! | M7: =+M3+M4+M6 -> #VALUE! | N7: =+N3+N4+N6 -> #VALUE! | O7: =+O3+O4+O6 -> #VALUE! | P7: =+P3+P4+P6 -> #VALUE! | Q7: =+Q3+Q4+Q6 -> #VALUE! | R7: =+R3+R4+R6 -> #VALUE! | S7: =+S3+S4+S6 -> #VALUE! | ... EA7: =+EA3+EA4+EA6 -> #VALUE!
B9: N.° de pago | C9: Fecha de pago | D9: Saldo inicial | E9: Pago | F9: Capital | G9: Intereses | H9: Saldo final
B10: =IFERROR(IF(PréstamoNoPagado*PréstamoPagado,NúmeroDePago,""), "") | C10: =IFERROR(IF(PréstamoNoPagado*PréstamoPagado,FechaDePago,""), "") | D10: =IFERROR(IF(PréstamoNoPagado*PréstamoPagado,ValorPréstamo,""), "") | E10: =IFERROR(IF(PréstamoNoPagado*PréstamoPagado,PagoMensual,""), "") | F10: =IFERROR(IF(PréstamoNoPagado*PréstamoPagado,Capital,""), "") | G10: =IFERROR(IF(PréstamoNoPagado*PréstamoPagado,AmortizaciónInterés,""), "") | H10: =IFERROR(IF(PréstamoNoPagado*PréstamoPagado,SaldoFinal,""), "")
B11: =IFERROR(IF(PréstamoNoPagado*PréstamoPagado,NúmeroDePago,""), "") | C11: =IFERROR(IF(PréstamoNoPagado*PréstamoPagado,FechaDePago,""), "") | D11: =IFERROR(IF(PréstamoNoPagado*PréstamoPagado,ValorPréstamo,""), "") | E11: =IFERROR(IF(PréstamoNoPagado*PréstamoPagado,PagoMensual,""), "") | F11: =IFERROR(IF(PréstamoNoPagado*PréstamoPagado,Capital,""), "") | G11: =IFERROR(IF(PréstamoNoPagado*PréstamoPagado,AmortizaciónInterés,""), "") | H11: =IFERROR(IF(PréstamoNoPagado*PréstamoPagado,SaldoFinal,""), "")
B12: =IFERROR(IF(PréstamoNoPagado*PréstamoPagado,NúmeroDePago,""), "") | C12: =IFERROR(IF(PréstamoNoPagado*PréstamoPagado,FechaDePago,""), "") | D12: =IFERROR(IF(PréstamoNoPagado*PréstamoPagado,ValorPréstamo,""), "") | E12: =IFERROR(IF(PréstamoNoPagado*PréstamoPagado,PagoMensual,""), "") | F12: =IFERROR(IF(PréstamoNoPagado*PréstamoPagado,Capital,""), "") | G12: =IFERROR(IF(PréstamoNoPagado*PréstamoPagado,AmortizaciónInterés,""), "") | H12: =IFERROR(IF(PréstamoNoPagado*PréstamoPagado,SaldoFinal,""), "")
B13: =IFERROR(IF(PréstamoNoPagado*PréstamoPagado,NúmeroDePago,""), "") | C13: =IFERROR(IF(PréstamoNoPagado*PréstamoPagado,FechaDePago,""), "") | D13: =IFERROR(IF(PréstamoNoPagado*PréstamoPagado,ValorPréstamo,""), "") | E13: =IFERROR(IF(PréstamoNoPagado*PréstamoPagado,PagoMensual,""), "") | F13: =IFERROR(IF(PréstamoNoPagado*PréstamoPagado,Capital,""), "") | G13: =IFERROR(IF(PréstamoNoPagado*PréstamoPagado,AmortizaciónInterés,""), "") | H13: =IFERROR(IF(PréstamoNoPagado*PréstamoPagado,SaldoFinal,""), "")
B14: =IFERROR(IF(PréstamoNoPagado*PréstamoPagado,NúmeroDePago,""), "") | C14: =IFERROR(IF(PréstamoNoPagado*PréstamoPagado,FechaDePago,""), "") | D14: =IFERROR(IF(PréstamoNoPagado*PréstamoPagado,ValorPréstamo,""), "") | E14: =IFERROR(IF(PréstamoNoPagado*PréstamoPagado,PagoMensual,""), "") | F14: =IFERROR(IF(PréstamoNoPagado*PréstamoPagado,Capital,""), "") | G14: =IFERROR(IF(PréstamoNoPagado*PréstamoPagado,AmortizaciónInterés,""), "") | H14: =IFERROR(IF(PréstamoNoPagado*PréstamoPagado,SaldoFinal,""), "")
B15: =IFERROR(IF(PréstamoNoPagado*PréstamoPagado,NúmeroDePago,""), "") | C15: =IFERROR(IF(PréstamoNoPagado*PréstamoPagado,FechaDePago,""), "") | D15: =IFERROR(IF(PréstamoNoPagado*PréstamoPagado,ValorPréstamo,""), "") | E15: =IFERROR(IF(PréstamoNoPagado*PréstamoPagado,PagoMensual,""), "") | F15: =IFERROR(IF(PréstamoNoPagado*PréstamoPagado,Capital,""), "") | G15: =IFERROR(IF(PréstamoNoPagado*PréstamoPagado,AmortizaciónInterés,""), "") | H15: =IFERROR(IF(PréstamoNoPagado*PréstamoPagado,SaldoFinal,""), "")
B16: =IFERROR(IF(PréstamoNoPagado*PréstamoPagado,NúmeroDePago,""), "") | C16: =IFERROR(IF(PréstamoNoPagado*PréstamoPagado,FechaDePago,""), "") | D16: =IFERROR(IF(PréstamoNoPagado*PréstamoPagado,ValorPréstamo,""), "") | E16: =IFERROR(IF(PréstamoNoPagado*PréstamoPagado,PagoMensual,""), "") | F16: =IFERROR(IF(PréstamoNoPagado*PréstamoPagado,Capital,""), "") | G16: =IFERROR(IF(PréstamoNoPagado*PréstamoPagado,AmortizaciónInterés,""), "") | H16: =IFERROR(IF(PréstamoNoPagado*PréstamoPagado,SaldoFinal,""), "")
B17: =IFERROR(IF(PréstamoNoPagado*PréstamoPagado,NúmeroDePago,""), "") | C17: =IFERROR(IF(PréstamoNoPagado*PréstamoPagado,FechaDePago,""), "") | D17: =IFERROR(IF(PréstamoNoPagado*PréstamoPagado,ValorPréstamo,""), "") | E17: =IFERROR(IF(PréstamoNoPagado*PréstamoPagado,PagoMensual,""), "") | F17: =IFERROR(IF(PréstamoNoPagado*PréstamoPagado,Capital,""), "") | G17: =IFERROR(IF(PréstamoNoPagado*PréstamoPagado,AmortizaciónInterés,""), "") | H17: =IFERROR(IF(PréstamoNoPagado*PréstamoPagado,SaldoFinal,""), "")
B18: =IFERROR(IF(PréstamoNoPagado*PréstamoPagado,NúmeroDePago,""), "") | C18: =IFERROR(IF(PréstamoNoPagado*PréstamoPagado,FechaDePago,""), "") | D18: =IFERROR(IF(PréstamoNoPagado*PréstamoPagado,ValorPréstamo,""), "") | E18: =IFERROR(IF(PréstamoNoPagado*PréstamoPagado,PagoMensual,""), "") | F18: =IFERROR(IF(PréstamoNoPagado*PréstamoPagado,Capital,""), "") | G18: =IFERROR(IF(PréstamoNoPagado*PréstamoPagado,AmortizaciónInterés,""), "") | H18: =IFERROR(IF(PréstamoNoPagado*PréstamoPagado,SaldoFinal,""), "")
B19: =IFERROR(IF(PréstamoNoPagado*PréstamoPagado,NúmeroDePago,""), "") | C19: =IFERROR(IF(PréstamoNoPagado*PréstamoPagado,FechaDePago,""), "") | D19: =IFERROR(IF(PréstamoNoPagado*PréstamoPagado,ValorPréstamo,""), "") | E19: =IFERROR(IF(PréstamoNoPagado*PréstamoPagado,PagoMensual,""), "") | F19: =IFERROR(IF(PréstamoNoPagado*PréstamoPagado,Capital,""), "") | G19: =IFERROR(IF(PréstamoNoPagado*PréstamoPagado,AmortizaciónInterés,""), "") | H19: =IFERROR(IF(PréstamoNoPagado*PréstamoPagado,SaldoFinal,""), "")
B20: =IFERROR(IF(PréstamoNoPagado*PréstamoPagado,NúmeroDePago,""), "") | C20: =IFERROR(IF(PréstamoNoPagado*PréstamoPagado,FechaDePago,""), "") | D20: =IFERROR(IF(PréstamoNoPagado*PréstamoPagado,ValorPréstamo,""), "") | E20: =IFERROR(IF(PréstamoNoPagado*PréstamoPagado,PagoMensual,""), "") | F20: =IFERROR(IF(PréstamoNoPagado*PréstamoPagado,Capital,""), "") | G20: =IFERROR(IF(PréstamoNoPagado*PréstamoPagado,AmortizaciónInterés,""), "") | H20: =IFERROR(IF(PréstamoNoPagado*PréstamoPagado,SaldoFinal,""), "")
B21: =IFERROR(IF(PréstamoNoPagado*PréstamoPagado,NúmeroDePago,""), "") | C21: =IFERROR(IF(PréstamoNoPagado*PréstamoPagado,FechaDePago,""), "") | D21: =IFERROR(IF(PréstamoNoPagado*PréstamoPagado,ValorPréstamo,""), "") | E21: =IFERROR(IF(PréstamoNoPagado*PréstamoPagado,PagoMensual,""), "") | F21: =IFERROR(IF(PréstamoNoPagado*PréstamoPagado,Capital,""), "") | G21: =IFERROR(IF(PréstamoNoPagado*PréstamoPagado,AmortizaciónInterés,""), "") | H21: =IFERROR(IF(PréstamoNoPagado*PréstamoPagado,SaldoFinal,""), "")
... B369: =IFERROR(IF(PréstamoNoPagado*PréstamoPagado,NúmeroDePago,""), "") | C369: =IFERROR(IF(PréstamoNoPagado*PréstamoPagado,FechaDePago,""), "") | D369: =IFERROR(IF(PréstamoNoPagado*PréstamoPagado,ValorPréstamo,""), "") | E369: =IFERROR(IF(PréstamoNoPagado*PréstamoPagado,PagoMensual,""), "") | F369: =IFERROR(IF(PréstamoNoPagado*PréstamoPagado,Capital,""), "") | G369: =IFERROR(IF(PréstamoNoPagado*PréstamoPagado,AmortizaciónInterés,""), "") | H369: =IFERROR(IF(PréstamoNoPagado*PréstamoPagado,SaldoFinal,""), "")

Sheet Simulacion prestamo
A1: Corto Plazo | B1: Con Seguro | C1: Sin Seguro
A2: Capital | B2: =+#REF! -> #REF! | D2: Cuota | E2: =+PMT(B4,B6,B2) -> #REF!
A3: Tasa EA | B3: 0.2065 | C3: 0.1899
A4: Tasa MV | B4: 0.0164 | C4: 0.0146
A5: Plazo años | B5: 4
A6: Plazo meses | B6: =+B5*12 -> 48
A7: Seguro por millon | B7: 1159
A10: Mes | B10: 0 | C10: 1 | D10: 2 | E10: 3 | F10: 4 | G10: 5 | H10: 6 | I10: 7 | J10: 8 | K10: 9 | L10: 10 | M10: 11 | N10: 12 | O10: 13 | P10: 14 | Q10: 15 | R10: 16 | S10: 17 | T10: 18 | U10: 19 | V10: 20 | W10: 21 | X10: 22 | Y10: 23 | Z10: 24 | AA10: 25 | AB10: 26 | AC10: 27 | AD10: 28 | AE10: 29 | AF10: 30 | AG10: 31 | AH10: 32 | AI10: 33 | AJ10: 34 | AK10: 35 | AL10: 36 | AM10: 37 | AN10: 38 | AO10: 39 | AP10: 40 | AQ10: 41 | AR10: 42 | AS10: 43 | AT10: 44 | AU10: 45 | AV10: 46 | AW10: 47 | AX10: 48 | AY10: 49 | AZ10: 50 | BA10: 51 | BB10: 52 | BC10: 53 | BD10: 54 | BE10: 55 | BF10: 56 | BG10: 57 | BH10: 58 | BI10: 59 | BJ10: 60
A11: Saldo Capital | B11: =+B2 -> #REF! | C11: =+B11-C13 -> #REF! | D11: =+C11-D13 -> #REF! | E11: =+D11-E13 -> #REF! | F11: =+E11-F13 -> #REF! | G11: =+F11-G13 -> #REF! | H11: =+G11-H13 -> #REF! | I11: =+H11-I13 -> #REF! | J11: =+I11-J13 -> #REF! | ... AX11: =+AW11-AX13 -> #REF!
A12: Pago a intereses | B12: 0 | C12: =+B11*$C$4 -> #REF! | D12: =+C11*$C$4 -> #REF! | E12: =+D11*$C$4 -> #REF! | F12: =+E11*$C$4 -> #REF! | G12: =+F11*$C$4 -> #REF! | H12: =+G11*$C$4 -> #REF! | I12: =+H11*$C$4 -> #REF! | J12: =+I11*$C$4 -> #REF! | ... AX12: =+AW11*$C$4 -> #REF!
A13: Pago a capital | B13: 0 | C13: =+C14-C12 -> #REF! | D13: =+D14-D12 -> #REF! | E13: =+E14-E12 -> #REF! | F13: =+F14-F12 -> #REF! | G13: =+G14-G12 -> #REF! | H13: =+H14-H12 -> #REF! | I13: =+I14-I12 -> #REF! | J13: =+J14-J12 -> #REF! | ... AX13: =+AX14-AX12 -> #REF!
A14: Cuota Total sin seguros | B14: 0 | C14: =+PMT($C$4,$B$6,-$B$2,0) -> #REF! | D14: =+PMT($C$4,$B$6,-$B$2,0) -> #REF! | E14: =+PMT($C$4,$B$6,-$B$2,0) -> #REF! | F14: =+PMT($C$4,$B$6,-$B$2,0) -> #REF! | G14: =+PMT($C$4,$B$6,-$B$2,0) -> #REF! | H14: =+PMT($C$4,$B$6,-$B$2,0) -> #REF! | I14: =+PMT($C$4,$B$6,-$B$2,0) -> #REF! | J14: =+PMT($C$4,$B$6,-$B$2,0) -> #REF! | ... AX14: =+PMT($C$4,$B$6,-$B$2,0) -> #REF!
A15: Seguros | B15: 0 | C15: =+$B$7*(B11/1000000) -> #REF! | D15: =+$B$7*(C11/1000000) -> #REF! | E15: =+$B$7*(D11/1000000) -> #REF! | F15: =+$B$7*(E11/1000000) -> #REF! | G15: =+$B$7*(F11/1000000) -> #REF! | H15: =+$B$7*(G11/1000000) -> #REF! | I15: =+$B$7*(H11/1000000) -> #REF! | J15: =+$B$7*(I11/1000000) -> #REF! | ... AX15: =+$B$7*(AW11/1000000) -> #REF!
A16: Cuota total con seguros | B16: 0 | C16: =+PMT($B$4,$B$6,-$B$2,0) -> #REF! | D16: =+PMT($B$4,$B$6,-$B$2,0) -> #REF! | E16: =+PMT($B$4,$B$6,-$B$2,0) -> #REF! | F16: =+PMT($B$4,$B$6,-$B$2,0) -> #REF! | G16: =+PMT($B$4,$B$6,-$B$2,0) -> #REF! | H16: =+PMT($B$4,$B$6,-$B$2,0) -> #REF! | I16: =+PMT($B$4,$B$6,-$B$2,0) -> #REF! | J16: =+PMT($B$4,$B$6,-$B$2,0) -> #REF! | ... AX16: =+PMT($B$4,$B$6,-$B$2,0) -> #REF!
A18: Capital | B18: =+SUM(B13:BJ13) -> #REF!
A19: Intereses | B19: =+SUM(B12:BJ12) -> #REF!
A20: Seguros | B20: =+SUM(B15:BJ15) -> #REF!
A23: Corto Plazo Cliente | B23: Con Seguro | C23: Sin Seguro
A24: Capital | B24: =+#REF! -> #REF! | D24: Cuota | E24: =+PMT(B26,B28,B24) -> #REF!
A25: Tasa EA | B25: 0.2065 | C25: 0.1899
A26: Tasa MV | B26: 0.0164 | C26: 0.0146
A27: Plazo años | B27: 5
A28: Plazo meses | B28: =+B27*12 -> 60
A29: Seguro por millon | B29: 1159
A32: Mes | B32: 0 | C32: 1 | D32: 2 | E32: 3 | F32: 4 | G32: 5 | H32: 6 | I32: 7 | J32: 8 | K32: 9 | L32: 10 | M32: 11 | N32: 12 | O32: 13 | P32: 14 | Q32: 15 | R32: 16 | S32: 17 | T32: 18 | U32: 19 | V32: 20 | W32: 21 | X32: 22 | Y32: 23 | Z32: 24 | AA32: 25 | AB32: 26 | AC32: 27 | AD32: 28 | AE32: 29 | AF32: 30 | AG32: 31 | AH32: 32 | AI32: 33 | AJ32: 34 | AK32: 35 | AL32: 36 | AM32: 37 | AN32: 38 | AO32: 39 | AP32: 40 | AQ32: 41 | AR32: 42 | AS32: 43 | AT32: 44 | AU32: 45 | AV32: 46 | AW32: 47 | AX32: 48 | AY32: 49 | AZ32: 50 | BA32: 51 | BB32: 52 | BC32: 53 | BD32: 54 | BE32: 55 | BF32: 56 | BG32: 57 | BH32: 58 | BI32: 59 | BJ32: 60
A33: Saldo Capital | B33: =+B24 -> #REF! | C33: =+'Prestamo 5 años'!L5 -> 48993160 | D33: =+'Prestamo 5 años'!M5 -> 48563483 | E33: =+'Prestamo 5 años'!N5 -> 48124854 | F33: =+'Prestamo 5 años'!O5 -> 47677087 | G33: =+'Prestamo 5 años'!P5 -> 47219991 | H33: =+'Prestamo 5 años'!Q5 -> 46753372 | I33: =+'Prestamo 5 años'!R5 -> 46277033 | J33: =+'Prestamo 5 años'!S5 -> 45790769 | ... BJ33: =+'Prestamo 5 años'!BS5 -> 4.7683716e-07
A34: Pago a intereses | B34: 0 | C34: =+'Prestamo 5 años'!L4 -> 1029459.8 | D34: =+'Prestamo 5 años'!M4 -> 1020690.8 | E34: =+'Prestamo 5 años'!N4 -> 1011739.2 | F34: =+'Prestamo 5 años'!O4 -> 1002601.1 | G34: =+'Prestamo 5 años'!P4 -> 993272.64 | H34: =+'Prestamo 5 años'!Q4 -> 983749.81 | I34: =+'Prestamo 5 años'!R4 -> 974028.59 | J34: =+'Prestamo 5 años'!S4 -> 964104.85 | ... BJ34: =+'Prestamo 5 años'!BS4 -> 29599.353
A35: Pago a capital | B35: 0 | C35: =+'Prestamo 5 años'!L3 -> 420908.55 | D35: =+'Prestamo 5 años'!M3 -> 429677.48 | E35: =+'Prestamo 5 años'!N3 -> 438629.09 | F35: =+'Prestamo 5 años'!O3 -> 447767.2 | G35: =+'Prestamo 5 años'!P3 -> 457095.68 | H35: =+'Prestamo 5 años'!Q3 -> 466618.51 | I35: =+'Prestamo 5 años'!R3 -> 476339.72 | J35: =+'Prestamo 5 años'!S3 -> 486263.47 | ... BJ35: =+'Prestamo 5 años'!BS3 -> 1420769
A36: Cuota Total sin seguros | B36: 0 | C36: =+C34+C35 -> 1450368.3 | D36: =+D34+D35 -> 1450368.3 | E36: =+E34+E35 -> 1450368.3 | F36: =+F34+F35 -> 1450368.3 | G36: =+G34+G35 -> 1450368.3 | H36: =+H34+H35 -> 1450368.3 | I36: =+I34+I35 -> 1450368.3 | J36: =+J34+J35 -> 1450368.3 | ... BJ36: =+BJ34+BJ35 -> 1450368.3
A37: Seguros | B37: 0 | C37: =+'Prestamo 5 años'!L6 -> 56783.073 | D37: =+'Prestamo 5 años'!M6 -> 56285.077 | E37: =+'Prestamo 5 años'!N6 -> 55776.706 | F37: =+'Prestamo 5 años'!O6 -> 55257.743 | G37: =+'Prestamo 5 años'!P6 -> 54727.97 | H37: =+'Prestamo 5 años'!Q6 -> 54187.159 | I37: =+'Prestamo 5 años'!R6 -> 53635.081 | J37: =+'Prestamo 5 años'!S6 -> 53071.502 | ... BJ37: =+'Prestamo 5 años'!BS6 -> 5.5265427e-10
A38: Cuota total con seguros | B38: 0 | C38: =+C36+C37 -> 1507151.4 | D38: =+D36+D37 -> 1506653.4 | E38: =+E36+E37 -> 1506145 | F38: =+F36+F37 -> 1505626.1 | G38: =+G36+G37 -> 1505096.3 | H38: =+H36+H37 -> 1504555.5 | I38: =+I36+I37 -> 1504003.4 | J38: =+J36+J37 -> 1503439.8 | ... BJ38: =+BJ36+BJ37 -> 1450368.3
A40: Capital | B40: =+SUM(B35:BJ35) -> 49414069
A41: Intereses | B41: =+SUM(B34:BJ34) -> 37608030
A42: Seguros | B42: =+SUM(B37:BJ37) -> 2034939
A45: Mediano Plazo | B45: Con Seguro | C45: Sin Seguro
A46: Capital | B46: =+B2 -> #REF! | D46: Cuota | E46: =+PMT(B48,B50,B46) -> #REF!
A47: Tasa EA | B47: =+B3 -> 0.2065 | C47: =+C3 -> 0.1899
A48: Tasa MV | B48: =+B4 -> 0.0164 | C48: =+C4 -> 0.0146
A49: Plazo años | B49: 6
A50: Plazo meses | B50: =+B49*12 -> 72
A51: Seguro por millon | B51: =+B7 -> 1159
A54: Mes | B54: 0 | C54: 1 | D54: 2 | E54: 3 | F54: 4 | G54: 5 | H54: 6 | I54: 7 | J54: 8 | K54: 9 | L54: 10 | M54: 11 | N54: 12 | O54: 13 | P54: 14 | Q54: 15 | R54: 16 | S54: 17 | T54: 18 | U54: 19 | V54: 20 | W54: 21 | X54: 22 | Y54: 23 | Z54: 24 | AA54: 25 | AB54: 26 | AC54: 27 | AD54: 28 | AE54: 29 | AF54: 30 | AG54: 31 | AH54: 32 | AI54: 33 | AJ54: 34 | AK54: 35 | AL54: 36 | AM54: 37 | AN54: 38 | AO54: 39 | AP54: 40 | AQ54: 41 | AR54: 42 | AS54: 43 | AT54: 44 | AU54: 45 | AV54: 46 | AW54: 47 | AX54: 48 | AY54: 49 | AZ54: 50 | BA54: 51 | BB54: 52 | BC54: 53 | BD54: 54 | BE54: 55 | BF54: 56 | BG54: 57 | BH54: 58 | BI54: 59 | BJ54: 60 | BK54: 61 | BL54: 62 | BM54: 63 | BN54: 64 | BO54: 65 | BP54: 66 | BQ54: 67 | BR54: 68 | BS54: 69 | BT54: 70 | BU54: 71 | BV54: 72
A55: Saldo Capital | B55: =+B46 -> #REF! | C55: =+B55-C57 -> #REF! | D55: =+C55-D57 -> #REF! | E55: =+D55-E57 -> #REF! | F55: =+E55-F57 -> #REF! | G55: =+F55-G57 -> #REF! | H55: =+G55-H57 -> #REF! | I55: =+H55-I57 -> #REF! | J55: =+I55-J57 -> #REF! | ... BV55: =+BU55-BV57 -> #REF!
A56: Pago a intereses | B56: 0 | C56: =+B55*$C$48 -> #REF! | D56: =+C55*$C$48 -> #REF! | E56: =+D55*$C$48 -> #REF! | F56: =+E55*$C$48 -> #REF! | G56: =+F55*$C$48 -> #REF! | H56: =+G55*$C$48 -> #REF! | I56: =+H55*$C$48 -> #REF! | J56: =+I55*$C$48 -> #REF! | ... BV56: =+BU55*$C$48 -> #REF!
A57: Pago a capital | B57: 0 | C57: =+C58-C56 -> #REF! | D57: =+D58-D56 -> #REF! | E57: =+E58-E56 -> #REF! | F57: =+F58-F56 -> #REF! | G57: =+G58-G56 -> #REF! | H57: =+H58-H56 -> #REF! | I57: =+I58-I56 -> #REF! | J57: =+J58-J56 -> #REF! | ... BV57: =+BV58-BV56 -> #REF!
A58: Cuota Total sin seguros | B58: 0 | C58: =+PMT($C$48,$B$50,-$B$46,0) -> #REF! | D58: =+PMT($C$48,$B$50,-$B$46,0) -> #REF! | E58: =+PMT($C$48,$B$50,-$B$46,0) -> #REF! | F58: =+PMT($C$48,$B$50,-$B$46,0) -> #REF! | G58: =+PMT($C$48,$B$50,-$B$46,0) -> #REF! | H58: =+PMT($C$48,$B$50,-$B$46,0) -> #REF! | I58: =+PMT($C$48,$B$50,-$B$46,0) -> #REF! | J58: =+PMT($C$48,$B$50,-$B$46,0) -> #REF! | ... BV58: =+PMT($C$48,$B$50,-$B$46,0) -> #REF!
A59: Seguros | B59: 0 | C59: =+$B$51*(B55/1000000) -> #REF! | D59: =+$B$51*(C55/1000000) -> #REF! | E59: =+$B$51*(D55/1000000) -> #REF! | F59: =+$B$51*(E55/1000000) -> #REF! | G59: =+$B$51*(F55/1000000) -> #REF! | H59: =+$B$51*(G55/1000000) -> #REF! | I59: =+$B$51*(H55/1000000) -> #REF! | J59: =+$B$51*(I55/1000000) -> #REF! | ... BV59: =+$B$51*(BU55/1000000) -> #REF!
A60: Cuota total con seguros | B60: 0 | C60: =+PMT($B$48,$B$50,-$B$46,0) -> #REF! | D60: =+PMT($B$48,$B$50,-$B$46,0) -> #REF! | E60: =+PMT($B$48,$B$50,-$B$46,0) -> #REF! | F60: =+PMT($B$48,$B$50,-$B$46,0) -> #REF! | G60: =+PMT($B$48,$B$50,-$B$46,0) -> #REF! | H60: =+PMT($B$48,$B$50,-$B$46,0) -> #REF! | I60: =+PMT($B$48,$B$50,-$B$46,0) -> #REF! | J60: =+PMT($B$48,$B$50,-$B$46,0) -> #REF! | ... BV60: =+PMT($B$48,$B$50,-$B$46,0) -> #REF!
A62: Capital | B62: =+SUM(B57:BV57) -> #REF!
A63: Intereses | B63: =+SUM(B56:BV56) -> #REF!
A64: Seguros | B64: =+SUM(B59:BV59) -> #REF!
A67: Mediano Plazo Cliente | B67: Con Seguro | C67: Sin Seguro
A68: Capital | B68: =+B24 -> #REF! | D68: Cuota | E68: =+PMT(B70,B72,B68) -> #REF!
A69: Tasa EA | B69: =+B25 -> 0.2065 | C69: =+C25 -> 0.1899
A70: Tasa MV | B70: =+B26 -> 0.0164 | C70: =+C26 -> 0.0146
A71: Plazo años | B71: 7
A72: Plazo meses | B72: =+B71*12 -> 84
A73: Seguro por millon | B73: =+B29 -> 1159
A76: Mes | B76: 0 | C76: 1 | D76: 2 | E76: 3 | F76: 4 | G76: 5 | H76: 6 | I76: 7 | J76: 8 | K76: 9 | L76: 10 | M76: 11 | N76: 12 | O76: 13 | P76: 14 | Q76: 15 | R76: 16 | S76: 17 | T76: 18 | U76: 19 | V76: 20 | W76: 21 | X76: 22 | Y76: 23 | Z76: 24 | AA76: 25 | AB76: 26 | AC76: 27 | AD76: 28 | AE76: 29 | AF76: 30 | AG76: 31 | AH76: 32 | AI76: 33 | AJ76: 34 | AK76: 35 | AL76: 36 | AM76: 37 | AN76: 38 | AO76: 39 | AP76: 40 | AQ76: 41 | AR76: 42 | AS76: 43 | AT76: 44 | AU76: 45 | AV76: 46 | AW76: 47 | AX76: 48 | AY76: 49 | AZ76: 50 | BA76: 51 | BB76: 52 | BC76: 53 | BD76: 54 | BE76: 55 | BF76: 56 | BG76: 57 | BH76: 58 | BI76: 59 | BJ76: 60 | BK76: 61 | BL76: 62 | BM76: 63 | BN76: 64 | BO76: 65 | BP76: 66 | BQ76: 67 | BR76: 68 | BS76: 69 | BT76: 70 | BU76: 71 | BV76: 72 | BW76: 73 | BX76: 74 | BY76: 75 | BZ76: 76 | CA76: 77 | CB76: 78 | CC76: 79 | CD76: 80 | CE76: 81 | CF76: 82 | CG76: 83 | CH76: 84
A77: Saldo Capital | B77: =+B68 -> #REF! | C77: =+B77-C79 -> #REF! | D77: =+C77-D79 -> #REF! | E77: =+D77-E79 -> #REF! | F77: =+E77-F79 -> #REF! | G77: =+F77-G79 -> #REF! | H77: =+G77-H79 -> #REF! | I77: =+H77-I79 -> #REF! | J77: =+I77-J79 -> #REF! | ... CH77: =+CG77-CH79 -> #REF!
A78: Pago a intereses | B78: 0 | C78: =+B77*$C$70 -> #REF! | D78: =+C77*$C$70 -> #REF! | E78: =+D77*$C$70 -> #REF! | F78: =+E77*$C$70 -> #REF! | G78: =+F77*$C$70 -> #REF! | H78: =+G77*$C$70 -> #REF! | I78: =+H77*$C$70 -> #REF! | J78: =+I77*$C$70 -> #REF! | ... CH78: =+CG77*$C$70 -> #REF!
A79: Pago a capital | B79: 0 | C79: =+C80-C78 -> #REF! | D79: =+D80-D78 -> #REF! | E79: =+E80-E78 -> #REF! | F79: =+F80-F78 -> #REF! | G79: =+G80-G78 -> #REF! | H79: =+H80-H78 -> #REF! | I79: =+I80-I78 -> #REF! | J79: =+J80-J78 -> #REF! | ... CH79: =+CH80-CH78 -> #REF!
A80: Cuota Total sin seguros | B80: 0 | C80: =+PMT($C$70,$B$72,-$B$68,0) -> #REF! | D80: =+PMT($C$70,$B$72,-$B$68,0) -> #REF! | E80: =+PMT($C$70,$B$72,-$B$68,0) -> #REF! | F80: =+PMT($C$70,$B$72,-$B$68,0) -> #REF! | G80: =+PMT($C$70,$B$72,-$B$68,0) -> #REF! | H80: =+PMT($C$70,$B$72,-$B$68,0) -> #REF! | I80: =+PMT($C$70,$B$72,-$B$68,0) -> #REF! | J80: =+PMT($C$70,$B$72,-$B$68,0) -> #REF! | ... CH80: =+PMT($C$70,$B$72,-$B$68,0) -> #REF!
A81: Seguros | B81: 0 | C81: =+$B$73*(B77/1000000) -> #REF! | D81: =+$B$73*(C77/1000000) -> #REF! | E81: =+$B$73*(D77/1000000) -> #REF! | F81: =+$B$73*(E77/1000000) -> #REF! | G81: =+$B$73*(F77/1000000) -> #REF! | H81: =+$B$73*(G77/1000000) -> #REF! | I81: =+$B$73*(H77/1000000) -> #REF! | J81: =+$B$73*(I77/1000000) -> #REF! | ... CH81: =+$B$73*(CG77/1000000) -> #REF!
A82: Cuota total con seguros | B82: 0 | C82: =+PMT($B$70,$B$72,-$B$68,0) -> #REF! | D82: =+PMT($B$70,$B$72,-$B$68,0) -> #REF! | E82: =+PMT($B$70,$B$72,-$B$68,0) -> #REF! | F82: =+PMT($B$70,$B$72,-$B$68,0) -> #REF! | G82: =+PMT($B$70,$B$72,-$B$68,0) -> #REF! | H82: =+PMT($B$70,$B$72,-$B$68,0) -> #REF! | I82: =+PMT($B$70,$B$72,-$B$68,0) -> #REF! | J82: =+PMT($B$70,$B$72,-$B$68,0) -> #REF! | ... CH82: =+PMT($B$70,$B$72,-$B$68,0) -> #REF!
A84: Capital | B84: =+SUM(B79:BV79) -> #REF!
A85: Intereses | B85: =+SUM(B78:BV78) -> #REF!
A86: Seguros | B86: =+SUM(B81:BV81) -> #REF!
A89: Largo Plazo | B89: Con Seguro | C89: Sin Seguro
A90: Capital | B90: =+B46 -> #REF! | D90: Cuota | E90: =+PMT(B92,B94,B90) -> #REF!
A91: Tasa EA | B91: =+B47 -> 0.2065 | C91: =+C47 -> 0.1899
A92: Tasa MV | B92: =+B48 -> 0.0164 | C92: =+C48 -> 0.0146
A93: Plazo años | B93: 7
A94: Plazo meses | B94: =+B93*12 -> 84
A95: Seguro por millon | B95: =+B51 -> 1159
A98: Mes | B98: 0 | C98: 1 | D98: 2 | E98: 3 | F98: 4 | G98: 5 | H98: 6 | I98: 7 | J98: 8 | K98: 9 | L98: 10 | M98: 11 | N98: 12 | O98: 13 | P98: 14 | Q98: 15 | R98: 16 | S98: 17 | T98: 18 | U98: 19 | V98: 20 | W98: 21 | X98: 22 | Y98: 23 | Z98: 24 | AA98: 25 | AB98: 26 | AC98: 27 | AD98: 28 | AE98: 29 | AF98: 30 | AG98: 31 | AH98: 32 | AI98: 33 | AJ98: 34 | AK98: 35 | AL98: 36 | AM98: 37 | AN98: 38 | AO98: 39 | AP98: 40 | AQ98: 41 | AR98: 42 | AS98: 43 | AT98: 44 | AU98: 45 | AV98: 46 | AW98: 47 | AX98: 48 | AY98: 49 | AZ98: 50 | BA98: 51 | BB98: 52 | BC98: 53 | BD98: 54 | BE98: 55 | BF98: 56 | BG98: 57 | BH98: 58 | BI98: 59 | BJ98: 60 | BK98: 61 | BL98: 62 | BM98: 63 | BN98: 64 | BO98: 65 | BP98: 66 | BQ98: 67 | BR98: 68 | BS98: 69 | BT98: 70 | BU98: 71 | BV98: 72 | BW98: 73 | BX98: 74 | BY98: 75 | BZ98: 76 | CA98: 77 | CB98: 78 | CC98: 79 | CD98: 80 | CE98: 81 | CF98: 82 | CG98: 83 | CH98: 84
A99: Saldo Capital | B99: =+B90 -> #REF! | C99: =+B99-C101 -> #REF! | D99: =+C99-D101 -> #REF! | E99: =+D99-E101 -> #REF! | F99: =+E99-F101 -> #REF! | G99: =+F99-G101 -> #REF! | H99: =+G99-H101 -> #REF! | I99: =+H99-I101 -> #REF! | J99: =+I99-J101 -> #REF! | ... CH99: =+CG99-CH101 -> #REF!
A100: Pago a intereses | B100: 0 | C100: =+B99*$C$92 -> #REF! | D100: =+C99*$C$92 -> #REF! | E100: =+D99*$C$92 -> #REF! | F100: =+E99*$C$92 -> #REF! | G100: =+F99*$C$92 -> #REF! | H100: =+G99*$C$92 -> #REF! | I100: =+H99*$C$92 -> #REF! | J100: =+I99*$C$92 -> #REF! | ... CH100: =+CG99*$C$92 -> #REF!
A101: Pago a capital | B101: 0 | C101: =+C102-C100 -> #REF! | D101: =+D102-D100 -> #REF! | E101: =+E102-E100 -> #REF! | F101: =+F102-F100 -> #REF! | G101: =+G102-G100 -> #REF! | H101: =+H102-H100 -> #REF! | I101: =+I102-I100 -> #REF! | J101: =+J102-J100 -> #REF! | ... CH101: =+CH102-CH100 -> #REF!
A102: Cuota Total sin seguros | B102: 0 | C102: =+PMT($C$92,$B$94,-$B$90,0) -> #REF! | D102: =+PMT($C$92,$B$94,-$B$90,0) -> #REF! | E102: =+PMT($C$92,$B$94,-$B$90,0) -> #REF! | F102: =+PMT($C$92,$B$94,-$B$90,0) -> #REF! | G102: =+PMT($C$92,$B$94,-$B$90,0) -> #REF! | H102: =+PMT($C$92,$B$94,-$B$90,0) -> #REF! | I102: =+PMT($C$92,$B$94,-$B$90,0) -> #REF! | J102: =+PMT($C$92,$B$94,-$B$90,0) -> #REF! | ... CH102: =+PMT($C$92,$B$94,-$B$90,0) -> #REF!
A103: Seguros | B103: 0 | C103: =+$B$95*(B99/1000000) -> #REF! | D103: =+$B$95*(C99/1000000) -> #REF! | E103: =+$B$95*(D99/1000000) -> #REF! | F103: =+$B$95*(E99/1000000) -> #REF! | G103: =+$B$95*(F99/1000000) -> #REF! | H103: =+$B$95*(G99/1000000) -> #REF! | I103: =+$B$95*(H99/1000000) -> #REF! | J103: =+$B$95*(I99/1000000) -> #REF! | ... CH103: =+$B$95*(CG99/1000000) -> #REF!
A104: Cuota total con seguros | B104: 0 | C104: =+PMT($B$92,$B$94,-$B$90,0) -> #REF! | D104: =+PMT($B$92,$B$94,-$B$90,0) -> #REF! | E104: =+PMT($B$92,$B$94,-$B$90,0) -> #REF! | F104: =+PMT($B$92,$B$94,-$B$90,0) -> #REF! | G104: =+PMT($B$92,$B$94,-$B$90,0) -> #REF! | H104: =+PMT($B$92,$B$94,-$B$90,0) -> #REF! | I104: =+PMT($B$92,$B$94,-$B$90,0) -> #REF! | J104: =+PMT($B$92,$B$94,-$B$90,0) -> #REF! | ... CH104: =+PMT($B$92,$B$94,-$B$90,0) -> #REF!
A106: Capital | B106: =+SUM(B101:CH101) -> #REF!
A107: Intereses | B107: =+SUM(B100:CH100) -> #REF!
A108: Seguros | B108: =+SUM(B103:CH103) -> #REF!

Sheet Prestamo 15 años
B1: Calculadora de préstamos simple
L2: {=+TRANSPOSE(B10:B189)}
B3: Valores del préstamo | F3: Resumen del préstamo | K3: Capital | L3: {=+TRANSPOSE(F10:F189)}
B4: Importe del préstamo | D4: =+#REF! -> #REF! | F4: Pago mensual | H4: =IFERROR(IF(PréstamoPagado,PagoMensual,""), "") | K4: Intereses | L4: {=+TRANSPOSE(G10:G189)}
B5: Tasa de interés anual | D5: 0.13 | F5: Número de pagos | H5: =IFERROR(IF(PréstamoPagado,AñosPréstamo*12,""), "") | K5: Saldo Capital | L5: {=+TRANSPOSE(H10:H189)}
B6: Periodo del préstamo en años | D6: 15 | F6: Importe total de los intereses | H6: =IFERROR(IF(PréstamoPagado,CosteTotalPréstamo-CantidadPréstamo,""), "") | J6: 1159 | K6: Seguros | L6: =+(L5/1000000)*$J$6 -> #VALUE! | M6: =+(M5/1000000)*$J$6 -> #VALUE! | N6: =+(N5/1000000)*$J$6 -> #VALUE! | O6: =+(O5/1000000)*$J$6 -> #VALUE! | P6: =+(P5/1000000)*$J$6 -> #VALUE! | Q6: =+(Q5/1000000)*$J$6 -> #VALUE! | R6: =+(R5/1000000)*$J$6 -> #VALUE! | S6: =+(S5/1000000)*$J$6 -> #VALUE! | ... GI6: =+(GI5/1000000)*$J$6 -> #VALUE!
B7: Fecha de inicio del préstamo | D7: =TODAY() -> 46301 | F7: Coste total del préstamo | H7: =IFERROR(IF(PréstamoPagado,PagoMensual*NúmeroDePagos,""), "") | K7: Total | L7: =+L3+L4+L6 -> #VALUE! | M7: =+M3+M4+M6 -> #VALUE! | N7: =+N3+N4+N6 -> #VALUE! | O7: =+O3+O4+O6 -> #VALUE! | P7: =+P3+P4+P6 -> #VALUE! | Q7: =+Q3+Q4+Q6 -> #VALUE! | R7: =+R3+R4+R6 -> #VALUE! | S7: =+S3+S4+S6 -> #VALUE! | ... GI7: =+GI3+GI4+GI6 -> #VALUE!
B9: N.° de pago | C9: Fecha de pago | D9: Saldo inicial | E9: Pago | F9: Capital | G9: Intereses | H9: Saldo final
B10: =IFERROR(IF(PréstamoNoPagado*PréstamoPagado,NúmeroDePago,""), "") | C10: =IFERROR(IF(PréstamoNoPagado*PréstamoPagado,FechaDePago,""), "") | D10: =IFERROR(IF(PréstamoNoPagado*PréstamoPagado,ValorPréstamo,""), "") | E10: =IFERROR(IF(PréstamoNoPagado*PréstamoPagado,PagoMensual,""), "") | F10: =IFERROR(IF(PréstamoNoPagado*PréstamoPagado,Capital,""), "") | G10: =IFERROR(IF(PréstamoNoPagado*PréstamoPagado,AmortizaciónInterés,""), "") | H10: =IFERROR(IF(PréstamoNoPagado*PréstamoPagado,SaldoFinal,""), "")
B11: =IFERROR(IF(PréstamoNoPagado*PréstamoPagado,NúmeroDePago,""), "") | C11: =IFERROR(IF(PréstamoNoPagado*PréstamoPagado,FechaDePago,""), "") | D11: =IFERROR(IF(PréstamoNoPagado*PréstamoPagado,ValorPréstamo,""), "") | E11: =IFERROR(IF(PréstamoNoPagado*PréstamoPagado,PagoMensual,""), "") | F11: =IFERROR(IF(PréstamoNoPagado*PréstamoPagado,Capital,""), "") | G11: =IFERROR(IF(PréstamoNoPagado*PréstamoPagado,AmortizaciónInterés,""), "") | H11: =IFERROR(IF(PréstamoNoPagado*PréstamoPagado,SaldoFinal,""), "")
B12: =IFERROR(IF(PréstamoNoPagado*PréstamoPagado,NúmeroDePago,""), "") | C12: =IFERROR(IF(PréstamoNoPagado*PréstamoPagado,FechaDePago,""), "") | D12: =IFERROR(IF(PréstamoNoPagado*PréstamoPagado,ValorPréstamo,""), "") | E12: =IFERROR(IF(PréstamoNoPagado*PréstamoPagado,PagoMensual,""), "") | F12: =IFERROR(IF(PréstamoNoPagado*PréstamoPagado,Capital,""), "") | G12: =IFERROR(IF(PréstamoNoPagado*PréstamoPagado,AmortizaciónInterés,""), "") | H12: =IFERROR(IF(PréstamoNoPagado*PréstamoPagado,SaldoFinal,""), "")
B13: =IFERROR(IF(PréstamoNoPagado*PréstamoPagado,NúmeroDePago,""), "") | C13: =IFERROR(IF(PréstamoNoPagado*PréstamoPagado,FechaDePago,""), "") | D13: =IFERROR(IF(PréstamoNoPagado*PréstamoPagado,ValorPréstamo,""), "") | E13: =IFERROR(IF(PréstamoNoPagado*PréstamoPagado,PagoMensual,""), "") | F13: =IFERROR(IF(PréstamoNoPagado*PréstamoPagado,Capital,""), "") | G13: =IFERROR(IF(PréstamoNoPagado*PréstamoPagado,AmortizaciónInterés,""), "") | H13: =IFERROR(IF(PréstamoNoPagado*PréstamoPagado,SaldoFinal,""), "")
B14: =IFERROR(IF(PréstamoNoPagado*PréstamoPagado,NúmeroDePago,""), "") | C14: =IFERROR(IF(PréstamoNoPagado*PréstamoPagado,FechaDePago,""), "") | D14: =IFERROR(IF(PréstamoNoPagado*PréstamoPagado,ValorPréstamo,""), "") | E14: =IFERROR(IF(PréstamoNoPagado*PréstamoPagado,PagoMensual,""), "") | F14: =IFERROR(IF(PréstamoNoPagado*PréstamoPagado,Capital,""), "") | G14: =IFERROR(IF(PréstamoNoPagado*PréstamoPagado,AmortizaciónInterés,""), "") | H14: =IFERROR(IF(PréstamoNoPagado*PréstamoPagado,SaldoFinal,""), "")
B15: =IFERROR(IF(PréstamoNoPagado*PréstamoPagado,NúmeroDePago,""), "") | C15: =IFERROR(IF(PréstamoNoPagado*PréstamoPagado,FechaDePago,""), "") | D15: =IFERROR(IF(PréstamoNoPagado*PréstamoPagado,ValorPréstamo,""), "") | E15: =IFERROR(IF(PréstamoNoPagado*PréstamoPagado,PagoMensual,""), "") | F15: =IFERROR(IF(PréstamoNoPagado*PréstamoPagado,Capital,""), "") | G15: =IFERROR(IF(PréstamoNoPagado*PréstamoPagado,AmortizaciónInterés,""), "") | H15: =IFERROR(IF(PréstamoNoPagado*PréstamoPagado,SaldoFinal,""), "")
B16: =IFERROR(IF(PréstamoNoPagado*PréstamoPagado,NúmeroDePago,""), "") | C16: =IFERROR(IF(PréstamoNoPagado*PréstamoPagado,FechaDePago,""), "") | D16: =IFERROR(IF(PréstamoNoPagado*PréstamoPagado,ValorPréstamo,""), "") | E16: =IFERROR(IF(PréstamoNoPagado*PréstamoPagado,PagoMensual,""), "") | F16: =IFERROR(IF(PréstamoNoPagado*PréstamoPagado,Capital,""), "") | G16: =IFERROR(IF(PréstamoNoPagado*PréstamoPagado,AmortizaciónInterés,""), "") | H16: =IFERROR(IF(PréstamoNoPagado*PréstamoPagado,SaldoFinal,""), "")
B17: =IFERROR(IF(PréstamoNoPagado*PréstamoPagado,NúmeroDePago,""), "") | C17: =IFERROR(IF(PréstamoNoPagado*PréstamoPagado,FechaDePago,""), "") | D17: =IFERROR(IF(PréstamoNoPagado*PréstamoPagado,ValorPréstamo,""), "") | E17: =IFERROR(IF(PréstamoNoPagado*PréstamoPagado,PagoMensual,""), "") | F17: =IFERROR(IF(PréstamoNoPagado*PréstamoPagado,Capital,""), "") | G17: =IFERROR(IF(PréstamoNoPagado*PréstamoPagado,AmortizaciónInterés,""), "") | H17: =IFERROR(IF(PréstamoNoPagado*PréstamoPagado,SaldoFinal,""), "")
B18: =IFERROR(IF(PréstamoNoPagado*PréstamoPagado,NúmeroDePago,""), "") | C18: =IFERROR(IF(PréstamoNoPagado*PréstamoPagado,FechaDePago,""), "") | D18: =IFERROR(IF(PréstamoNoPagado*PréstamoPagado,ValorPréstamo,""), "") | E18: =IFERROR(IF(PréstamoNoPagado*PréstamoPagado,PagoMensual,""), "") | F18: =IFERROR(IF(PréstamoNoPagado*PréstamoPagado,Capital,""), "") | G18: =IFERROR(IF(PréstamoNoPagado*PréstamoPagado,AmortizaciónInterés,""), "") | H18: =IFERROR(IF(PréstamoNoPagado*PréstamoPagado,SaldoFinal,""), "")
B19: =IFERROR(IF(PréstamoNoPagado*PréstamoPagado,NúmeroDePago,""), "") | C19: =IFERROR(IF(PréstamoNoPagado*PréstamoPagado,FechaDePago,""), "") | D19: =IFERROR(IF(PréstamoNoPagado*PréstamoPagado,ValorPréstamo,""), "") | E19: =IFERROR(IF(PréstamoNoPagado*PréstamoPagado,PagoMensual,""), "") | F19: =IFERROR(IF(PréstamoNoPagado*PréstamoPagado,Capital,""), "") | G19: =IFERROR(IF(PréstamoNoPagado*PréstamoPagado,AmortizaciónInterés,""), "") | H19: =IFERROR(IF(PréstamoNoPagado*PréstamoPagado,SaldoFinal,""), "")
B20: =IFERROR(IF(PréstamoNoPagado*PréstamoPagado,NúmeroDePago,""), "") | C20: =IFERROR(IF(PréstamoNoPagado*PréstamoPagado,FechaDePago,""), "") | D20: =IFERROR(IF(PréstamoNoPagado*PréstamoPagado,ValorPréstamo,""), "") | E20: =IFERROR(IF(PréstamoNoPagado*PréstamoPagado,PagoMensual,""), "") | F20: =IFERROR(IF(PréstamoNoPagado*PréstamoPagado,Capital,""), "") | G20: =IFERROR(IF(PréstamoNoPagado*PréstamoPagado,AmortizaciónInterés,""), "") | H20: =IFERROR(IF(PréstamoNoPagado*PréstamoPagado,SaldoFinal,""), "")
B21: =IFERROR(IF(PréstamoNoPagado*PréstamoPagado,NúmeroDePago,""), "") | C21: =IFERROR(IF(PréstamoNoPagado*PréstamoPagado,FechaDePago,""), "") | D21: =IFERROR(IF(PréstamoNoPagado*PréstamoPagado,ValorPréstamo,""), "") | E21: =IFERROR(IF(PréstamoNoPagado*PréstamoPagado,PagoMensual,""), "") | F21: =IFERROR(IF(PréstamoNoPagado*PréstamoPagado,Capital,""), "") | G21: =IFERROR(IF(PréstamoNoPagado*PréstamoPagado,AmortizaciónInterés,""), "") | H21: =IFERROR(IF(PréstamoNoPagado*PréstamoPagado,SaldoFinal,""), "")
... B369: =IFERROR(IF(PréstamoNoPagado*PréstamoPagado,NúmeroDePago,""), "") | C369: =IFERROR(IF(PréstamoNoPagado*PréstamoPagado,FechaDePago,""), "") | D369: =IFERROR(IF(PréstamoNoPagado*PréstamoPagado,ValorPréstamo,""), "") | E369: =IFERROR(IF(PréstamoNoPagado*PréstamoPagado,PagoMensual,""), "") | F369: =IFERROR(IF(PréstamoNoPagado*PréstamoPagado,Capital,""), "") | G369: =IFERROR(IF(PréstamoNoPagado*PréstamoPagado,AmortizaciónInterés,""), "") | H369: =IFERROR(IF(PréstamoNoPagado*PréstamoPagado,SaldoFinal,""), "")

Sheet Comparativo
C2: Francisco Alcala | D2: MarjorieCosto | E2: Marjorie Venta | F2: Celsia Habitat
B3: A todo costo | C3: 3800 | D3: =+#REF! -> #REF! | E3: =+#REF! -> #REF! | F3: =316854696/70000 -> 4526.4957
B4: Equipos | D4: =+#REF! -> #REF!
B5: Diseños | D5: =+#REF! -> #REF!
B6: Materiales | D6: =+#REF!+#REF!+#REF!+#REF!+#REF!+#REF!+#REF! -> #REF!
B7: Certificación | D7: =+#REF! -> #REF!
B8: Solo MO | C8: 500 | D8: =+#REF! -> #REF!
B9: Materiales y MO | C9: 1500 | D9: =+D8+D6 -> #REF!
B16: Decradación anual
B17: Año | C17: 1 | D17: 2 | E17: 3 | F17: 4 | G17: 5 | H17: 6 | I17: 7 | J17: 8 | K17: 9 | L17: 10 | M17: 11 | N17: 12 | O17: 13 | P17: 14 | Q17: 15 | R17: 16 | S17: 17 | T17: 18 | U17: 19 | V17: 20 | W17: 21 | X17: 22 | Y17: 23 | Z17: 24 | AA17: 25
B18: Con degradación de acuerdo a gráfico | C18: 0.98 | D18: 0.978 | E18: 0.977 | F18: 0.976 | G18: 0.975 | H18: 0.97 | I18: 0.965 | J18: 0.96 | K18: 0.955 | L18: 0.95 | M18: 0.94 | N18: 0.93 | O18: 0.92 | P18: 0.91 | Q18: 0.9 | R18: 0.89 | S18: 0.88 | T18: 0.87 | U18: 0.86 | V18: 0.85 | W18: 0.845 | X18: 0.84 | Y18: 0.835 | Z18: 0.832 | AA18: 0.831
B19: Con degradación anual del 0,45% | C19: =+C18 -> 0.98 | D19: =+C19-0.45% -> 0.9755 | E19: =+D19-0.45% -> 0.971 | F19: =+E19-0.45% -> 0.9665 | G19: =+F19-0.45% -> 0.962 | H19: =+G19-0.45% -> 0.9575 | I19: =+H19-0.45% -> 0.953 | J19: =+I19-0.45% -> 0.9485 | K19: =+J19-0.45% -> 0.944 | ... AA19: =+Z19-0.45% -> 0.872
C25: =+Producción!J3 -> 45658 | D25: =+Producción!K3 -> 45689 | E25: =+Producción!L3 -> 45717 | F25: =+Producción!M3 -> 45748 | G25: =+Producción!N3 -> 45778 | H25: =+Producción!O3 -> 45809 | I25: =+Producción!P3 -> 45839 | J25: =+Producción!Q3 -> 45870 | ... N25: =+Producción!U3 -> 45992 | O25: Total año
B26: SALVA kWh-mes | C26: =+Producción!J8 -> 2150.5786 | D26: =+Producción!K8 -> 1982.636 | E26: =+Producción!L8 -> 2360.8296 | F26: =+Producción!M8 -> 2144.5576 | G26: =+Producción!N8 -> 2079.2997 | H26: =+Producción!O8 -> 2090.0679 | I26: =+Producción!P8 -> 2224.0865 | J26: =+Producción!Q8 -> 2191.452 | ... N26: =+Producción!U8 -> 1867.9423 | O26: =+SUM(C26:N26) -> 24758.348
B27: PV System kWh-mes | C27: 1498 | D27: 1369 | E27: 1670 | F27: 1621 | G27: 1636 | H27: 1645 | I27: 1691 | J27: 1628 | K27: 1423 | L27: 1279 | M27: 1221 | N27: 1301 | O27: =+SUM(C27:N27) -> 17982
B28: Diferencia kWh-mes | C28: =+C27-C26 -> -652.57863 | D28: =+D27-D26 -> -613.63604 | E28: =+E27-E26 -> -690.82965 | F28: =+F27-F26 -> -523.55757 | G28: =+G27-G26 -> -443.29971 | H28: =+H27-H26 -> -445.0679 | I28: =+I27-I26 -> -533.08653 | J28: =+J27-J26 -> -563.45204 | ... O28: =+O27-O26 -> -6776.3476

Sheet Producción
A1: Potencia Sistema | B1: =+Cálculos!D8 -> 15950 | E1: Wp
B2: Total | E2: =+YEAR(E3) -> 2024 | F2: =+YEAR(F3) -> 2024 | G2: =+YEAR(G3) -> 2024 | H2: =+YEAR(H3) -> 2024 | I2: =+YEAR(I3) -> 2024 | J2: =+YEAR(J3) -> 2025 | K2: =+YEAR(K3) -> 2025 | L2: =+YEAR(L3) -> 2025 | ... IO2: =+YEAR(IO3) -> 2044
A3: Producción | E3: 45505 | F3: 45536 | G3: 45566 | H3: 45597 | I3: 45627 | J3: 45658 | K3: 45689 | L3: 45717 | M3: 45748 | N3: 45778 | O3: 45809 | P3: 45839 | Q3: 45870 | R3: 45901 | S3: 45931 | T3: 45962 | U3: 45992 | V3: 46023 | W3: 46054 | X3: 46082 | Y3: 46113 | Z3: 46143 | AA3: 46174 | AB3: 46204 | AC3: 46235 | AD3: 46266 | AE3: 46296 | AF3: 46327 | AG3: 46357 | AH3: 46388 | AI3: 46419 | AJ3: 46447 | AK3: 46478 | AL3: 46508 | AM3: 46539 | AN3: 46569 | AO3: 46600 | AP3: 46631 | AQ3: 46661 | AR3: 46692 | AS3: 46722 | AT3: 46753 | AU3: 46784 | AV3: 46813 | AW3: 46844 | AX3: 46874 | AY3: 46905 | AZ3: 46935 | BA3: 46966 | BB3: 46997 | BC3: 47027 | BD3: 47058 | BE3: 47088 | BF3: 47119 | BG3: 47150 | BH3: 47178 | BI3: 47209 | BJ3: 47239 | BK3: 47270 | BL3: 47300 | BM3: 47331 | BN3: 47362 | BO3: 47392 | BP3: 47423 | BQ3: 47453 | BR3: 47484 | BS3: 47515 | BT3: 47543 | BU3: 47574 | BV3: 47604 | BW3: 47635 | BX3: 47665 | BY3: 47696 | BZ3: 47727 | CA3: 47757 | CB3: 47788 | CC3: 47818 | CD3: 47849 | CE3: 47880 | CF3: 47908 | CG3: 47939 | CH3: 47969 | CI3: 48000 | CJ3: 48030 | CK3: 48061 | CL3: 48092 | CM3: 48122 | CN3: 48153 | CO3: 48183 | CP3: 48214 | CQ3: 48245 | CR3: 48274 | CS3: 48305 | CT3: 48335 | CU3: 48366 | CV3: 48396 | CW3: 48427 | CX3: 48458 | CY3: 48488 | CZ3: 48519 | DA3: 48549 | DB3: 48580 | DC3: 48611 | DD3: 48639 | DE3: 48670 | DF3: 48700 | DG3: 48731 | DH3: 48761 | DI3: 48792 | DJ3: 48823 | DK3: 48853 | DL3: 48884 | DM3: 48914 | DN3: 48945 | DO3: 48976 | DP3: 49004 | DQ3: 49035 | DR3: 49065 | DS3: 49096 | DT3: 49126 | DU3: 49157 | DV3: 49188 | DW3: 49218 | DX3: 49249 | DY3: 49279 | DZ3: 49310 | EA3: 49341 | EB3: 49369 | EC3: 49400 | ED3: 49430 | EE3: 49461 | EF3: 49491 | EG3: 49522 | EH3: 49553 | EI3: 49583 | EJ3: 49614 | EK3: 49644 | EL3: 49675 | EM3: 49706 | EN3: 49735 | EO3: 49766 | EP3: 49796 | EQ3: 49827 | ER3: 49857 | ES3: 49888 | ET3: 49919 | EU3: 49949 | EV3: 49980 | EW3: 50010 | EX3: 50041 | EY3: 50072 | EZ3: 50100 | FA3: 50131 | FB3: 50161 | FC3: 50192 | FD3: 50222 | FE3: 50253 | FF3: 50284 | FG3: 50314 | FH3: 50345 | FI3: 50375 | FJ3: 50406 | FK3: 50437 | FL3: 50465 | FM3: 50496 | FN3: 50526 | FO3: 50557 | FP3: 50587 | FQ3: 50618 | FR3: 50649 | FS3: 50679 | FT3: 50710 | FU3: 50740 | FV3: 50771 | FW3: 50802 | FX3: 50830 | FY3: 50861 | FZ3: 50891 | GA3: 50922 | GB3: 50952 | GC3: 50983 | GD3: 51014 | GE3: 51044 | GF3: 51075 | GG3: 51105 | GH3: 51136 | GI3: 51167 | GJ3: 51196 | GK3: 51227 | GL3: 51257 | GM3: 51288 | GN3: 51318 | GO3: 51349 | GP3: 51380 | GQ3: 51410 | GR3: 51441 | GS3: 51471 | GT3: 51502 | GU3: 51533 | GV3: 51561 | GW3: 51592 | GX3: 51622 | GY3: 51653 | GZ3: 51683 | HA3: 51714 | HB3: 51745 | HC3: 51775 | HD3: 51806 | HE3: 51836 | HF3: 51867 | HG3: 51898 | HH3: 51926 | HI3: 51957 | HJ3: 51987 | HK3: 52018 | HL3: 52048 | HM3: 52079 | HN3: 52110 | HO3: 52140 | HP3: 52171 | HQ3: 52201 | HR3: 52232 | HS3: 52263 | HT3: 52291 | HU3: 52322 | HV3: 52352 | HW3: 52383 | HX3: 52413 | HY3: 52444 | HZ3: 52475 | IA3: 52505 | IB3: 52536 | IC3: 52566 | ID3: 52597 | IE3: 52628 | IF3: 52657 | IG3: 52688 | IH3: 52718 | II3: 52749 | IJ3: 52779 | IK3: 52810 | IL3: 52841 | IM3: 52871 | IN3: 52902 | IO3: 52932
A4: No. Dias | E4: 31 | F4: 30 | G4: 31 | H4: 30 | I4: 31 | J4: 31 | K4: 28 | L4: 31 | M4: 30 | N4: 31 | O4: 30 | P4: 31 | Q4: 31 | R4: 30 | S4: 31 | T4: 30 | U4: 31 | V4: 31 | W4: 28 | X4: 31 | Y4: 30 | Z4: 31 | AA4: 30 | AB4: 31 | AC4: 31 | AD4: 30 | AE4: 31 | AF4: 30 | AG4: 31 | AH4: 31 | AI4: 28 | AJ4: 31 | AK4: 30 | AL4: 31 | AM4: 30 | AN4: 31 | AO4: 31 | AP4: 30 | AQ4: 31 | AR4: 30 | AS4: 31 | AT4: 31 | AU4: 29 | AV4: 31 | AW4: 30 | AX4: 31 | AY4: 30 | AZ4: 31 | BA4: 31 | BB4: 30 | BC4: 31 | BD4: 30 | BE4: 31 | BF4: 31 | BG4: 28 | BH4: 31 | BI4: 30 | BJ4: 31 | BK4: 30 | BL4: 31 | BM4: 31 | BN4: 30 | BO4: 31 | BP4: 30 | BQ4: 31 | BR4: 31 | BS4: 28 | BT4: 31 | BU4: 30 | BV4: 31 | BW4: 30 | BX4: 31 | BY4: 31 | BZ4: 30 | CA4: 31 | CB4: 30 | CC4: 31 | CD4: 31 | CE4: 28 | CF4: 31 | CG4: 30 | CH4: 31 | CI4: 30 | CJ4: 31 | CK4: 31 | CL4: 30 | CM4: 31 | CN4: 30 | CO4: 31 | CP4: 31 | CQ4: 29 | CR4: 31 | CS4: 30 | CT4: 31 | CU4: 30 | CV4: 31 | CW4: 31 | CX4: 30 | CY4: 31 | CZ4: 30 | DA4: 31 | DB4: 31 | DC4: 28 | DD4: 31 | DE4: 30 | DF4: 31 | DG4: 30 | DH4: 31 | DI4: 31 | DJ4: 30 | DK4: 31 | DL4: 30 | DM4: 31 | DN4: 31 | DO4: 28 | DP4: 31 | DQ4: 30 | DR4: 31 | DS4: 30 | DT4: 31 | DU4: 31 | DV4: 31 | DW4: 31 | DX4: 31 | DY4: 31 | DZ4: 31 | EA4: 28 | EB4: 31 | EC4: 30 | ED4: 31 | EE4: 30 | EF4: 31 | EG4: 31 | EH4: 31 | EI4: 31 | EJ4: 31 | EK4: 31 | EL4: 31 | EM4: 29 | EN4: 31 | EO4: 30 | EP4: 31 | EQ4: 30 | ER4: 31 | ES4: 31 | ET4: 31 | EU4: 31 | EV4: 31 | EW4: 31 | EX4: 31 | EY4: 28 | EZ4: 31 | FA4: 30 | FB4: 31 | FC4: 30 | FD4: 31 | FE4: 31 | FF4: 31 | FG4: 31 | FH4: 31 | FI4: 31 | FJ4: 31 | FK4: 28 | FL4: 31 | FM4: 30 | FN4: 31 | FO4: 30 | FP4: 31 | FQ4: 31 | FR4: 31 | FS4: 31 | FT4: 31 | FU4: 31 | FV4: 31 | FW4: 28 | FX4: 31 | FY4: 30 | FZ4: 31 | GA4: 30 | GB4: 31 | GC4: 31 | GD4: 31 | GE4: 31 | GF4: 31 | GG4: 31 | GH4: 31 | GI4: 29 | GJ4: 31 | GK4: 30 | GL4: 31 | GM4: 30 | GN4: 31 | GO4: 31 | GP4: 31 | GQ4: 31 | GR4: 31 | GS4: 31 | GT4: 31 | GU4: 28 | GV4: 31 | GW4: 30 | GX4: 31 | GY4: 30 | GZ4: 31 | HA4: 31 | HB4: 31 | HC4: 31 | HD4: 31 | HE4: 31 | HF4: 31 | HG4: 28 | HH4: 31 | HI4: 30 | HJ4: 31 | HK4: 30 | HL4: 31 | HM4: 31 | HN4: 31 | HO4: 31 | HP4: 31 | HQ4: 31 | HR4: 31 | HS4: 28 | HT4: 31 | HU4: 30 | HV4: 31 | HW4: 30 | HX4: 31 | HY4: 31 | HZ4: 31 | IA4: 31 | IB4: 31 | IC4: 31 | ID4: 31 | IE4: 29 | IF4: 31 | IG4: 30 | IH4: 31 | II4: 30 | IJ4: 31 | IK4: 30.714286 | IL4: 30.785714 | IM4: 30.857143 | IN4: 30.928571 | IO4: 31
A5: Eficiencia | E5: =+Comparativo!C18 -> 0.98 | F5: =+E5 -> 0.98 | G5: =+F5 -> 0.98 | H5: =+G5 -> 0.98 | I5: =+H5 -> 0.98 | J5: =+I5 -> 0.98 | K5: =+J5 -> 0.98 | L5: =+K5 -> 0.98 | M5: =+L5 -> 0.98 | ... P5: =+O5 -> 0.98 | Q5: =+Comparativo!D18 -> 0.978 | R5: =+Q5 -> 0.978 | S5: =+R5 -> 0.978 | T5: =+S5 -> 0.978 | U5: =+T5 -> 0.978 | V5: =+U5 -> 0.978 | W5: =+V5 -> 0.978 | X5: =+W5 -> 0.978 | Y5: =+X5 -> 0.978 | ... AB5: =+AA5 -> 0.978 | AC5: =+Comparativo!E18 -> 0.977 | AD5: =+AC5 -> 0.977 | AE5: =+AD5 -> 0.977 | AF5: =+AE5 -> 0.977 | AG5: =+AF5 -> 0.977 | AH5: =+AG5 -> 0.977 | AI5: =+AH5 -> 0.977 | AJ5: =+AI5 -> 0.977 | AK5: =+AJ5 -> 0.977 | ... AN5: =+AM5 -> 0.977 | AO5: =+Comparativo!F18 -> 0.976 | AP5: =+AO5 -> 0.976 | AQ5: =+AP5 -> 0.976 | AR5: =+AQ5 -> 0.976 | AS5: =+AR5 -> 0.976 | AT5: =+AS5 -> 0.976 | AU5: =+AT5 -> 0.976 | AV5: =+AU5 -> 0.976 | AW5: =+AV5 -> 0.976 | ... AZ5: =+AY5 -> 0.976 | BA5: =+Comparativo!G18 -> 0.975 | BB5: =+BA5 -> 0.975 | BC5: =+BB5 -> 0.975 | BD5: =+BC5 -> 0.975 | BE5: =+BD5 -> 0.975 | BF5: =+BE5 -> 0.975 | BG5: =+BF5 -> 0.975 | BH5: =+BG5 -> 0.975 | BI5: =+BH5 -> 0.975 | ... BL5: =+BK5 -> 0.975 | BM5: =+Comparativo!H18 -> 0.97 | BN5: =+BM5 -> 0.97 | BO5: =+BN5 -> 0.97 | BP5: =+BO5 -> 0.97 | BQ5: =+BP5 -> 0.97 | BR5: =+BQ5 -> 0.97 | BS5: =+BR5 -> 0.97 | BT5: =+BS5 -> 0.97 | BU5: =+BT5 -> 0.97 | ... BX5: =+BW5 -> 0.97 | BY5: =+Comparativo!I18 -> 0.965 | BZ5: =+BY5 -> 0.965 | CA5: =+BZ5 -> 0.965 | CB5: =+CA5 -> 0.965 | CC5: =+CB5 -> 0.965 | CD5: =+CC5 -> 0.965 | CE5: =+CD5 -> 0.965 | CF5: =+CE5 -> 0.965 | CG5: =+CF5 -> 0.965 | ... CJ5: =+CI5 -> 0.965 | CK5: =+Comparativo!J18 -> 0.96 | CL5: =+CK5 -> 0.96 | CM5: =+CL5 -> 0.96 | CN5: =+CM5 -> 0.96 | CO5: =+CN5 -> 0.96 | CP5: =+CO5 -> 0.96 | CQ5: =+CP5 -> 0.96 | CR5: =+CQ5 -> 0.96 | CS5: =+CR5 -> 0.96 | ... CV5: =+CU5 -> 0.96 | CW5: =+Comparativo!K18 -> 0.955 | CX5: =+CW5 -> 0.955 | CY5: =+CX5 -> 0.955 | CZ5: =+CY5 -> 0.955 | DA5: =+CZ5 -> 0.955 | DB5: =+DA5 -> 0.955 | DC5: =+DB5 -> 0.955 | DD5: =+DC5 -> 0.955 | DE5: =+DD5 -> 0.955 | ... DH5: =+DG5 -> 0.955 | DI5: =+Comparativo!L18 -> 0.95 | DJ5: =+DI5 -> 0.95 | DK5: =+DJ5 -> 0.95 | DL5: =+DK5 -> 0.95 | DM5: =+DL5 -> 0.95 | DN5: =+DM5 -> 0.95 | DO5: =+DN5 -> 0.95 | DP5: =+DO5 -> 0.95 | DQ5: =+DP5 -> 0.95 | ... DT5: =+DS5 -> 0.95 | DU5: =+Comparativo!M18 -> 0.94 | DV5: =+DU5 -> 0.94 | DW5: =+DV5 -> 0.94 | DX5: =+DW5 -> 0.94 | DY5: =+DX5 -> 0.94 | DZ5: =+DY5 -> 0.94 | EA5: =+DZ5 -> 0.94 | EB5: =+EA5 -> 0.94 | EC5: =+EB5 -> 0.94 | ... EF5: =+EE5 -> 0.94 | EG5: =+Comparativo!N18 -> 0.93 | EH5: =+EG5 -> 0.93 | EI5: =+EH5 -> 0.93 | EJ5: =+EI5 -> 0.93 | EK5: =+EJ5 -> 0.93 | EL5: =+EK5 -> 0.93 | EM5: =+EL5 -> 0.93 | EN5: =+EM5 -> 0.93 | EO5: =+EN5 -> 0.93 | ... ER5: =+EQ5 -> 0.93 | ES5: =+Comparativo!O18 -> 0.92 | ET5: =+ES5 -> 0.92 | EU5: =+ET5 -> 0.92 | EV5: =+EU5 -> 0.92 | EW5: =+EV5 -> 0.92 | EX5: =+EW5 -> 0.92 | EY5: =+EX5 -> 0.92 | EZ5: =+EY5 -> 0.92 | FA5: =+EZ5 -> 0.92 | ... FD5: =+FC5 -> 0.92 | FE5: =+Comparativo!P18 -> 0.91 | FF5: =+FE5 -> 0.91 | FG5: =+FF5 -> 0.91 | FH5: =+FG5 -> 0.91 | FI5: =+FH5 -> 0.91 | FJ5: =+FI5 -> 0.91 | FK5: =+FJ5 -> 0.91 | FL5: =+FK5 -> 0.91 | FM5: =+FL5 -> 0.91 | ... FP5: =+FO5 -> 0.91 | FQ5: =+Comparativo!Q18 -> 0.9 | FR5: =+FQ5 -> 0.9 | FS5: =+FR5 -> 0.9 | FT5: =+FS5 -> 0.9 | FU5: =+FT5 -> 0.9 | FV5: =+FU5 -> 0.9 | FW5: =+FV5 -> 0.9 | FX5: =+FW5 -> 0.9 | FY5: =+FX5 -> 0.9 | ... GB5: =+GA5 -> 0.9 | GC5: =+Comparativo!R18 -> 0.89 | GD5: =+GC5 -> 0.89 | GE5: =+GD5 -> 0.89 | GF5: =+GE5 -> 0.89 | GG5: =+GF5 -> 0.89 | GH5: =+GG5 -> 0.89 | GI5: =+GH5 -> 0.89 | GJ5: =+GI5 -> 0.89 | GK5: =+GJ5 -> 0.89 | ... GN5: =+GM5 -> 0.89 | GO5: =+Comparativo!S18 -> 0.88 | GP5: =+GO5 -> 0.88 | GQ5: =+GP5 -> 0.88 | GR5: =+GQ5 -> 0.88 | GS5: =+GR5 -> 0.88 | GT5: =+GS5 -> 0.88 | GU5: =+GT5 -> 0.88 | GV5: =+GU5 -> 0.88 | GW5: =+GV5 -> 0.88 | ... GZ5: =+GY5 -> 0.88 | HA5: =+Comparativo!T18 -> 0.87 | HB5: =+HA5 -> 0.87 | HC5: =+HB5 -> 0.87 | HD5: =+HC5 -> 0.87 | HE5: =+HD5 -> 0.87 | HF5: =+HE5 -> 0.87 | HG5: =+HF5 -> 0.87 | HH5: =+HG5 -> 0.87 | HI5: =+HH5 -> 0.87 | ... HL5: =+HK5 -> 0.87 | HM5: =+Comparativo!U18 -> 0.86 | HN5: =+HM5 -> 0.86 | HO5: =+HN5 -> 0.86 | HP5: =+HO5 -> 0.86 | HQ5: =+HP5 -> 0.86 | HR5: =+HQ5 -> 0.86 | HS5: =+HR5 -> 0.86 | HT5: =+HS5 -> 0.86 | HU5: =+HT5 -> 0.86 | ... HX5: =+HW5 -> 0.86 | HY5: =+Comparativo!V18 -> 0.85 | HZ5: =+HY5 -> 0.85 | IA5: =+HZ5 -> 0.85 | IB5: =+IA5 -> 0.85 | IC5: =+IB5 -> 0.85 | ID5: =+IC5 -> 0.85 | IE5: =+ID5 -> 0.85 | IF5: =+IE5 -> 0.85 | IG5: =+IF5 -> 0.85 | ... IO5: =+IN5 -> 0.85
A6: HSP | E6: =+Datos2!H56 -> 5.46 | F6: =+Datos2!I56 -> 5.28 | G6: =+Datos2!J56 -> 4.84 | H6: =+Datos2!K56 -> 4.72 | I6: =+Datos2!L56 -> 5.22 | J6: =+Datos2!A56 -> 5.69 | K6: =+Datos2!B56 -> 6.04 | L6: =+Datos2!C56 -> 5.87 | M6: =+Datos2!D56 -> 5.51 | N6: =+Datos2!E56 -> 5.17 | O6: =+Datos2!F56 -> 5.37 | P6: =+Datos2!G56 -> 5.53 | Q6: =+E6 -> 5.46 | R6: =+F6 -> 5.28 | S6: =+G6 -> 4.84 | T6: =+H6 -> 4.72 | U6: =+I6 -> 5.22 | V6: =+J6 -> 5.69 | W6: =+K6 -> 6.04 | X6: =+L6 -> 5.87 | ... IO6: =+IC6 -> 5.22
A7: PR | E7: =+Q7 -> 0.83 | F7: =+R7 -> 0.83 | G7: =+S7 -> 0.79 | H7: =+T7 -> 0.8 | I7: =+U7 -> 0.74 | J7: 0.78 | K7: 0.75 | L7: 0.83 | M7: 0.83 | N7: 0.83 | O7: 0.83 | P7: 0.83 | Q7: 0.83 | R7: 0.83 | S7: 0.79 | T7: 0.8 | U7: 0.74 | V7: =+J7 -> 0.78 | W7: =+K7 -> 0.75 | X7: =+L7 -> 0.83 | Y7: =+M7 -> 0.83 | Z7: =+N7 -> 0.83 | AA7: =+O7 -> 0.83 | AB7: =+P7 -> 0.83 | AC7: =+Q7 -> 0.83 | ... IO7: =+IC7 -> 0.74
A8: Energia Producida (kWh-mes) | B8: =+SUM(E8:IO8) -> 481211.07 | E8: =+($B$1*E4*E5*E6*E7)/1000 -> 2195.9335 | F8: =+($B$1*F4*F5*F6*F7)/1000 -> 2055.0388 | G8: =+($B$1*G4*G5*G6*G7)/1000 -> 1852.7674 | H8: =+($B$1*H4*H5*H6*H7)/1000 -> 1770.6797 | I8: =+($B$1*I4*I5*I6*I7)/1000 -> 1871.7622 | J8: =+($B$1*J4*J5*J6*J7)/1000 -> 2150.5786 | K8: =+($B$1*K4*K5*K6*K7)/1000 -> 1982.636 | L8: =+($B$1*L4*L5*L6*L7)/1000 -> 2360.8296 | ... IO8: =+($B$1*IO4*IO5*IO6*IO7)/1000 -> 1623.4672
A9: Energía Consumida (kWh-mes) | B9: =+SUM(E9:IJ9) -> 419500 | E9: =+Datos2!U6 -> 1361 | F9: =+Datos2!V6 -> 1712 | G9: =+Datos2!W6 -> 1565 | H9: =+Datos2!X6 -> 2143 | I9: =+Datos2!Y6 -> 2131 | J9: =+Datos2!Z6 -> 2409 | K9: =+Datos2!O6 -> 2063 | L9: =+Datos2!P6 -> 1931 | M9: =+Datos2!Q6 -> 1439 | N9: =+Datos2!R6 -> 1428 | O9: =+Datos2!S6 -> 1562 | P9: =+Datos2!T6 -> 1231 | Q9: =+Datos2!U6 -> 1361 | R9: =+Datos2!V6 -> 1712 | ... V9: =+Datos2!Z6 -> 2409 | W9: =+K9 -> 2063 | X9: =+L9 -> 1931 | Y9: =+M9 -> 1439 | Z9: =+N9 -> 1428 | AA9: =+O9 -> 1562 | AB9: =+P9 -> 1231 | AC9: =+Q9 -> 1361 | AD9: =+R9 -> 1712 | ... IO9: =+IC9 -> 2131
A10: Autoconsumo | E10: =+Liquidación!E73 -> 831.52462 | F10: =+Liquidación!F73 -> 998.68043 | G10: =+Liquidación!G73 -> 910.55471 | H10: =+Liquidación!H73 -> 1176.3603 | I10: =+Liquidación!I73 -> 1179.9824 | J10: =+Liquidación!J73 -> 1337.1029 | K10: =+Liquidación!K73 -> 1158.0208 | L10: =+Liquidación!L73 -> 1129.6226 | ... P10: =+Liquidación!P73 -> 767.90694 | Q10: =+E10*(1-(E5-Q5)) -> 829.86157 | R10: =+F10*(1-(F5-R5)) -> 996.68307 | S10: =+G10*(1-(G5-S5)) -> 908.7336 | T10: =+H10*(1-(H5-T5)) -> 1174.0076 | U10: =+I10*(1-(I5-U5)) -> 1177.6224 | V10: =+J10*(1-(J5-V5)) -> 1334.4287 | W10: =+K10*(1-(K5-W5)) -> 1155.7048 | X10: =+L10*(1-(L5-X5)) -> 1127.3633 | ... IO10: =+IC10*(1-(IC5-IO5)) -> 1035.5472
A11: Importación | E11: =+Liquidación!E74 -> 529.47538 | F11: =+Liquidación!F74 -> 713.31957 | G11: =+Liquidación!G74 -> 654.44529 | H11: =+Liquidación!H74 -> 966.63972 | I11: =+Liquidación!I74 -> 951.0176 | J11: =+Liquidación!J74 -> 1071.8971 | K11: =+Liquidación!K74 -> 904.9792 | L11: =+Liquidación!L74 -> 801.37741 | ... P11: =+Liquidación!P74 -> 463.09306 | Q11: =+E11*(1-(E5-Q5)) -> 528.41643 | R11: =+F11*(1-(F5-R5)) -> 711.89293 | S11: =+G11*(1-(G5-S5)) -> 653.1364 | T11: =+H11*(1-(H5-T5)) -> 964.70644 | U11: =+I11*(1-(I5-U5)) -> 949.11556 | V11: =+J11*(1-(J5-V5)) -> 1069.7533 | W11: =+K11*(1-(K5-W5)) -> 903.16924 | X11: =+L11*(1-(L5-X5)) -> 799.77466 | ... IO11: =+IC11*(1-(IC5-IO5)) -> 834.6087
A12: Total Excedentes | E12: =+Liquidación!E75 -> 1364.4089 | F12: =+Liquidación!F75 -> 1056.3584 | G12: =+Liquidación!G75 -> 942.21273 | H12: =+Liquidación!H75 -> 594.3194 | I12: =+Liquidación!I75 -> 691.77983 | J12: =+Liquidación!J75 -> 813.47573 | K12: =+Liquidación!K75 -> 824.61524 | L12: =+Liquidación!L75 -> 1231.2071 | ... P12: =+Liquidación!P75 -> 1456.1796 | Q12: =+E12*(1-(E5-Q5)) -> 1361.6801 | R12: =+F12*(1-(F5-R5)) -> 1054.2457 | S12: =+G12*(1-(G5-S5)) -> 940.32831 | T12: =+H12*(1-(H5-T5)) -> 593.13076 | U12: =+I12*(1-(I5-U5)) -> 690.39627 | V12: =+J12*(1-(J5-V5)) -> 811.84878 | W12: =+K12*(1-(K5-W5)) -> 822.966 | X12: =+L12*(1-(L5-X5)) -> 1228.7446 | ... IO12: =+IC12*(1-(IC5-IO5)) -> 607.10282
A13: Excedentes T1 con crédito | E13: =+Liquidación!E76 -> 529.47538 | F13: =+Liquidación!F76 -> 713.31957 | G13: =+Liquidación!G76 -> 654.44529 | H13: =+Liquidación!H76 -> 594.3194 | I13: =+Liquidación!I76 -> 691.77983 | J13: =+Liquidación!J76 -> 813.47573 | K13: =+Liquidación!K76 -> 824.61524 | L13: =+Liquidación!L76 -> 801.37741 | ... P13: =+Liquidación!P76 -> 463.09306 | Q13: =+E13 -> 529.47538 | R13: =+F13 -> 713.31957 | S13: =+G13 -> 654.44529 | T13: =+H13 -> 594.3194 | U13: =+I13 -> 691.77983 | V13: =+J13 -> 813.47573 | W13: =+K13 -> 824.61524 | X13: =+L13 -> 801.37741 | ... IO13: =+IC13 -> 691.77983
A14: Importación sin crédito | E14: =+Liquidación!E77 -> 0 | F14: =+Liquidación!F77 -> 0 | G14: =+Liquidación!G77 -> 0 | H14: =+Liquidación!H77 -> 372.32032 | I14: =+Liquidación!I77 -> 259.23777 | J14: =+Liquidación!J77 -> 258.42137 | K14: =+Liquidación!K77 -> 80.36396 | L14: =+Liquidación!L77 -> 0 | ... P14: =+Liquidación!P77 -> 0 | Q14: =+E14 -> 0 | R14: =+F14 -> 0 | S14: =+G14 -> 0 | T14: =+H14 -> 372.32032 | U14: =+I14 -> 259.23777 | V14: =+J14 -> 258.42137 | W14: =+K14 -> 80.36396 | X14: =+L14 -> 0 | ... IO14: =+IC14 -> 259.23777
A15: Excedentes tipo 2 | E15: =+Liquidación!E78 -> -834.93354 | F15: =+Liquidación!F78 -> -343.03883 | G15: =+Liquidación!G78 -> -287.76744 | H15: =+Liquidación!H78 -> 0 | I15: =+Liquidación!I78 -> 0 | J15: =+Liquidación!J78 -> 0 | K15: =+Liquidación!K78 -> 0 | L15: =+Liquidación!L78 -> -429.82965 | ... P15: =+Liquidación!P78 -> -993.08653 | Q15: =+E15 -> -834.93354 | R15: =+F15 -> -343.03883 | S15: =+G15 -> -287.76744 | T15: =+H15 -> 0 | U15: =+I15 -> 0 | V15: =+J15 -> 0 | W15: =+K15 -> 0 | X15: =+L15 -> -429.82965 | ... IO15: =+IC15 -> 0
A17: IPC | B17: =+Tarifas!B2 -> 0.03
E18: =+YEAR(E19) -> 2024 | F18: =+YEAR(F19) -> 2024 | G18: =+YEAR(G19) -> 2024 | H18: =+YEAR(H19) -> 2024 | I18: =+YEAR(I19) -> 2024 | J18: =+YEAR(J19) -> 2025 | K18: =+YEAR(K19) -> 2025 | L18: =+YEAR(L19) -> 2025 | ... IO18: =+YEAR(IO19) -> 2044
A19: Costos para el cliente CP | B19: Total | C19: Capital Propio | D19: Pareto | E19: 45505 | F19: 45536 | G19: 45566 | H19: 45597 | I19: 45627 | J19: 45658 | K19: 45689 | L19: 45717 | M19: 45748 | N19: 45778 | O19: 45809 | P19: 45839 | Q19: 45870 | R19: 45901 | S19: 45931 | T19: 45962 | U19: 45992 | V19: 46023 | W19: 46054 | X19: 46082 | Y19: 46113 | Z19: 46143 | AA19: 46174 | AB19: 46204 | AC19: 46235 | AD19: 46266 | AE19: 46296 | AF19: 46327 | AG19: 46357 | AH19: 46388 | AI19: 46419 | AJ19: 46447 | AK19: 46478 | AL19: 46508 | AM19: 46539 | AN19: 46569 | AO19: 46600 | AP19: 46631 | AQ19: 46661 | AR19: 46692 | AS19: 46722 | AT19: 46753 | AU19: 46784 | AV19: 46813 | AW19: 46844 | AX19: 46874 | AY19: 46905 | AZ19: 46935 | BA19: 46966 | BB19: 46997 | BC19: 47027 | BD19: 47058 | BE19: 47088 | BF19: 47119 | BG19: 47150 | BH19: 47178 | BI19: 47209 | BJ19: 47239 | BK19: 47270 | BL19: 47300 | BM19: 47331 | BN19: 47362 | BO19: 47392 | BP19: 47423 | BQ19: 47453 | BR19: 47484 | BS19: 47515 | BT19: 47543 | BU19: 47574 | BV19: 47604 | BW19: 47635 | BX19: 47665 | BY19: 47696 | BZ19: 47727 | CA19: 47757 | CB19: 47788 | CC19: 47818 | CD19: 47849 | CE19: 47880 | CF19: 47908 | CG19: 47939 | CH19: 47969 | CI19: 48000 | CJ19: 48030 | CK19: 48061 | CL19: 48092 | CM19: 48122 | CN19: 48153 | CO19: 48183 | CP19: 48214 | CQ19: 48245 | CR19: 48274 | CS19: 48305 | CT19: 48335 | CU19: 48366 | CV19: 48396 | CW19: 48427 | CX19: 48458 | CY19: 48488 | CZ19: 48519 | DA19: 48549 | DB19: 48580 | DC19: 48611 | DD19: 48639 | DE19: 48670 | DF19: 48700 | DG19: 48731 | DH19: 48761 | DI19: 48792 | DJ19: 48823 | DK19: 48853 | DL19: 48884 | DM19: 48914 | DN19: 48945 | DO19: 48976 | DP19: 49004 | DQ19: 49035 | DR19: 49065 | DS19: 49096 | DT19: 49126 | DU19: 49157 | DV19: 49188 | DW19: 49218 | DX19: 49249 | DY19: 49279 | DZ19: 49310 | EA19: 49341 | EB19: 49369 | EC19: 49400 | ED19: 49430 | EE19: 49461 | EF19: 49491 | EG19: 49522 | EH19: 49553 | EI19: 49583 | EJ19: 49614 | EK19: 49644 | EL19: 49675 | EM19: 49706 | EN19: 49735 | EO19: 49766 | EP19: 49796 | EQ19: 49827 | ER19: 49857 | ES19: 49888 | ET19: 49919 | EU19: 49949 | EV19: 49980 | EW19: 50010 | EX19: 50041 | EY19: 50072 | EZ19: 50100 | FA19: 50131 | FB19: 50161 | FC19: 50192 | FD19: 50222 | FE19: 50253 | FF19: 50284 | FG19: 50314 | FH19: 50345 | FI19: 50375 | FJ19: 50406 | FK19: 50437 | FL19: 50465 | FM19: 50496 | FN19: 50526 | FO19: 50557 | FP19: 50587 | FQ19: 50618 | FR19: 50649 | FS19: 50679 | FT19: 50710 | FU19: 50740 | FV19: 50771 | FW19: 50802 | FX19: 50830 | FY19: 50861 | FZ19: 50891 | GA19: 50922 | GB19: 50952 | GC19: 50983 | GD19: 51014 | GE19: 51044 | GF19: 51075 | GG19: 51105 | GH19: 51136 | GI19: 51167 | GJ19: 51196 | GK19: 51227 | GL19: 51257 | GM19: 51288 | GN19: 51318 | GO19: 51349 | GP19: 51380 | GQ19: 51410 | GR19: 51441 | GS19: 51471 | GT19: 51502 | GU19: 51533 | GV19: 51561 | GW19: 51592 | GX19: 51622 | GY19: 51653 | GZ19: 51683 | HA19: 51714 | HB19: 51745 | HC19: 51775 | HD19: 51806 | HE19: 51836 | HF19: 51867 | HG19: 51898 | HH19: 51926 | HI19: 51957 | HJ19: 51987 | HK19: 52018 | HL19: 52048 | HM19: 52079 | HN19: 52110 | HO19: 52140 | HP19: 52171 | HQ19: 52201 | HR19: 52232 | HS19: 52263 | HT19: 52291 | HU19: 52322 | HV19: 52352 | HW19: 52383 | HX19: 52413 | HY19: 52444 | HZ19: 52475 | IA19: 52505 | IB19: 52536 | IC19: 52566 | ID19: 52597 | IE19: 52628 | IF19: 52657 | IG19: 52688 | IH19: 52718 | II19: 52749 | IJ19: 52779 | IK19: 52810 | IL19: 52841 | IM19: 52871 | IN19: 52902 | IO19: 52932
A20: Amortización | B20: =+SUM(E20:IJ20) -> 89057038 | C20: =+'Capex GoodWe'!M152 -> 49414069 | D20: =+B20/$B$27 -> 1.4772247 | AF20: =+'Prestamo 5 años'!L7 -> 1507151.4 | AG20: =+'Prestamo 5 años'!M7 -> 1506653.4 | AH20: =+'Prestamo 5 años'!N7 -> 1506145 | AI20: =+'Prestamo 5 años'!O7 -> 1505626.1 | AJ20: =+'Prestamo 5 años'!P7 -> 1505096.3 | AK20: =+'Prestamo 5 años'!Q7 -> 1504555.5 | AL20: =+'Prestamo 5 años'!R7 -> 1504003.4 | AM20: =+'Prestamo 5 años'!S7 -> 1503439.8 | ... IO20: =+'Prestamo 5 años'!HU7 -> 0
A21: Capital | AF21: =+'Prestamo 5 años'!L3 -> 420908.55 | AG21: =+'Prestamo 5 años'!M3 -> 429677.48 | AH21: =+'Prestamo 5 años'!N3 -> 438629.09 | AI21: =+'Prestamo 5 años'!O3 -> 447767.2 | AJ21: =+'Prestamo 5 años'!P3 -> 457095.68 | AK21: =+'Prestamo 5 años'!Q3 -> 466618.51 | AL21: =+'Prestamo 5 años'!R3 -> 476339.72 | AM21: =+'Prestamo 5 años'!S3 -> 486263.47 | ... IO21: =+'Prestamo 5 años'!HU3 -> 0
A22: Interéses | AF22: =+'Prestamo 5 años'!L4 -> 1029459.8 | AG22: =+'Prestamo 5 años'!M4 -> 1020690.8 | AH22: =+'Prestamo 5 años'!N4 -> 1011739.2 | AI22: =+'Prestamo 5 años'!O4 -> 1002601.1 | AJ22: =+'Prestamo 5 años'!P4 -> 993272.64 | AK22: =+'Prestamo 5 años'!Q4 -> 983749.81 | AL22: =+'Prestamo 5 años'!R4 -> 974028.59 | AM22: =+'Prestamo 5 años'!S4 -> 964104.85 | ... IO22: =+'Prestamo 5 años'!HU4 -> 0
A23: Seguros | AF23: =+'Prestamo 5 años'!L6 -> 56783.073 | AG23: =+'Prestamo 5 años'!M6 -> 56285.077 | AH23: =+'Prestamo 5 años'!N6 -> 55776.706 | AI23: =+'Prestamo 5 años'!O6 -> 55257.743 | AJ23: =+'Prestamo 5 años'!P6 -> 54727.97 | AK23: =+'Prestamo 5 años'!Q6 -> 54187.159 | AL23: =+'Prestamo 5 años'!R6 -> 53635.081 | AM23: =+'Prestamo 5 años'!S6 -> 53071.502 | ... IO23: =+'Prestamo 5 años'!HU6 -> 0
A24: Mantenimiento | B24: =+SUM(V24:CC24) -> 3290000 | C24: =+B24 -> 3290000 | D24: =+B24/$B$27 -> 0.054572544 | AH24: =+'Capex GoodWe'!C194 -> 200000 | AK24: =+'Capex GoodWe'!C194*(1+Tarifas!B2) -> 206000 | AN24: =AK24 -> 206000 | AO24: =AL24 -> 0 | AP24: =AM24 -> 0 | AQ24: =AN24 -> 206000 | AR24: =AO24 -> 0 | AS24: =AP24 -> 0 | AT24: =AQ24 -> 206000 | AU24: =AR24 -> 0 | ... IO24: =IL24 -> 0
A25: Reposición | B25: =+SUM(E25:BQ25) -> 0 | C25: =+B25 -> 0 | D25: =+B25/$B$27 -> 0 | BR25: 0 | BS25: 0 | BT25: 0 | BU25: 0 | BV25: 0 | BW25: =(0.015*'Capex GoodWe'!M161)/12 -> 61767.586 | BX25: =+BW25 -> 61767.586 | BY25: =+BX25 -> 61767.586 | BZ25: =+BY25 -> 61767.586 | CA25: =+BZ25 -> 61767.586 | CB25: =+CA25 -> 61767.586 | CC25: =+CB25 -> 61767.586 | CD25: =+CC25*(1+$B$17) -> 63620.614 | CE25: =+CD25 -> 63620.614 | CF25: =+CE25 -> 63620.614 | CG25: =+CF25 -> 63620.614 | CH25: =+CG25 -> 63620.614 | CI25: =+CH25 -> 63620.614 | CJ25: =+CI25 -> 63620.614 | CK25: =+CJ25 -> 63620.614 | CL25: =+CK25 -> 63620.614 | ... CO25: =+CN25 -> 63620.614 | CP25: =+CO25*(1+$B$17) -> 65529.232 | CQ25: =+CP25 -> 65529.232 | CR25: =+CQ25 -> 65529.232 | CS25: =+CR25 -> 65529.232 | CT25: =+CS25 -> 65529.232 | CU25: =+CT25 -> 65529.232 | CV25: =+CU25 -> 65529.232 | CW25: =+CV25 -> 65529.232 | CX25: =+CW25 -> 65529.232 | ... DA25: =+CZ25 -> 65529.232 | DB25: =+DA25*(1+$B$17) -> 67495.109 | DC25: =+DB25 -> 67495.109 | DD25: =+DC25 -> 67495.109 | DE25: =+DD25 -> 67495.109 | DF25: =+DE25 -> 67495.109 | DG25: =+DF25 -> 67495.109 | DH25: =+DG25 -> 67495.109 | DI25: =+DH25 -> 67495.109 | DJ25: =+DI25 -> 67495.109 | ... DM25: =+DL25 -> 67495.109 | DN25: =+DM25*(1+$B$17) -> 69519.962 | DO25: =+DN25 -> 69519.962 | DP25: =+DO25 -> 69519.962 | DQ25: =+DP25 -> 69519.962 | DR25: =+DQ25 -> 69519.962 | DS25: =+DR25 -> 69519.962 | DT25: =+DS25 -> 69519.962 | DU25: =+DT25 -> 69519.962 | DV25: =+DU25 -> 69519.962 | ... DY25: =+DX25 -> 69519.962 | DZ25: =+DY25*(1+$B$17) -> 71605.561 | EA25: =+DZ25 -> 71605.561 | EB25: =+EA25 -> 71605.561 | EC25: =+EB25 -> 71605.561 | ED25: =+EC25 -> 71605.561 | EE25: =+ED25 -> 71605.561 | EF25: =+EE25 -> 71605.561 | EG25: =+EF25 -> 71605.561 | EH25: =+EG25 -> 71605.561 | ... EK25: =+EJ25 -> 71605.561 | EL25: =+EK25*(1+$B$17) -> 73753.728 | EM25: =+EL25 -> 73753.728 | EN25: =+EM25 -> 73753.728 | EO25: =+EN25 -> 73753.728 | EP25: =+EO25 -> 73753.728 | EQ25: =+EP25 -> 73753.728 | ER25: =+EQ25 -> 73753.728 | ES25: =+ER25 -> 73753.728 | ET25: =+ES25 -> 73753.728 | ... EW25: =+EV25 -> 73753.728 | EX25: =+EW25*(1+$B$17) -> 75966.34 | EY25: =+EX25 -> 75966.34 | EZ25: =+EY25 -> 75966.34 | FA25: =+EZ25 -> 75966.34 | FB25: =+FA25 -> 75966.34 | FC25: =+FB25 -> 75966.34 | FD25: =+FC25 -> 75966.34 | FE25: =+FD25 -> 75966.34 | FF25: =+FE25 -> 75966.34 | ... FI25: =+FH25 -> 75966.34 | FJ25: =+FI25*(1+$B$17) -> 78245.33 | FK25: =+FJ25 -> 78245.33 | FL25: =+FK25 -> 78245.33 | FM25: =+FL25 -> 78245.33 | FN25: =+FM25 -> 78245.33 | FO25: =+FN25 -> 78245.33 | FP25: =+FO25 -> 78245.33 | FQ25: =+FP25 -> 78245.33 | FR25: =+FQ25 -> 78245.33 | ... FU25: =+FT25 -> 78245.33 | FV25: =+FU25*(1+$B$17) -> 80592.69 | FW25: =+FV25 -> 80592.69 | FX25: =+FW25 -> 80592.69 | FY25: =+FX25 -> 80592.69 | FZ25: =+FY25 -> 80592.69 | GA25: =+FZ25 -> 80592.69 | GB25: =+GA25 -> 80592.69 | GC25: =+GB25 -> 80592.69 | GD25: =+GC25 -> 80592.69 | ... GG25: =+GF25 -> 80592.69 | GH25: =+GG25*(1+$B$17) -> 83010.471 | GI25: =+GH25 -> 83010.471 | GJ25: =+GI25 -> 83010.471 | GK25: =+GJ25 -> 83010.471 | GL25: =+GK25 -> 83010.471 | GM25: =+GL25 -> 83010.471 | GN25: =+GM25 -> 83010.471 | GO25: =+GN25 -> 83010.471 | GP25: =+GO25 -> 83010.471 | ... GS25: =+GR25 -> 83010.471 | GT25: =+GS25*(1+$B$17) -> 85500.785 | GU25: =+GT25 -> 85500.785 | GV25: =+GU25 -> 85500.785 | GW25: =+GV25 -> 85500.785 | GX25: =+GW25 -> 85500.785 | GY25: =+GX25 -> 85500.785 | GZ25: =+GY25 -> 85500.785 | HA25: =+GZ25 -> 85500.785 | HB25: =+HA25 -> 85500.785 | ... HE25: =+HD25 -> 85500.785 | HF25: =+HE25*(1+$B$17) -> 88065.808 | HG25: =+HF25 -> 88065.808 | HH25: =+HG25 -> 88065.808 | HI25: =+HH25 -> 88065.808 | HJ25: =+HI25 -> 88065.808 | HK25: =+HJ25 -> 88065.808 | HL25: =+HK25 -> 88065.808 | HM25: =+HL25 -> 88065.808 | HN25: =+HM25 -> 88065.808 | ... HQ25: =+HP25 -> 88065.808 | HR25: =+HQ25*(1+$B$17) -> 90707.783 | HS25: =+HR25 -> 90707.783 | HT25: =+HS25 -> 90707.783 | HU25: =+HT25 -> 90707.783 | HV25: =+HU25 -> 90707.783 | HW25: =+HV25 -> 90707.783 | HX25: =+HW25 -> 90707.783 | HY25: =+HX25 -> 90707.783 | HZ25: =+HY25 -> 90707.783 | ... IC25: =+IB25 -> 90707.783 | ID25: =+IC25*(1+$B$17) -> 93429.016 | IE25: =+ID25 -> 93429.016 | IF25: =+IE25 -> 93429.016 | IG25: =+IF25 -> 93429.016 | IH25: =+IG25 -> 93429.016 | II25: =+IH25 -> 93429.016 | IJ25: =+II25 -> 93429.016 | IK25: =+IJ25 -> 93429.016 | IL25: =+IK25 -> 93429.016 | ... IO25: =+IN25 -> 93429.016
A26: Operación | B26: =+SUM(V26:CC26) -> 1342740.7 | C26: =+B26 -> 1342740.7 | D26: =+B26/$B$27 -> 0.022272577 | AF26: ='Capex GoodWe'!C195 -> 25000 | AG26: =+AF26 -> 25000 | AH26: =+AG26*(1+$B$17) -> 25750 | AI26: =+AH26 -> 25750 | AJ26: =+AI26 -> 25750 | AK26: =+AJ26 -> 25750 | AL26: =+AK26 -> 25750 | AM26: =+AL26 -> 25750 | AN26: =+AM26 -> 25750 | AO26: =+AN26 -> 25750 | AP26: =+AO26 -> 25750 | ... AS26: =+AR26 -> 25750 | AT26: =+AS26*(1+$B$17) -> 26522.5 | AU26: =+AT26 -> 26522.5 | AV26: =+AU26 -> 26522.5 | AW26: =+AV26 -> 26522.5 | AX26: =+AW26 -> 26522.5 | AY26: =+AX26 -> 26522.5 | AZ26: =+AY26 -> 26522.5 | BA26: =+AZ26 -> 26522.5 | BB26: =+BA26 -> 26522.5 | ... BE26: =+BD26 -> 26522.5 | BF26: =+BE26*(1+$B$17) -> 27318.175 | BG26: =+BF26 -> 27318.175 | BH26: =+BG26 -> 27318.175 | BI26: =+BH26 -> 27318.175 | BJ26: =+BI26 -> 27318.175 | BK26: =+BJ26 -> 27318.175 | BL26: =+BK26 -> 27318.175 | BM26: =+BL26 -> 27318.175 | BN26: =+BM26 -> 27318.175 | ... BQ26: =+BP26 -> 27318.175 | BR26: =+BQ26*(1+$B$17) -> 28137.72 | BS26: =+BR26 -> 28137.72 | BT26: =+BS26 -> 28137.72 | BU26: =+BT26 -> 28137.72 | BV26: =+BU26 -> 28137.72 | BW26: =+BV26 -> 28137.72 | BX26: =+BW26 -> 28137.72 | BY26: =+BX26 -> 28137.72 | BZ26: =+BY26 -> 28137.72 | ... CC26: =+CB26 -> 28137.72 | CD26: =+CC26*(1+$B$17) -> 28981.852 | CE26: =+CD26 -> 28981.852 | CF26: =+CE26 -> 28981.852 | CG26: =+CF26 -> 28981.852 | CH26: =+CG26 -> 28981.852 | CI26: =+CH26 -> 28981.852 | CJ26: =+CI26 -> 28981.852 | CK26: =+CJ26 -> 28981.852 | CL26: =+CK26 -> 28981.852 | ... CO26: =+CN26 -> 28981.852 | CP26: =+CO26*(1+$B$17) -> 29851.307 | CQ26: =+CP26 -> 29851.307 | CR26: =+CQ26 -> 29851.307 | CS26: =+CR26 -> 29851.307 | CT26: =+CS26 -> 29851.307 | CU26: =+CT26 -> 29851.307 | CV26: =+CU26 -> 29851.307 | CW26: =+CV26 -> 29851.307 | CX26: =+CW26 -> 29851.307 | ... DA26: =+CZ26 -> 29851.307 | DB26: =+DA26*(1+$B$17) -> 30746.847 | DC26: =+DB26 -> 30746.847 | DD26: =+DC26 -> 30746.847 | DE26: =+DD26 -> 30746.847 | DF26: =+DE26 -> 30746.847 | DG26: =+DF26 -> 30746.847 | DH26: =+DG26 -> 30746.847 | DI26: =+DH26 -> 30746.847 | DJ26: =+DI26 -> 30746.847 | ... DM26: =+DL26 -> 30746.847 | DN26: =+DM26*(1+$B$17) -> 31669.252 | DO26: =+DN26 -> 31669.252 | DP26: =+DO26 -> 31669.252 | DQ26: =+DP26 -> 31669.252 | DR26: =+DQ26 -> 31669.252 | DS26: =+DR26 -> 31669.252 | DT26: =+DS26 -> 31669.252 | DU26: =+DT26 -> 31669.252 | DV26: =+DU26 -> 31669.252 | ... DY26: =+DX26 -> 31669.252 | DZ26: =+DY26*(1+$B$17) -> 32619.33 | EA26: =+DZ26 -> 32619.33 | EB26: =+EA26 -> 32619.33 | EC26: =+EB26 -> 32619.33 | ED26: =+EC26 -> 32619.33 | EE26: =+ED26 -> 32619.33 | EF26: =+EE26 -> 32619.33 | EG26: =+EF26 -> 32619.33 | EH26: =+EG26 -> 32619.33 | ... EK26: =+EJ26 -> 32619.33 | EL26: =+EK26*(1+$B$17) -> 33597.909 | EM26: =+EL26 -> 33597.909 | EN26: =+EM26 -> 33597.909 | EO26: =+EN26 -> 33597.909 | EP26: =+EO26 -> 33597.909 | EQ26: =+EP26 -> 33597.909 | ER26: =+EQ26 -> 33597.909 | ES26: =+ER26 -> 33597.909 | ET26: =+ES26 -> 33597.909 | ... EW26: =+EV26 -> 33597.909 | EX26: =+EW26*(1+$B$17) -> 34605.847 | EY26: =+EX26 -> 34605.847 | EZ26: =+EY26 -> 34605.847 | FA26: =+EZ26 -> 34605.847 | FB26: =+FA26 -> 34605.847 | FC26: =+FB26 -> 34605.847 | FD26: =+FC26 -> 34605.847 | FE26: =+FD26 -> 34605.847 | FF26: =+FE26 -> 34605.847 | ... FI26: =+FH26 -> 34605.847 | FJ26: =+FI26*(1+$B$17) -> 35644.022 | FK26: =+FJ26 -> 35644.022 | FL26: =+FK26 -> 35644.022 | FM26: =+FL26 -> 35644.022 | FN26: =+FM26 -> 35644.022 | FO26: =+FN26 -> 35644.022 | FP26: =+FO26 -> 35644.022 | FQ26: =+FP26 -> 35644.022 | FR26: =+FQ26 -> 35644.022 | ... FU26: =+FT26 -> 35644.022 | FV26: =+FU26*(1+$B$17) -> 36713.343 | FW26: =+FV26 -> 36713.343 | FX26: =+FW26 -> 36713.343 | FY26: =+FX26 -> 36713.343 | FZ26: =+FY26 -> 36713.343 | GA26: =+FZ26 -> 36713.343 | GB26: =+GA26 -> 36713.343 | GC26: =+GB26 -> 36713.343 | GD26: =+GC26 -> 36713.343 | ... GG26: =+GF26 -> 36713.343 | GH26: =+GG26*(1+$B$17) -> 37814.743 | GI26: =+GH26 -> 37814.743 | GJ26: =+GI26 -> 37814.743 | GK26: =+GJ26 -> 37814.743 | GL26: =+GK26 -> 37814.743 | GM26: =+GL26 -> 37814.743 | GN26: =+GM26 -> 37814.743 | GO26: =+GN26 -> 37814.743 | GP26: =+GO26 -> 37814.743 | ... GS26: =+GR26 -> 37814.743 | GT26: =+GS26*(1+$B$17) -> 38949.185 | GU26: =+GT26 -> 38949.185 | GV26: =+GU26 -> 38949.185 | GW26: =+GV26 -> 38949.185 | GX26: =+GW26 -> 38949.185 | GY26: =+GX26 -> 38949.185 | GZ26: =+GY26 -> 38949.185 | HA26: =+GZ26 -> 38949.185 | HB26: =+HA26 -> 38949.185 | ... HE26: =+HD26 -> 38949.185 | HF26: =+HE26*(1+$B$17) -> 40117.661 | HG26: =+HF26 -> 40117.661 | HH26: =+HG26 -> 40117.661 | HI26: =+HH26 -> 40117.661 | HJ26: =+HI26 -> 40117.661 | HK26: =+HJ26 -> 40117.661 | HL26: =+HK26 -> 40117.661 | HM26: =+HL26 -> 40117.661 | HN26: =+HM26 -> 40117.661 | ... HQ26: =+HP26 -> 40117.661 | HR26: =+HQ26*(1+$B$17) -> 41321.191 | HS26: =+HR26 -> 41321.191 | HT26: =+HS26 -> 41321.191 | HU26: =+HT26 -> 41321.191 | HV26: =+HU26 -> 41321.191 | HW26: =+HV26 -> 41321.191 | HX26: =+HW26 -> 41321.191 | HY26: =+HX26 -> 41321.191 | HZ26: =+HY26 -> 41321.191 | ... IC26: =+IB26 -> 41321.191 | ID26: =+IC26*(1+$B$17) -> 42560.827 | IE26: =+ID26 -> 42560.827 | IF26: =+IE26 -> 42560.827 | IG26: =+IF26 -> 42560.827 | IH26: =+IG26 -> 42560.827 | II26: =+IH26 -> 42560.827 | IJ26: =+II26 -> 42560.827 | IK26: =+IJ26*(1+$B$17) -> 43837.651 | IL26: =+IK26*(1+$B$17) -> 45152.781 | IM26: =+IL26 -> 45152.781 | IN26: =+IM26 -> 45152.781 | IO26: =+IN26 -> 45152.781
A27: Total | B27: =+SUM(E27:BQ27) -> 60286726 | C27: =+SUM(C20:C26) -> 54046810 | E27: =+SUM(E20:E26) -> 0 | F27: =+SUM(F20:F26) -> 0 | G27: =+SUM(G20:G26) -> 0 | H27: =+SUM(H20:H26) -> 0 | I27: =+SUM(I20:I26) -> 0 | J27: =+SUM(J20:J26) -> 0 | K27: =+SUM(K21:K26) -> 0 | AF27: =+SUM(AF21:AF26) -> 1532151.4 | AG27: =+SUM(AG21:AG26) -> 1531653.4 | AH27: =+SUM(AH21:AH26) -> 1731895 | AI27: =+SUM(AI21:AI26) -> 1531376.1 | AJ27: =+SUM(AJ21:AJ26) -> 1530846.3 | AK27: =+SUM(AK21:AK26) -> 1736305.5 | AL27: =+SUM(AL21:AL26) -> 1529753.4 | AM27: =+SUM(AM21:AM26) -> 1529189.8 | ... IO27: =+SUM(IO21:IO26) -> 138581.8
A28: Energia 20 años | B28: =+B8 -> 481211.07 | C28: =+B28 -> 481211.07
A29: Tarifa ($/kWH) | B29: =+B27/B28 -> 125.28125 | C29: =+C27/C28 -> 112.31414 | E29: =+E27/E8 -> 0 | F29: =+F27/F8 -> 0 | G29: =+G27/G8 -> 0 | H29: =+H27/H8 -> 0 | I29: =+I27/I8 -> 0 | J29: =+J27/J8 -> 0 | K29: =+K27/K8 -> 0 | L29: =+L27/L8 -> 0 | ... IO29: =+IO27/IO8 -> 85.361622
A30: Arriendo | B30: =+B27/240 -> 251194.69
B31: =+B20/B28 -> 185.06856 | C31: =+C20/C28 -> 102.68689
E32: 2024 | F32: 2025 | G32: 2026 | H32: 2027 | I32: 2028 | J32: 2029 | K32: 2030 | L32: 2031 | M32: 2032 | N32: 2033 | O32: 2034 | P32: 2035 | Q32: 2036 | R32: 2037 | S32: 2038 | T32: 2039 | U32: 2040 | V32: 2041 | W32: 2042 | X32: 2043 | Y32: 2044
B33: Energia anual | E33: =+SUMIFS(8:8,2:2,E32) -> 9746.1817 | F33: =+SUMIFS(8:8,2:2,F32) -> 24758.348 | G33: =+SUMIFS(8:8,2:2,G32) -> 24717.725 | H33: =+SUMIFS(8:8,2:2,H32) -> 24692.441 | I33: =+SUMIFS(8:8,2:2,I32) -> 24737.676 | J33: =+SUMIFS(8:8,2:2,J32) -> 24602.093 | K33: =+SUMIFS(8:8,2:2,K32) -> 24475.673 | L33: =+SUMIFS(8:8,2:2,L32) -> 24349.254 | ... Y33: =+SUMIFS(8:8,2:2,Y32) -> 21622.004
B34: Costos Total | E34: =+SUMIFS(27:27,2:2,E32) -> 0 | F34: =+SUMIFS(27:27,2:2,F32) -> 0 | G34: =+SUMIFS(27:27,2:2,G32) -> 3063804.8 | H34: =+SUMIFS(27:27,2:2,H32) -> 19163995 | I34: =+SUMIFS(27:27,2:2,I32) -> 19085032 | J34: =+SUMIFS(27:27,2:2,J32) -> 18973894 | K34: =+SUMIFS(27:27,2:2,K32) -> 19261535 | L34: =+SUMIFS(27:27,2:2,L32) -> 16509121 | ... Y34: =+SUMIFS(27:27,2:2,Y32) -> 2467522.8
B35: Tarifa | E35: =+E34/E33 -> 0 | F35: =+F34/F33 -> 0 | G35: =+G34/G33 -> 123.95173 | H35: =+H34/H33 -> 776.10775 | I35: =+I34/I33 -> 771.49657 | J35: =+J34/J33 -> 771.23089 | K35: =+K34/K33 -> 786.96649 | L35: =+L34/L33 -> 678.01343 | ... Y35: =+Y34/Y33 -> 114.12091
B36: Arriendo | E36: =+E34/5 -> 0 | F36: =+F34/12 -> 0 | G36: =+G34/12 -> 255317.07 | H36: =+H34/12 -> 1596999.6 | I36: =+I34/12 -> 1590419.4 | J36: =+J34/12 -> 1581157.8 | K36: =+K34/12 -> 1605127.9 | L36: =+L34/12 -> 1375760.1 | M36: =+M34/12 -> 164047.21 | ... X36: =+X34/12 -> 200695.64 | Y36: =+Y34/7 -> 352503.25
E38: 1 año | F38: 2 años | G38: 3 años | H38: 4 años | I38: 5 años | J38: 6 años | K38: 7 años | L38: 8 años | M38: 9 años | N38: 10 años | O38: 11 años | P38: 12 años | Q38: 13 años | R38: 14 años | S38: 15 años | T38: 16 años | U38: 17 años | V38: 18 años | W38: 19 años | X38: 20 años
B39: Tarifa promedio | E39: =+E35 -> 0 | F39: =+AVERAGE(E35:F35) -> 0 | G39: =+AVERAGE(E35:G35) -> 41.317244 | H39: =+AVERAGE(E35:H35) -> 225.01487 | I39: =+AVERAGE(E35:I35) -> 334.31121 | J39: =+AVERAGE(E35:J35) -> 407.13116 | K39: =+AVERAGE(E35:K35) -> 461.39335 | L39: =+AVERAGE(E35:L35) -> 488.47086 | M39: =+AVERAGE(E35:M35) -> 443.20043 | N39: =+AVERAGE(E35:N35) -> 407.19242 | O39: =+AVERAGE(E35:O35) -> 377.88198 | P39: =+AVERAGE(E35:P35) -> 353.65969 | Q39: =+AVERAGE(E35:Q35) -> 333.33934 | R39: =+AVERAGE(E35:R35) -> 316.12871 | S39: =+AVERAGE(E35:S35) -> 301.39606 | T39: =+AVERAGE(E35:T35) -> 288.68388 | U39: =+AVERAGE(E35:U35) -> 277.62572 | V39: =+AVERAGE(E35:V35) -> 267.9848 | W39: =+AVERAGE(E35:W35) -> 259.5291 | X39: =+AVERAGE(E35:X35) -> 252.08773
B40: Arriendo promedio | E40: =+E36 -> 0 | F40: =+AVERAGE(E36:F36) -> 0 | K40: =+AVERAGE(E36:K36) -> 947003.1 | L40: =+AVERAGE(E36:L36) -> 1000597.7 | M40: =+AVERAGE(E36:M36) -> 907647.67 | N40: =+AVERAGE(E36:N36) -> 833573.76 | O40: =+AVERAGE(E36:O36) -> 773235.77 | P40: =+AVERAGE(E36:P36) -> 723207.09 | Q40: =+AVERAGE(E36:Q36) -> 681115.64 | R40: =+AVERAGE(E36:R36) -> 645267.3 | S40: =+AVERAGE(E36:S36) -> 614419.88 | T40: =+AVERAGE(E36:T36) -> 587641.93 | U40: =+AVERAGE(E36:U36) -> 564221.34 | V40: =+AVERAGE(E36:V36) -> 543604.41 | W40: =+AVERAGE(E36:W36) -> 525354.19 | X40: =+AVERAGE(E36:X36) -> 509121.26
A42: Costo Cliente MP | B42: =+SUM(E24:DY26) -> 13010084 | K42: =+'Prestamo 10 años'!L7 -> #VALUE! | L42: =+'Prestamo 10 años'!M7 -> #VALUE! | M42: =+'Prestamo 10 años'!N7 -> #VALUE! | N42: =+'Prestamo 10 años'!O7 -> #VALUE! | O42: =+'Prestamo 10 años'!P7 -> #VALUE! | P42: =+'Prestamo 10 años'!Q7 -> #VALUE! | Q42: =+'Prestamo 10 años'!R7 -> #VALUE! | R42: =+'Prestamo 10 años'!S7 -> #VALUE! | ... IO42: =+'Prestamo 10 años'!IP7 -> 0
A43: Capital | K43: =+'Prestamo 10 años'!L3 | L43: =+'Prestamo 10 años'!M3 | M43: =+'Prestamo 10 años'!N3 | N43: =+'Prestamo 10 años'!O3 | O43: =+'Prestamo 10 años'!P3 | P43: =+'Prestamo 10 años'!Q3 | Q43: =+'Prestamo 10 años'!R3 | R43: =+'Prestamo 10 años'!S3 | ... FH43: =+'Prestamo 10 años'!FI3 -> 0
A44: Interéses | K44: =+'Prestamo 10 años'!L4 | L44: =+'Prestamo 10 años'!M4 | M44: =+'Prestamo 10 años'!N4 | N44: =+'Prestamo 10 años'!O4 | O44: =+'Prestamo 10 años'!P4 | P44: =+'Prestamo 10 años'!Q4 | Q44: =+'Prestamo 10 años'!R4 | R44: =+'Prestamo 10 años'!S4 | ... FH44: =+'Prestamo 10 años'!FI4 -> 0
A45: Seguros | K45: =+'Prestamo 10 años'!L6 -> #VALUE! | L45: =+'Prestamo 10 años'!M6 -> #VALUE! | M45: =+'Prestamo 10 años'!N6 -> #VALUE! | N45: =+'Prestamo 10 años'!O6 -> #VALUE! | O45: =+'Prestamo 10 años'!P6 -> #VALUE! | P45: =+'Prestamo 10 años'!Q6 -> #VALUE! | Q45: =+'Prestamo 10 años'!R6 -> #VALUE! | R45: =+'Prestamo 10 años'!S6 -> #VALUE! | ... FH45: =+'Prestamo 10 años'!FI6 -> 0
A46: Costo Cliente LP | B46: =+SUM(E24:GG26) -> 23770213 | K46: =+'Prestamo 15 años'!L7 -> #VALUE! | L46: =+'Prestamo 15 años'!M7 -> #VALUE! | M46: =+'Prestamo 15 años'!N7 -> #VALUE! | N46: =+'Prestamo 15 años'!O7 -> #VALUE! | O46: =+'Prestamo 15 años'!P7 -> #VALUE! | P46: =+'Prestamo 15 años'!Q7 -> #VALUE! | Q46: =+'Prestamo 15 años'!R7 -> #VALUE! | R46: =+'Prestamo 15 años'!S7 -> #VALUE! | ... IO46: =+'Prestamo 15 años'!IP7 -> 0
A47: Capital | K47: =+'Prestamo 15 años'!L3 | L47: =+'Prestamo 15 años'!M3 | M47: =+'Prestamo 15 años'!N3 | N47: =+'Prestamo 15 años'!O3 | O47: =+'Prestamo 15 años'!P3 | P47: =+'Prestamo 15 años'!Q3 | Q47: =+'Prestamo 15 años'!R3 | R47: =+'Prestamo 15 años'!S3 | ... GX47: =+'Prestamo 15 años'!GY3 -> 0
A48: Interéses | K48: =+'Prestamo 15 años'!L4 | L48: =+'Prestamo 15 años'!M4 | M48: =+'Prestamo 15 años'!N4 | N48: =+'Prestamo 15 años'!O4 | O48: =+'Prestamo 15 años'!P4 | P48: =+'Prestamo 15 años'!Q4 | Q48: =+'Prestamo 15 años'!R4 | R48: =+'Prestamo 15 años'!S4 | ... GX48: =+'Prestamo 15 años'!GY4 -> 0
A49: Seguros | K49: =+'Prestamo 15 años'!L6 -> #VALUE! | L49: =+'Prestamo 15 años'!M6 -> #VALUE! | M49: =+'Prestamo 15 años'!N6 -> #VALUE! | N49: =+'Prestamo 15 años'!O6 -> #VALUE! | O49: =+'Prestamo 15 años'!P6 -> #VALUE! | P49: =+'Prestamo 15 años'!Q6 -> #VALUE! | Q49: =+'Prestamo 15 años'!R6 -> #VALUE! | R49: =+'Prestamo 15 años'!S6 -> #VALUE! | ... GX49: =+'Prestamo 15 años'!GY6 -> 0
E51: =+YEAR(E52) -> 2024 | F51: =+YEAR(F52) -> 2024 | G51: =+YEAR(G52) -> 2024 | H51: =+YEAR(H52) -> 2024 | I51: =+YEAR(I52) -> 2024 | J51: =+YEAR(J52) -> 2025 | K51: =+YEAR(K52) -> 2025 | L51: =+YEAR(L52) -> 2025 | ... IO51: =+YEAR(IO52) -> 2044
A52: Costos para la empresa CP | B52: Total | C52: Pareto | D52: Tarifa | E52: 45505 | F52: 45536 | G52: 45566 | H52: 45597 | I52: 45627 | J52: 45658 | K52: 45689 | L52: 45717 | M52: 45748 | N52: 45778 | O52: 45809 | P52: 45839 | Q52: 45870 | R52: 45901 | S52: 45931 | T52: 45962 | U52: 45992 | V52: 46023 | W52: 46054 | X52: 46082 | Y52: 46113 | Z52: 46143 | AA52: 46174 | AB52: 46204 | AC52: 46235 | AD52: 46266 | AE52: 46296 | AF52: 46327 | AG52: 46357 | AH52: 46388 | AI52: 46419 | AJ52: 46447 | AK52: 46478 | AL52: 46508 | AM52: 46539 | AN52: 46569 | AO52: 46600 | AP52: 46631 | AQ52: 46661 | AR52: 46692 | AS52: 46722 | AT52: 46753 | AU52: 46784 | AV52: 46813 | AW52: 46844 | AX52: 46874 | AY52: 46905 | AZ52: 46935 | BA52: 46966 | BB52: 46997 | BC52: 47027 | BD52: 47058 | BE52: 47088 | BF52: 47119 | BG52: 47150 | BH52: 47178 | BI52: 47209 | BJ52: 47239 | BK52: 47270 | BL52: 47300 | BM52: 47331 | BN52: 47362 | BO52: 47392 | BP52: 47423 | BQ52: 47453 | BR52: 47484 | BS52: 47515 | BT52: 47543 | BU52: 47574 | BV52: 47604 | BW52: 47635 | BX52: 47665 | BY52: 47696 | BZ52: 47727 | CA52: 47757 | CB52: 47788 | CC52: 47818 | CD52: 47849 | CE52: 47880 | CF52: 47908 | CG52: 47939 | CH52: 47969 | CI52: 48000 | CJ52: 48030 | CK52: 48061 | CL52: 48092 | CM52: 48122 | CN52: 48153 | CO52: 48183 | CP52: 48214 | CQ52: 48245 | CR52: 48274 | CS52: 48305 | CT52: 48335 | CU52: 48366 | CV52: 48396 | CW52: 48427 | CX52: 48458 | CY52: 48488 | CZ52: 48519 | DA52: 48549 | DB52: 48580 | DC52: 48611 | DD52: 48639 | DE52: 48670 | DF52: 48700 | DG52: 48731 | DH52: 48761 | DI52: 48792 | DJ52: 48823 | DK52: 48853 | DL52: 48884 | DM52: 48914 | DN52: 48945 | DO52: 48976 | DP52: 49004 | DQ52: 49035 | DR52: 49065 | DS52: 49096 | DT52: 49126 | DU52: 49157 | DV52: 49188 | DW52: 49218 | DX52: 49249 | DY52: 49279 | DZ52: 49310 | EA52: 49341 | EB52: 49369 | EC52: 49400 | ED52: 49430 | EE52: 49461 | EF52: 49491 | EG52: 49522 | EH52: 49553 | EI52: 49583 | EJ52: 49614 | EK52: 49644 | EL52: 49675 | EM52: 49706 | EN52: 49735 | EO52: 49766 | EP52: 49796 | EQ52: 49827 | ER52: 49857 | ES52: 49888 | ET52: 49919 | EU52: 49949 | EV52: 49980 | EW52: 50010 | EX52: 50041 | EY52: 50072 | EZ52: 50100 | FA52: 50131 | FB52: 50161 | FC52: 50192 | FD52: 50222 | FE52: 50253 | FF52: 50284 | FG52: 50314 | FH52: 50345 | FI52: 50375 | FJ52: 50406 | FK52: 50437 | FL52: 50465 | FM52: 50496 | FN52: 50526 | FO52: 50557 | FP52: 50587 | FQ52: 50618 | FR52: 50649 | FS52: 50679 | FT52: 50710 | FU52: 50740 | FV52: 50771 | FW52: 50802 | FX52: 50830 | FY52: 50861 | FZ52: 50891 | GA52: 50922 | GB52: 50952 | GC52: 50983 | GD52: 51014 | GE52: 51044 | GF52: 51075 | GG52: 51105 | GH52: 51136 | GI52: 51167 | GJ52: 51196 | GK52: 51227 | GL52: 51257 | GM52: 51288 | GN52: 51318 | GO52: 51349 | GP52: 51380 | GQ52: 51410 | GR52: 51441 | GS52: 51471 | GT52: 51502 | GU52: 51533 | GV52: 51561 | GW52: 51592 | GX52: 51622 | GY52: 51653 | GZ52: 51683 | HA52: 51714 | HB52: 51745 | HC52: 51775 | HD52: 51806 | HE52: 51836 | HF52: 51867 | HG52: 51898 | HH52: 51926 | HI52: 51957 | HJ52: 51987 | HK52: 52018 | HL52: 52048 | HM52: 52079 | HN52: 52110 | HO52: 52140 | HP52: 52171 | HQ52: 52201 | HR52: 52232 | HS52: 52263 | HT52: 52291 | HU52: 52322 | HV52: 52352 | HW52: 52383 | HX52: 52413 | HY52: 52444 | HZ52: 52475 | IA52: 52505 | IB52: 52536 | IC52: 52566 | ID52: 52597 | IE52: 52628 | IF52: 52657 | IG52: 52688 | IH52: 52718 | II52: 52749 | IJ52: 52779 | IK52: 52810 | IL52: 52841 | IM52: 52871 | IN52: 52902 | IO52: 52932
A53: Amortización Capital | B53: =+SUM(E53:IJ53) -> #REF! | C53: =+B53/$B$59 -> #REF! | D53: =+B53/$C$64 -> #REF! | E53: =+'Simulacion prestamo'!C13 -> #REF! | F53: =+'Simulacion prestamo'!D13 -> #REF! | G53: =+'Simulacion prestamo'!E13 -> #REF! | H53: =+'Simulacion prestamo'!F13 -> #REF! | I53: =+'Simulacion prestamo'!G13 -> #REF! | J53: =+'Simulacion prestamo'!H13 -> #REF! | K53: =+'Simulacion prestamo'!I13 -> #REF! | L53: =+'Simulacion prestamo'!J13 -> #REF! | ... AZ53: =+'Simulacion prestamo'!AX13 -> #REF!
A54: Amortización Intereses | B54: =+SUM(E54:IJ54) -> #REF! | C54: =+B54/$B$59 -> #REF! | D54: =+B54/$C$64 -> #REF! | E54: =+'Simulacion prestamo'!C12 -> #REF! | F54: =+'Simulacion prestamo'!D12 -> #REF! | G54: =+'Simulacion prestamo'!E12 -> #REF! | H54: =+'Simulacion prestamo'!F12 -> #REF! | I54: =+'Simulacion prestamo'!G12 -> #REF! | J54: =+'Simulacion prestamo'!H12 -> #REF! | K54: =+'Simulacion prestamo'!I12 -> #REF! | L54: =+'Simulacion prestamo'!J12 -> #REF! | ... IO54: =+'Simulacion prestamo'!IM12 -> 0
A55: Seguros | B55: =+SUM(E55:IJ55) -> #REF! | C55: =+B55/$B$59 -> #REF! | D55: =+B55/$C$64 -> #REF! | E55: =+'Simulacion prestamo'!C15 -> #REF! | F55: =+'Simulacion prestamo'!D15 -> #REF! | G55: =+'Simulacion prestamo'!E15 -> #REF! | H55: =+'Simulacion prestamo'!F15 -> #REF! | I55: =+'Simulacion prestamo'!G15 -> #REF! | J55: =+'Simulacion prestamo'!H15 -> #REF! | K55: =+'Simulacion prestamo'!I15 -> #REF! | L55: =+'Simulacion prestamo'!J15 -> #REF! | ... IO55: =+'Simulacion prestamo'!IM15 -> 0
A56: Mantenimiento | B56: =+SUM(E56:BQ56) -> #REF! | C56: =+B56/$B$59 -> #REF! | D56: =+B56/$C$64 -> #REF! | H56: =+#REF! -> #REF! | K56: =+H56*1.1 -> #REF! | N56: =+K56 -> #REF! | Q56: =+N56 -> #REF! | T56: =+Q56 -> #REF! | W56: =+T56*1.1 -> #REF! | Z56: =+W56 -> #REF! | AC56: =+Z56 -> #REF! | AF56: =+AC56 -> #REF! | AI56: =+AF56*1.1 -> #REF! | AL56: =+AI56 -> #REF! | AO56: =+AL56 -> #REF! | AR56: =+AO56 -> #REF! | AU56: =+AR56*1.1 -> #REF! | AX56: =+AU56 -> #REF! | BA56: =+AX56 -> #REF! | BD56: =+BA56 -> #REF! | BG56: =+BD56*1.1 -> #REF! | BJ56: =+BG56 -> #REF! | BM56: =+BJ56 -> #REF! | BP56: =+BM56 -> #REF! | BS56: =+BP56*1.1 -> #REF! | BV56: =+BS56 -> #REF! | BY56: =+BV56 -> #REF! | CB56: =+BY56 -> #REF! | CE56: =+CB56*1.1 -> #REF! | CH56: =+CE56 -> #REF! | CK56: =+CH56 -> #REF! | CN56: =+CK56 -> #REF! | CQ56: =+CN56*1.1 -> #REF! | CT56: =+CQ56 -> #REF! | CW56: =+CT56 -> #REF! | CZ56: =+CW56 -> #REF! | DC56: =+CZ56*1.1 -> #REF! | DF56: =+DC56 -> #REF! | DI56: =+DF56 -> #REF! | DL56: =+DI56 -> #REF! | DO56: =+DL56*1.1 -> #REF! | DR56: =+DO56 -> #REF! | DU56: =+DR56 -> #REF! | DX56: =+DU56 -> #REF! | EA56: =+DX56*1.1 -> #REF! | ED56: =+EA56 -> #REF! | EG56: =+ED56 -> #REF! | EJ56: =+EG56 -> #REF! | EM56: =+EJ56*1.1 -> #REF! | EP56: =+EM56 -> #REF! | ES56: =+EP56 -> #REF! | EV56: =+ES56 -> #REF! | EY56: =+EV56*1.1 -> #REF! | FB56: =+EY56 -> #REF! | FE56: =+FB56 -> #REF! | FH56: =+FE56 -> #REF! | FK56: =+FH56*1.1 -> #REF! | FN56: =+FK56 -> #REF! | FQ56: =+FN56 -> #REF! | FT56: =+FQ56 -> #REF! | FW56: =+FT56*1.1 -> #REF! | FZ56: =+FW56 -> #REF! | GC56: =+FZ56 -> #REF! | GF56: =+GC56 -> #REF! | GI56: =+GF56*1.1 -> #REF! | GL56: =+GI56 -> #REF! | GO56: =+GL56 -> #REF! | GR56: =+GO56 -> #REF! | GU56: =+GR56*1.1 -> #REF! | GX56: =+GU56 -> #REF! | HA56: =+GX56 -> #REF! | HD56: =+HA56 -> #REF! | HG56: =+HD56*1.1 -> #REF! | HJ56: =+HG56 -> #REF! | HM56: =+HJ56 -> #REF! | HP56: =+HM56 -> #REF! | HS56: =+HP56*1.1 -> #REF! | HV56: =+HS56 -> #REF! | HY56: =+HV56 -> #REF! | IB56: =+HY56 -> #REF! | IE56: =+IB56*1.1 -> #REF! | IH56: =+IE56 -> #REF! | IM56: =+IJ56*1.1 -> 0
A57: Reposición | B57: =+SUM(E57:BQ57) -> #REF! | C57: =+B57/$B$59 -> #REF! | D57: =+B57/$C$64 -> #REF! | BA57: =+#REF! -> #REF! | BB57: =+BA57 -> #REF! | BC57: =+BB57 -> #REF! | BD57: =+BC57 -> #REF! | BE57: =+BD57 -> #REF! | BF57: =+BE57 -> #REF! | BG57: =+BF57 -> #REF! | BH57: =+BG57 -> #REF! | BI57: =+BH57 -> #REF! | ... FP57: =+FO57 -> #REF!
A58: Operación | B58: =+SUM(E58:BQ58) -> #REF! | C58: =+B58/$B$59 -> #REF! | D58: =+B58/$C$64 -> #REF! | E58: =+#REF! -> #REF! | F58: =+E58 -> #REF! | G58: =+F58 -> #REF! | H58: =+G58 -> #REF! | I58: =+H58 -> #REF! | J58: =+I58*1.1 -> #REF! | K58: =+J58 -> #REF! | L58: =+K58 -> #REF! | M58: =+L58 -> #REF! | N58: =+M58 -> #REF! | O58: =+N58 -> #REF! | P58: =+O58 -> #REF! | Q58: =+P58 -> #REF! | R58: =+Q58 -> #REF! | ... U58: =+T58 -> #REF! | V58: =+U58*1.1 -> #REF! | W58: =+V58 -> #REF! | X58: =+W58 -> #REF! | Y58: =+X58 -> #REF! | Z58: =+Y58 -> #REF! | AA58: =+Z58 -> #REF! | AB58: =+AA58 -> #REF! | AC58: =+AB58 -> #REF! | AD58: =+AC58 -> #REF! | ... AG58: =+AF58 -> #REF! | AH58: =+AG58*1.1 -> #REF! | AI58: =+AH58 -> #REF! | AJ58: =+AI58 -> #REF! | AK58: =+AJ58 -> #REF! | AL58: =+AK58 -> #REF! | AM58: =+AL58 -> #REF! | AN58: =+AM58 -> #REF! | AO58: =+AN58 -> #REF! | AP58: =+AO58 -> #REF! | ... AS58: =+AR58 -> #REF! | AT58: =+AS58*1.1 -> #REF! | AU58: =+AT58 -> #REF! | AV58: =+AU58 -> #REF! | AW58: =+AV58 -> #REF! | AX58: =+AW58 -> #REF! | AY58: =+AX58 -> #REF! | AZ58: =+AY58 -> #REF! | BA58: =+AZ58 -> #REF! | BB58: =+BA58 -> #REF! | ... BE58: =+BD58 -> #REF! | BF58: =+BE58*1.1 -> #REF! | BG58: =+BF58 -> #REF! | BH58: =+BG58 -> #REF! | BI58: =+BH58 -> #REF! | BJ58: =+BI58 -> #REF! | BK58: =+BJ58 -> #REF! | BL58: =+BK58 -> #REF! | BM58: =+BL58 -> #REF! | BN58: =+BM58 -> #REF! | ... BQ58: =+BP58 -> #REF! | BR58: =+BQ58*1.1 -> #REF! | BS58: =+BR58 -> #REF! | BT58: =+BS58 -> #REF! | BU58: =+BT58 -> #REF! | BV58: =+BU58 -> #REF! | BW58: =+BV58 -> #REF! | BX58: =+BW58 -> #REF! | BY58: =+BX58 -> #REF! | BZ58: =+BY58 -> #REF! | ... CC58: =+CB58 -> #REF! | CD58: =+CC58*1.1 -> #REF! | CE58: =+CD58 -> #REF! | CF58: =+CE58 -> #REF! | CG58: =+CF58 -> #REF! | CH58: =+CG58 -> #REF! | CI58: =+CH58 -> #REF! | CJ58: =+CI58 -> #REF! | CK58: =+CJ58 -> #REF! | CL58: =+CK58 -> #REF! | ... CO58: =+CN58 -> #REF! | CP58: =+CO58*1.1 -> #REF! | CQ58: =+CP58 -> #REF! | CR58: =+CQ58 -> #REF! | CS58: =+CR58 -> #REF! | CT58: =+CS58 -> #REF! | CU58: =+CT58 -> #REF! | CV58: =+CU58 -> #REF! | CW58: =+CV58 -> #REF! | CX58: =+CW58 -> #REF! | ... DA58: =+CZ58 -> #REF! | DB58: =+DA58*1.1 -> #REF! | DC58: =+DB58 -> #REF! | DD58: =+DC58 -> #REF! | DE58: =+DD58 -> #REF! | DF58: =+DE58 -> #REF! | DG58: =+DF58 -> #REF! | DH58: =+DG58 -> #REF! | DI58: =+DH58 -> #REF! | DJ58: =+DI58 -> #REF! | ... DM58: =+DL58 -> #REF! | DN58: =+DM58*1.1 -> #REF! | DO58: =+DN58 -> #REF! | DP58: =+DO58 -> #REF! | DQ58: =+DP58 -> #REF! | DR58: =+DQ58 -> #REF! | DS58: =+DR58 -> #REF! | DT58: =+DS58 -> #REF! | DU58: =+DT58 -> #REF! | DV58: =+DU58 -> #REF! | ... DY58: =+DX58 -> #REF! | DZ58: =+DY58*1.1 -> #REF! | EA58: =+DZ58 -> #REF! | EB58: =+EA58 -> #REF! | EC58: =+EB58 -> #REF! | ED58: =+EC58 -> #REF! | EE58: =+ED58 -> #REF! | EF58: =+EE58 -> #REF! | EG58: =+EF58 -> #REF! | EH58: =+EG58 -> #REF! | ... EK58: =+EJ58 -> #REF! | EL58: =+EK58*1.1 -> #REF! | EM58: =+EL58 -> #REF! | EN58: =+EM58 -> #REF! | EO58: =+EN58 -> #REF! | EP58: =+EO58 -> #REF! | EQ58: =+EP58 -> #REF! | ER58: =+EQ58 -> #REF! | ES58: =+ER58 -> #REF! | ET58: =+ES58 -> #REF! | ... EW58: =+EV58 -> #REF! | EX58: =+EW58*1.1 -> #REF! | EY58: =+EX58 -> #REF! | EZ58: =+EY58 -> #REF! | FA58: =+EZ58 -> #REF! | FB58: =+FA58 -> #REF! | FC58: =+FB58 -> #REF! | FD58: =+FC58 -> #REF! | FE58: =+FD58 -> #REF! | FF58: =+FE58 -> #REF! | ... FI58: =+FH58 -> #REF! | FJ58: =+FI58*1.1 -> #REF! | FK58: =+FJ58 -> #REF! | FL58: =+FK58 -> #REF! | FM58: =+FL58 -> #REF! | FN58: =+FM58 -> #REF! | FO58: =+FN58 -> #REF! | FP58: =+FO58 -> #REF! | FQ58: =+FP58 -> #REF! | FR58: =+FQ58 -> #REF! | ... FU58: =+FT58 -> #REF! | FV58: =+FU58*1.1 -> #REF! | FW58: =+FV58 -> #REF! | FX58: =+FW58 -> #REF! | FY58: =+FX58 -> #REF! | FZ58: =+FY58 -> #REF! | GA58: =+FZ58 -> #REF! | GB58: =+GA58 -> #REF! | GC58: =+GB58 -> #REF! | GD58: =+GC58 -> #REF! | ... GG58: =+GF58 -> #REF! | GH58: =+GG58*1.1 -> #REF! | GI58: =+GH58 -> #REF! | GJ58: =+GI58 -> #REF! | GK58: =+GJ58 -> #REF! | GL58: =+GK58 -> #REF! | GM58: =+GL58 -> #REF! | GN58: =+GM58 -> #REF! | GO58: =+GN58 -> #REF! | GP58: =+GO58 -> #REF! | ... GS58: =+GR58 -> #REF! | GT58: =+GS58*1.1 -> #REF! | GU58: =+GT58 -> #REF! | GV58: =+GU58 -> #REF! | GW58: =+GV58 -> #REF! | GX58: =+GW58 -> #REF! | GY58: =+GX58 -> #REF! | GZ58: =+GY58 -> #REF! | HA58: =+GZ58 -> #REF! | HB58: =+HA58 -> #REF! | ... HE58: =+HD58 -> #REF! | HF58: =+HE58*1.1 -> #REF! | HG58: =+HF58 -> #REF! | HH58: =+HG58 -> #REF! | HI58: =+HH58 -> #REF! | HJ58: =+HI58 -> #REF! | HK58: =+HJ58 -> #REF! | HL58: =+HK58 -> #REF! | HM58: =+HL58 -> #REF! | HN58: =+HM58 -> #REF! | ... HQ58: =+HP58 -> #REF! | HR58: =+HQ58*1.1 -> #REF! | HS58: =+HR58 -> #REF! | HT58: =+HS58 -> #REF! | HU58: =+HT58 -> #REF! | HV58: =+HU58 -> #REF! | HW58: =+HV58 -> #REF! | HX58: =+HW58 -> #REF! | HY58: =+HX58 -> #REF! | HZ58: =+HY58 -> #REF! | ... IC58: =+IB58 -> #REF! | ID58: =+IC58*1.1 -> #REF! | IE58: =+ID58 -> #REF! | IF58: =+IE58 -> #REF! | IG58: =+IF58 -> #REF! | IH58: =+IG58 -> #REF! | II58: =+IH58 -> #REF! | IJ58: =+II58 -> #REF! | IK58: =+IJ58*1.1 -> #REF! | IL58: =+IK58*1.1 -> #REF! | IM58: =+IL58 -> #REF! | IN58: =+IM58 -> #REF! | IO58: =+IN58 -> #REF!
A59: Total | B59: =+SUM(E59:BQ59) -> #REF! | D59: =+B59/$C$64 -> #REF! | E59: =+SUM(E53:E58) -> #REF! | F59: =+SUM(F53:F58) -> #REF! | G59: =+SUM(G53:G58) -> #REF! | H59: =+SUM(H53:H58) -> #REF! | I59: =+SUM(I53:I58) -> #REF! | J59: =+SUM(J53:J58) -> #REF! | K59: =+SUM(K53:K58) -> #REF! | L59: =+SUM(L53:L58) -> #REF! | ... IO59: =+SUM(IO53:IO58) -> #REF!
A61: Tarifa ($/kWH) | B61: =+B59/SUM(E8:BQ8) -> #REF! | E61: =+E59/E8 -> #REF! | F61: =+F59/F8 -> #REF! | G61: =+G59/G8 -> #REF! | H61: =+H59/H8 -> #REF! | I61: =+I59/I8 -> #REF! | J61: =+J59/J8 -> #REF! | K61: =+K59/K8 -> #REF! | L61: =+L59/L8 -> #REF! | ... IO61: =+IO59/IO8 -> #REF!
E63: 2024 | F63: 2025 | G63: 2026 | H63: 2027 | I63: 2028 | J63: 2029 | K63: 2030 | L63: 2031 | M63: 2032 | N63: 2033 | O63: 2034 | P63: 2035 | Q63: 2036 | R63: 2037 | S63: 2038 | T63: 2039 | U63: 2040 | V63: 2041 | W63: 2042 | X63: 2043 | Y63: 2044
B64: Energia anual | C64: =+SUM(E64:J64) -> 133254.46 | E64: =+SUMIFS(8:8,2:2,E63) -> 9746.1817 | F64: =+SUMIFS(8:8,2:2,F63) -> 24758.348 | G64: =+SUMIFS(8:8,2:2,G63) -> 24717.725 | H64: =+SUMIFS(8:8,2:2,H63) -> 24692.441 | I64: =+SUMIFS(8:8,2:2,I63) -> 24737.676 | J64: =+SUMIFS(8:8,2:2,J63) -> 24602.093 | K64: =+SUMIFS(8:8,2:2,K63) -> 24475.673 | L64: =+SUMIFS(8:8,2:2,L63) -> 24349.254 | ... Y64: =+SUMIFS(8:8,2:2,Y63) -> 21622.004
B65: Costos Total | C65: =+SUM(E65:J65) -> #REF! | E65: =+SUMIFS(59:59,2:2,E63) -> #REF! | F65: =+SUMIFS(59:59,2:2,F63) -> #REF! | G65: =+SUMIFS(59:59,2:2,G63) -> #REF! | H65: =+SUMIFS(59:59,2:2,H63) -> #REF! | I65: =+SUMIFS(59:59,2:2,I63) -> #REF! | J65: =+SUMIFS(59:59,2:2,J63) -> #REF! | K65: =+SUMIFS(59:59,2:2,K63) -> #REF! | L65: =+SUMIFS(59:59,2:2,L63) -> #REF! | ... Y65: =+SUMIFS(59:59,2:2,Y63) -> #REF!
B66: Tarifa | C66: =+C65/C64 -> #REF! | E66: =+E65/E64 -> #REF! | F66: =+F65/F64 -> #REF! | G66: =+G65/G64 -> #REF! | H66: =+H65/H64 -> #REF! | I66: =+I65/I64 -> #REF! | J66: =+J65/J64 -> #REF! | K66: =+K65/K64 -> #REF! | L66: =+L65/L64 -> #REF! | ... Y66: =+Y65/Y64 -> #REF!
B67: Arriendo | E67: =+E65/5 -> #REF! | F67: =+F65/12 -> #REF! | G67: =+G65/12 -> #REF! | H67: =+H65/12 -> #REF! | I67: =+I65/12 -> #REF! | J67: =+J65/12 -> #REF! | K67: =+K65/12 -> #REF! | L67: =+L65/12 -> #REF! | M67: =+M65/12 -> #REF! | ... X67: =+X65/12 -> #REF! | Y67: =+Y65/7 -> #REF!
E69: 1 año | F69: 2 años | G69: 3 años | H69: 4 años | I69: 5 años | J69: 6 años | K69: 7 años | L69: 8 años | M69: 9 años | N69: 10 años | O69: 11 años | P69: 12 años | Q69: 13 años | R69: 14 años | S69: 15 años | T69: 16 años | U69: 17 años | V69: 18 años | W69: 19 años | X69: 20 años
B70: Tarifa promedio | E70: =+E66 -> #REF! | F70: =+AVERAGE(E66:F66) -> #REF! | G70: =+AVERAGE(E66:G66) -> #REF! | H70: =+AVERAGE(E66:H66) -> #REF! | I70: =+AVERAGE(E66:I66) -> #REF! | J70: =+AVERAGE(E66:J66) -> #REF! | K70: =+AVERAGE(E66:K66) -> #REF! | L70: =+AVERAGE(E66:L66) -> #REF! | M70: =+AVERAGE(E66:M66) -> #REF! | N70: =+AVERAGE(E66:N66) -> #REF! | O70: =+AVERAGE(E66:O66) -> #REF! | P70: =+AVERAGE(E66:P66) -> #REF! | Q70: =+AVERAGE(E66:Q66) -> #REF! | R70: =+AVERAGE(E66:R66) -> #REF! | S70: =+AVERAGE(E66:S66) -> #REF! | T70: =+AVERAGE(E66:T66) -> #REF! | U70: =+AVERAGE(E66:U66) -> #REF! | V70: =+AVERAGE(E66:V66) -> #REF! | W70: =+AVERAGE(E66:W66) -> #REF! | X70: =+AVERAGE(E66:X66) -> #REF!
B71: Arriendo promedio | E71: =+E67 -> #REF! | F71: =+AVERAGE(E67:F67) -> #REF! | G71: =+AVERAGE(E67:G67) -> #REF! | H71: =+AVERAGE(E67:H67) -> #REF! | I71: =+AVERAGE(E67:I67) -> #REF! | J71: =+AVERAGE(E67:J67) -> #REF! | K71: =+AVERAGE(E67:K67) -> #REF! | L71: =+AVERAGE(E67:L67) -> #REF! | M71: =+AVERAGE(E67:M67) -> #REF! | N71: =+AVERAGE(E67:N67) -> #REF! | O71: =+AVERAGE(E67:O67) -> #REF! | P71: =+AVERAGE(E67:P67) -> #REF! | Q71: =+AVERAGE(E67:Q67) -> #REF! | R71: =+AVERAGE(E67:R67) -> #REF! | S71: =+AVERAGE(E67:S67) -> #REF! | T71: =+AVERAGE(E67:T67) -> #REF! | U71: =+AVERAGE(E67:U67) -> #REF! | V71: =+AVERAGE(E67:V67) -> #REF! | W71: =+AVERAGE(E67:W67) -> #REF! | X71: =+AVERAGE(E67:X67) -> #REF!
B72: Margen | E72: =+(E40-E71)/E71 -> #REF! | F72: =+(F40-F71)/F71 -> #REF! | G72: =+(G40-G71)/G71 -> #REF! | H72: =+(H40-H71)/H71 -> #REF! | I72: =+(I40-I71)/I71 -> #REF! | J72: =+(J40-J71)/J71 -> #REF! | K72: =+(K40-K71)/K71 -> #REF! | L72: =+(L40-L71)/L71 -> #REF! | ... X72: =+(X40-X71)/X71 -> #REF!
E74: 2024 | F74: 2025 | G74: 2026 | H74: 2027 | I74: 2028 | J74: 2029 | K74: 2030 | L74: 2031 | M74: 2032 | N74: 2033 | O74: 2034 | P74: 2035 | Q74: 2036 | R74: 2037 | S74: 2038 | T74: 2039 | U74: 2040 | V74: 2041 | W74: 2042 | X74: 2043 | Y74: 2044
B75: Costos | E75: =+SUM(E76:E79) -> #REF! | F75: =+SUM(F76:F79) -> #REF! | G75: =+SUM(G76:G79) -> #REF! | H75: =+SUM(H76:H79) -> #REF! | I75: =+SUM(I76:I79) -> #REF! | J75: =+SUM(J76:J79) -> #REF! | K75: =+SUM(K76:K79) -> #REF! | L75: =+SUM(L76:L79) -> #REF! | ... Y75: =+SUM(Y76:Y79) -> #REF!
B76: Amortización Capital | E76: =+SUMIFS(53:53,51:51,E74) -> #REF! | F76: =+SUMIFS(53:53,51:51,F74) -> #REF! | G76: =+SUMIFS(53:53,51:51,G74) -> #REF! | H76: =+SUMIFS(53:53,51:51,H74) -> #REF! | I76: =+SUMIFS(53:53,51:51,I74) -> #REF! | J76: =+SUMIFS(53:53,51:51,J74) -> 0 | K76: =+SUMIFS(53:53,51:51,K74) -> 0 | L76: =+SUMIFS(53:53,51:51,L74) -> 0 | ... Y76: =+SUMIFS(53:53,51:51,Y74) -> 0
B77: Mantenimiento | E77: =+SUMIFS(56:56,51:51,E74) -> #REF! | F77: =+SUMIFS(56:56,51:51,F74) -> #REF! | G77: =+SUMIFS(56:56,51:51,G74) -> #REF! | H77: =+SUMIFS(56:56,51:51,H74) -> #REF! | I77: =+SUMIFS(56:56,51:51,I74) -> #REF! | J77: =+SUMIFS(56:56,51:51,J74) -> #REF! | K77: =+SUMIFS(56:56,51:51,K74) -> #REF! | L77: =+SUMIFS(56:56,51:51,L74) -> #REF! | ... Y77: =+SUMIFS(56:56,51:51,Y74) -> #REF!
B78: Reposición | E78: =+SUMIFS(57:57,51:51,E74) -> 0 | F78: =+SUMIFS(57:57,51:51,F74) -> 0 | G78: =+SUMIFS(57:57,51:51,G74) -> 0 | H78: =+SUMIFS(57:57,51:51,H74) -> 0 | I78: =+SUMIFS(57:57,51:51,I74) -> #REF! | J78: =+SUMIFS(57:57,51:51,J74) -> #REF! | K78: =+SUMIFS(57:57,51:51,K74) -> #REF! | L78: =+SUMIFS(57:57,51:51,L74) -> #REF! | ... Y78: =+SUMIFS(57:57,51:51,Y74) -> 0
B79: Operación | E79: =+SUMIFS(58:58,51:51,E74) -> #REF! | F79: =+SUMIFS(58:58,51:51,F74) -> #REF! | G79: =+SUMIFS(58:58,51:51,G74) -> #REF! | H79: =+SUMIFS(58:58,51:51,H74) -> #REF! | I79: =+SUMIFS(58:58,51:51,I74) -> #REF! | J79: =+SUMIFS(58:58,51:51,J74) -> #REF! | K79: =+SUMIFS(58:58,51:51,K74) -> #REF! | L79: =+SUMIFS(58:58,51:51,L74) -> #REF! | ... Y79: =+SUMIFS(58:58,51:51,Y74) -> #REF!
B80: Intereses | E80: =+SUMIFS(54:54,51:51,E74) -> #REF! | F80: =+SUMIFS(54:54,51:51,F74) -> #REF! | G80: =+SUMIFS(54:54,51:51,G74) -> #REF! | H80: =+SUMIFS(54:54,51:51,H74) -> #REF! | I80: =+SUMIFS(54:54,51:51,I74) -> #REF! | J80: =+SUMIFS(54:54,51:51,J74) -> 0 | K80: =+SUMIFS(54:54,51:51,K74) -> 0 | L80: =+SUMIFS(54:54,51:51,L74) -> 0 | ... Y80: =+SUMIFS(54:54,51:51,Y74) -> 0
B81: Seguros | E81: =+SUMIFS(55:55,51:51,E74) -> #REF! | F81: =+SUMIFS(55:55,51:51,F74) -> #REF! | G81: =+SUMIFS(55:55,51:51,G74) -> #REF! | H81: =+SUMIFS(55:55,51:51,H74) -> #REF! | I81: =+SUMIFS(55:55,51:51,I74) -> #REF! | J81: =+SUMIFS(55:55,51:51,J74) -> 0 | K81: =+SUMIFS(55:55,51:51,K74) -> 0 | L81: =+SUMIFS(55:55,51:51,L74) -> 0 | ... Y81: =+SUMIFS(55:55,51:51,Y74) -> 0
B82: Total | E82: =+E75+E80+E81 -> #REF! | F82: =+F75+F80+F81 -> #REF! | G82: =+G75+G80+G81 -> #REF! | H82: =+H75+H80+H81 -> #REF! | I82: =+I75+I80+I81 -> #REF! | J82: =+J75+J80+J81 -> #REF! | K82: =+K75+K80+K81 -> #REF! | L82: =+L75+L80+L81 -> #REF! | ... Y82: =+Y75+Y80+Y81 -> #REF!
E84: =+YEAR(E85) -> 2024 | F84: =+YEAR(F85) -> 2024 | G84: =+YEAR(G85) -> 2024 | H84: =+YEAR(H85) -> 2024 | I84: =+YEAR(I85) -> 2024 | J84: =+YEAR(J85) -> 2025 | K84: =+YEAR(K85) -> 2025 | L84: =+YEAR(L85) -> 2025 | ... IO84: =+YEAR(IO85) -> 2044
A85: Costos para la empresa MP | B85: Total | C85: Pareto | D85: Tarifa | E85: 45505 | F85: 45536 | G85: 45566 | H85: 45597 | I85: 45627 | J85: 45658 | K85: 45689 | L85: 45717 | M85: 45748 | N85: 45778 | O85: 45809 | P85: 45839 | Q85: 45870 | R85: 45901 | S85: 45931 | T85: 45962 | U85: 45992 | V85: 46023 | W85: 46054 | X85: 46082 | Y85: 46113 | Z85: 46143 | AA85: 46174 | AB85: 46204 | AC85: 46235 | AD85: 46266 | AE85: 46296 | AF85: 46327 | AG85: 46357 | AH85: 46388 | AI85: 46419 | AJ85: 46447 | AK85: 46478 | AL85: 46508 | AM85: 46539 | AN85: 46569 | AO85: 46600 | AP85: 46631 | AQ85: 46661 | AR85: 46692 | AS85: 46722 | AT85: 46753 | AU85: 46784 | AV85: 46813 | AW85: 46844 | AX85: 46874 | AY85: 46905 | AZ85: 46935 | BA85: 46966 | BB85: 46997 | BC85: 47027 | BD85: 47058 | BE85: 47088 | BF85: 47119 | BG85: 47150 | BH85: 47178 | BI85: 47209 | BJ85: 47239 | BK85: 47270 | BL85: 47300 | BM85: 47331 | BN85: 47362 | BO85: 47392 | BP85: 47423 | BQ85: 47453 | BR85: 47484 | BS85: 47515 | BT85: 47543 | BU85: 47574 | BV85: 47604 | BW85: 47635 | BX85: 47665 | BY85: 47696 | BZ85: 47727 | CA85: 47757 | CB85: 47788 | CC85: 47818 | CD85: 47849 | CE85: 47880 | CF85: 47908 | CG85: 47939 | CH85: 47969 | CI85: 48000 | CJ85: 48030 | CK85: 48061 | CL85: 48092 | CM85: 48122 | CN85: 48153 | CO85: 48183 | CP85: 48214 | CQ85: 48245 | CR85: 48274 | CS85: 48305 | CT85: 48335 | CU85: 48366 | CV85: 48396 | CW85: 48427 | CX85: 48458 | CY85: 48488 | CZ85: 48519 | DA85: 48549 | DB85: 48580 | DC85: 48611 | DD85: 48639 | DE85: 48670 | DF85: 48700 | DG85: 48731 | DH85: 48761 | DI85: 48792 | DJ85: 48823 | DK85: 48853 | DL85: 48884 | DM85: 48914 | DN85: 48945 | DO85: 48976 | DP85: 49004 | DQ85: 49035 | DR85: 49065 | DS85: 49096 | DT85: 49126 | DU85: 49157 | DV85: 49188 | DW85: 49218 | DX85: 49249 | DY85: 49279 | DZ85: 49310 | EA85: 49341 | EB85: 49369 | EC85: 49400 | ED85: 49430 | EE85: 49461 | EF85: 49491 | EG85: 49522 | EH85: 49553 | EI85: 49583 | EJ85: 49614 | EK85: 49644 | EL85: 49675 | EM85: 49706 | EN85: 49735 | EO85: 49766 | EP85: 49796 | EQ85: 49827 | ER85: 49857 | ES85: 49888 | ET85: 49919 | EU85: 49949 | EV85: 49980 | EW85: 50010 | EX85: 50041 | EY85: 50072 | EZ85: 50100 | FA85: 50131 | FB85: 50161 | FC85: 50192 | FD85: 50222 | FE85: 50253 | FF85: 50284 | FG85: 50314 | FH85: 50345 | FI85: 50375 | FJ85: 50406 | FK85: 50437 | FL85: 50465 | FM85: 50496 | FN85: 50526 | FO85: 50557 | FP85: 50587 | FQ85: 50618 | FR85: 50649 | FS85: 50679 | FT85: 50710 | FU85: 50740 | FV85: 50771 | FW85: 50802 | FX85: 50830 | FY85: 50861 | FZ85: 50891 | GA85: 50922 | GB85: 50952 | GC85: 50983 | GD85: 51014 | GE85: 51044 | GF85: 51075 | GG85: 51105 | GH85: 51136 | GI85: 51167 | GJ85: 51196 | GK85: 51227 | GL85: 51257 | GM85: 51288 | GN85: 51318 | GO85: 51349 | GP85: 51380 | GQ85: 51410 | GR85: 51441 | GS85: 51471 | GT85: 51502 | GU85: 51533 | GV85: 51561 | GW85: 51592 | GX85: 51622 | GY85: 51653 | GZ85: 51683 | HA85: 51714 | HB85: 51745 | HC85: 51775 | HD85: 51806 | HE85: 51836 | HF85: 51867 | HG85: 51898 | HH85: 51926 | HI85: 51957 | HJ85: 51987 | HK85: 52018 | HL85: 52048 | HM85: 52079 | HN85: 52110 | HO85: 52140 | HP85: 52171 | HQ85: 52201 | HR85: 52232 | HS85: 52263 | HT85: 52291 | HU85: 52322 | HV85: 52352 | HW85: 52383 | HX85: 52413 | HY85: 52444 | HZ85: 52475 | IA85: 52505 | IB85: 52536 | IC85: 52566 | ID85: 52597 | IE85: 52628 | IF85: 52657 | IG85: 52688 | IH85: 52718 | II85: 52749 | IJ85: 52779 | IK85: 52810 | IL85: 52841 | IM85: 52871 | IN85: 52902 | IO85: 52932
A86: Amortización Capital | B86: =+SUM(E86:DY86) -> #REF! | C86: =+B86/$B$92 -> #REF! | D86: =+B86/$B$93 -> #REF! | E86: =+'Simulacion prestamo'!C57 -> #REF! | F86: =+'Simulacion prestamo'!D57 -> #REF! | G86: =+'Simulacion prestamo'!E57 -> #REF! | H86: =+'Simulacion prestamo'!F57 -> #REF! | I86: =+'Simulacion prestamo'!G57 -> #REF! | J86: =+'Simulacion prestamo'!H57 -> #REF! | K86: =+'Simulacion prestamo'!I57 -> #REF! | L86: =+'Simulacion prestamo'!J57 -> #REF! | ... IO86: =+'Simulacion prestamo'!IM57 -> 0
A87: Amortización Intereses | B87: =+SUM(E87:DY87) -> #REF! | C87: =+B87/$B$92 -> #REF! | D87: =+B87/$B$93 -> #REF! | E87: =+'Simulacion prestamo'!C56 -> #REF! | F87: =+'Simulacion prestamo'!D56 -> #REF! | G87: =+'Simulacion prestamo'!E56 -> #REF! | H87: =+'Simulacion prestamo'!F56 -> #REF! | I87: =+'Simulacion prestamo'!G56 -> #REF! | J87: =+'Simulacion prestamo'!H56 -> #REF! | K87: =+'Simulacion prestamo'!I56 -> #REF! | L87: =+'Simulacion prestamo'!J56 -> #REF! | ... IO87: =+'Simulacion prestamo'!IM56 -> 0
A88: Seguros | B88: =+SUM(E88:DY88) -> #REF! | C88: =+B88/$B$92 -> #REF! | D88: =+B88/$B$93 -> #REF! | E88: =+'Simulacion prestamo'!C59 -> #REF! | F88: =+'Simulacion prestamo'!D59 -> #REF! | G88: =+'Simulacion prestamo'!E59 -> #REF! | H88: =+'Simulacion prestamo'!F59 -> #REF! | I88: =+'Simulacion prestamo'!G59 -> #REF! | J88: =+'Simulacion prestamo'!H59 -> #REF! | K88: =+'Simulacion prestamo'!I59 -> #REF! | L88: =+'Simulacion prestamo'!J59 -> #REF! | ... IO88: =+'Simulacion prestamo'!IM59 -> 0
A89: Mantenimiento | B89: =+SUM(E89:DY89) -> #REF! | C89: =+B89/$B$92 -> #REF! | D89: =+B89/$B$93 -> #REF! | E89: =+E56 -> 0 | F89: =+F56 -> 0 | G89: =+G56 -> 0 | H89: =+H56 -> #REF! | I89: =+I56 -> 0 | J89: =+J56 -> 0 | K89: =+K56 -> #REF! | L89: =+L56 -> 0 | ... IO89: =+IO56 -> 0
A90: Reposición | B90: =+SUM(E90:DY90) -> #REF! | C90: =+B90/$B$92 -> #REF! | D90: =+B90/$B$93 -> #REF! | E90: =+E57 -> 0 | F90: =+F57 -> 0 | G90: =+G57 -> 0 | H90: =+H57 -> 0 | I90: =+I57 -> 0 | J90: =+J57 -> 0 | K90: =+K57 -> 0 | L90: =+L57 -> 0 | ... IO90: =+IO57 -> 0
A91: Operación | B91: =+SUM(E91:DY91) -> #REF! | C91: =+B91/$B$92 -> #REF! | D91: =+B91/$B$93 -> #REF! | E91: =+E58 -> #REF! | F91: =+F58 -> #REF! | G91: =+G58 -> #REF! | H91: =+H58 -> #REF! | I91: =+I58 -> #REF! | J91: =+J58 -> #REF! | K91: =+K58 -> #REF! | L91: =+L58 -> #REF! | ... IO91: =+IO58 -> #REF!
A92: Total | B92: =+SUM(E92:DY92) -> #REF! | D92: =+B92/$B$93 -> #REF! | E92: =+SUM(E86:E91) -> #REF! | F92: =+SUM(F86:F91) -> #REF! | G92: =+SUM(G86:G91) -> #REF! | H92: =+SUM(H86:H91) -> #REF! | I92: =+SUM(I86:I91) -> #REF! | J92: =+SUM(J86:J91) -> #REF! | K92: =+SUM(K86:K91) -> #REF! | L92: =+SUM(L86:L91) -> #REF! | ... IO92: =+SUM(IO86:IO91) -> #REF!
A93: Energía | B93: =+SUM(E8:DY8) -> 254510.59
A94: Tarifa ($/kWH) | B94: =+B92/SUM(E8:DY8) -> #REF!
E96: 2024 | F96: 2025 | G96: 2026 | H96: 2027 | I96: 2028 | J96: 2029 | K96: 2030 | L96: 2031 | M96: 2032 | N96: 2033 | O96: 2034 | P96: 2035 | Q96: 2036 | R96: 2037 | S96: 2038 | T96: 2039 | U96: 2040 | V96: 2041 | W96: 2042 | X96: 2043 | Y96: 2044
B97: Costos | E97: =+SUM(E98:E101) -> #REF! | F97: =+SUM(F98:F101) -> #REF! | G97: =+SUM(G98:G101) -> #REF! | H97: =+SUM(H98:H101) -> #REF! | I97: =+SUM(I98:I101) -> #REF! | J97: =+SUM(J98:J101) -> #REF! | K97: =+SUM(K98:K101) -> #REF! | L97: =+SUM(L98:L101) -> #REF! | ... Y97: =+SUM(Y98:Y101) -> #REF!
B98: Amortización Capital | E98: =+SUMIFS(86:86,84:84,E96) -> #REF! | F98: =+SUMIFS(86:86,84:84,F96) -> #REF! | G98: =+SUMIFS(86:86,84:84,G96) -> #REF! | H98: =+SUMIFS(86:86,84:84,H96) -> #REF! | I98: =+SUMIFS(86:86,84:84,I96) -> #REF! | J98: =+SUMIFS(86:86,84:84,J96) -> #REF! | K98: =+SUMIFS(86:86,84:84,K96) -> #REF! | L98: =+SUMIFS(86:86,84:84,L96) -> 0 | ... Y98: =+SUMIFS(86:86,84:84,Y96) -> 0
B99: Mantenimiento | E99: =+SUMIFS(89:89,84:84,E96) -> #REF! | F99: =+SUMIFS(89:89,84:84,F96) -> #REF! | G99: =+SUMIFS(89:89,84:84,G96) -> #REF! | H99: =+SUMIFS(89:89,84:84,H96) -> #REF! | I99: =+SUMIFS(89:89,84:84,I96) -> #REF! | J99: =+SUMIFS(89:89,84:84,J96) -> #REF! | K99: =+SUMIFS(89:89,84:84,K96) -> #REF! | L99: =+SUMIFS(89:89,84:84,L96) -> #REF! | ... Y99: =+SUMIFS(89:89,84:84,Y96) -> #REF!
B100: Reposición | E100: =+SUMIFS(90:90,84:84,E96) -> 0 | F100: =+SUMIFS(90:90,84:84,F96) -> 0 | G100: =+SUMIFS(90:90,84:84,G96) -> 0 | H100: =+SUMIFS(90:90,84:84,H96) -> 0 | I100: =+SUMIFS(90:90,84:84,I96) -> #REF! | J100: =+SUMIFS(90:90,84:84,J96) -> #REF! | K100: =+SUMIFS(90:90,84:84,K96) -> #REF! | L100: =+SUMIFS(90:90,84:84,L96) -> #REF! | ... Y100: =+SUMIFS(90:90,84:84,Y96) -> 0
B101: Operación | E101: =+SUMIFS(91:91,84:84,E96) -> #REF! | F101: =+SUMIFS(91:91,84:84,F96) -> #REF! | G101: =+SUMIFS(91:91,84:84,G96) -> #REF! | H101: =+SUMIFS(91:91,84:84,H96) -> #REF! | I101: =+SUMIFS(91:91,84:84,I96) -> #REF! | J101: =+SUMIFS(91:91,84:84,J96) -> #REF! | K101: =+SUMIFS(91:91,84:84,K96) -> #REF! | L101: =+SUMIFS(91:91,84:84,L96) -> #REF! | ... Y101: =+SUMIFS(91:91,84:84,Y96) -> #REF!
B102: Intereses | E102: =+SUMIFS(87:87,84:84,E96) -> #REF! | F102: =+SUMIFS(87:87,84:84,F96) -> #REF! | G102: =+SUMIFS(87:87,84:84,G96) -> #REF! | H102: =+SUMIFS(87:87,84:84,H96) -> #REF! | I102: =+SUMIFS(87:87,84:84,I96) -> #REF! | J102: =+SUMIFS(87:87,84:84,J96) -> #REF! | K102: =+SUMIFS(87:87,84:84,K96) -> #REF! | L102: =+SUMIFS(87:87,84:84,L96) -> 0 | ... Y102: =+SUMIFS(87:87,84:84,Y96) -> 0
B103: Seguros | E103: =+SUMIFS(88:88,84:84,E96) -> #REF! | F103: =+SUMIFS(88:88,84:84,F96) -> #REF! | G103: =+SUMIFS(88:88,84:84,G96) -> #REF! | H103: =+SUMIFS(88:88,84:84,H96) -> #REF! | I103: =+SUMIFS(88:88,84:84,I96) -> #REF! | J103: =+SUMIFS(88:88,84:84,J96) -> #REF! | K103: =+SUMIFS(88:88,84:84,K96) -> #REF! | L103: =+SUMIFS(88:88,84:84,L96) -> 0 | ... Y103: =+SUMIFS(88:88,84:84,Y96) -> 0
B104: Total | E104: =+E97+E102+E103 -> #REF! | F104: =+F97+F102+F103 -> #REF! | G104: =+G97+G102+G103 -> #REF! | H104: =+H97+H102+H103 -> #REF! | I104: =+I97+I102+I103 -> #REF! | J104: =+J97+J102+J103 -> #REF! | K104: =+K97+K102+K103 -> #REF! | L104: =+L97+L102+L103 -> #REF! | ... Y104: =+Y97+Y102+Y103 -> #REF!
E106: =+YEAR(E107) -> 2024 | F106: =+YEAR(F107) -> 2024 | G106: =+YEAR(G107) -> 2024 | H106: =+YEAR(H107) -> 2024 | I106: =+YEAR(I107) -> 2024 | J106: =+YEAR(J107) -> 2025 | K106: =+YEAR(K107) -> 2025 | L106: =+YEAR(L107) -> 2025 | ... IJ106: =+YEAR(IJ107) -> 2044
A107: Costos para la empresa LP | B107: Total | C107: Pareto | D107: Tarifa | E107: 45505 | F107: 45536 | G107: 45566 | H107: 45597 | I107: 45627 | J107: 45658 | K107: 45689 | L107: 45717 | M107: 45748 | N107: 45778 | O107: 45809 | P107: 45839 | Q107: 45870 | R107: 45901 | S107: 45931 | T107: 45962 | U107: 45992 | V107: 46023 | W107: 46054 | X107: 46082 | Y107: 46113 | Z107: 46143 | AA107: 46174 | AB107: 46204 | AC107: 46235 | AD107: 46266 | AE107: 46296 | AF107: 46327 | AG107: 46357 | AH107: 46388 | AI107: 46419 | AJ107: 46447 | AK107: 46478 | AL107: 46508 | AM107: 46539 | AN107: 46569 | AO107: 46600 | AP107: 46631 | AQ107: 46661 | AR107: 46692 | AS107: 46722 | AT107: 46753 | AU107: 46784 | AV107: 46813 | AW107: 46844 | AX107: 46874 | AY107: 46905 | AZ107: 46935 | BA107: 46966 | BB107: 46997 | BC107: 47027 | BD107: 47058 | BE107: 47088 | BF107: 47119 | BG107: 47150 | BH107: 47178 | BI107: 47209 | BJ107: 47239 | BK107: 47270 | BL107: 47300 | BM107: 47331 | BN107: 47362 | BO107: 47392 | BP107: 47423 | BQ107: 47453 | BR107: 47484 | BS107: 47515 | BT107: 47543 | BU107: 47574 | BV107: 47604 | BW107: 47635 | BX107: 47665 | BY107: 47696 | BZ107: 47727 | CA107: 47757 | CB107: 47788 | CC107: 47818 | CD107: 47849 | CE107: 47880 | CF107: 47908 | CG107: 47939 | CH107: 47969 | CI107: 48000 | CJ107: 48030 | CK107: 48061 | CL107: 48092 | CM107: 48122 | CN107: 48153 | CO107: 48183 | CP107: 48214 | CQ107: 48245 | CR107: 48274 | CS107: 48305 | CT107: 48335 | CU107: 48366 | CV107: 48396 | CW107: 48427 | CX107: 48458 | CY107: 48488 | CZ107: 48519 | DA107: 48549 | DB107: 48580 | DC107: 48611 | DD107: 48639 | DE107: 48670 | DF107: 48700 | DG107: 48731 | DH107: 48761 | DI107: 48792 | DJ107: 48823 | DK107: 48853 | DL107: 48884 | DM107: 48914 | DN107: 48945 | DO107: 48976 | DP107: 49004 | DQ107: 49035 | DR107: 49065 | DS107: 49096 | DT107: 49126 | DU107: 49157 | DV107: 49188 | DW107: 49218 | DX107: 49249 | DY107: 49279 | DZ107: 49310 | EA107: 49341 | EB107: 49369 | EC107: 49400 | ED107: 49430 | EE107: 49461 | EF107: 49491 | EG107: 49522 | EH107: 49553 | EI107: 49583 | EJ107: 49614 | EK107: 49644 | EL107: 49675 | EM107: 49706 | EN107: 49735 | EO107: 49766 | EP107: 49796 | EQ107: 49827 | ER107: 49857 | ES107: 49888 | ET107: 49919 | EU107: 49949 | EV107: 49980 | EW107: 50010 | EX107: 50041 | EY107: 50072 | EZ107: 50100 | FA107: 50131 | FB107: 50161 | FC107: 50192 | FD107: 50222 | FE107: 50253 | FF107: 50284 | FG107: 50314 | FH107: 50345 | FI107: 50375 | FJ107: 50406 | FK107: 50437 | FL107: 50465 | FM107: 50496 | FN107: 50526 | FO107: 50557 | FP107: 50587 | FQ107: 50618 | FR107: 50649 | FS107: 50679 | FT107: 50710 | FU107: 50740 | FV107: 50771 | FW107: 50802 | FX107: 50830 | FY107: 50861 | FZ107: 50891 | GA107: 50922 | GB107: 50952 | GC107: 50983 | GD107: 51014 | GE107: 51044 | GF107: 51075 | GG107: 51105 | GH107: 51136 | GI107: 51167 | GJ107: 51196 | GK107: 51227 | GL107: 51257 | GM107: 51288 | GN107: 51318 | GO107: 51349 | GP107: 51380 | GQ107: 51410 | GR107: 51441 | GS107: 51471 | GT107: 51502 | GU107: 51533 | GV107: 51561 | GW107: 51592 | GX107: 51622 | GY107: 51653 | GZ107: 51683 | HA107: 51714 | HB107: 51745 | HC107: 51775 | HD107: 51806 | HE107: 51836 | HF107: 51867 | HG107: 51898 | HH107: 51926 | HI107: 51957 | HJ107: 51987 | HK107: 52018 | HL107: 52048 | HM107: 52079 | HN107: 52110 | HO107: 52140 | HP107: 52171 | HQ107: 52201 | HR107: 52232 | HS107: 52263 | HT107: 52291 | HU107: 52322 | HV107: 52352 | HW107: 52383 | HX107: 52413 | HY107: 52444 | HZ107: 52475 | IA107: 52505 | IB107: 52536 | IC107: 52566 | ID107: 52597 | IE107: 52628 | IF107: 52657 | IG107: 52688 | IH107: 52718 | II107: 52749 | IJ107: 52779
A108: Amortización Capital | B108: =+SUM(E108:GG108) -> #REF! | C108: =+B108/$B$114 -> #REF! | D108: =+B108/$B$115 -> #REF! | E108: =+'Simulacion prestamo'!C101 -> #REF! | F108: =+'Simulacion prestamo'!D101 -> #REF! | G108: =+'Simulacion prestamo'!E101 -> #REF! | H108: =+'Simulacion prestamo'!F101 -> #REF! | I108: =+'Simulacion prestamo'!G101 -> #REF! | J108: =+'Simulacion prestamo'!H101 -> #REF! | K108: =+'Simulacion prestamo'!I101 -> #REF! | L108: =+'Simulacion prestamo'!J101 -> #REF! | ... IJ108: =+'Simulacion prestamo'!IH101 -> 0
A109: Amortización Intereses | B109: =+SUM(E109:GG109) -> #REF! | C109: =+B109/$B$114 -> #REF! | D109: =+B109/$B$115 -> #REF! | E109: =+'Simulacion prestamo'!C100 -> #REF! | F109: =+'Simulacion prestamo'!D100 -> #REF! | G109: =+'Simulacion prestamo'!E100 -> #REF! | H109: =+'Simulacion prestamo'!F100 -> #REF! | I109: =+'Simulacion prestamo'!G100 -> #REF! | J109: =+'Simulacion prestamo'!H100 -> #REF! | K109: =+'Simulacion prestamo'!I100 -> #REF! | L109: =+'Simulacion prestamo'!J100 -> #REF! | ... IJ109: =+'Simulacion prestamo'!IH100 -> 0
A110: Seguros | B110: =+SUM(E110:GG110) -> #REF! | C110: =+B110/$B$114 -> #REF! | D110: =+B110/$B$115 -> #REF! | E110: =+'Simulacion prestamo'!C103 -> #REF! | F110: =+'Simulacion prestamo'!D103 -> #REF! | G110: =+'Simulacion prestamo'!E103 -> #REF! | H110: =+'Simulacion prestamo'!F103 -> #REF! | I110: =+'Simulacion prestamo'!G103 -> #REF! | J110: =+'Simulacion prestamo'!H103 -> #REF! | K110: =+'Simulacion prestamo'!I103 -> #REF! | L110: =+'Simulacion prestamo'!J103 -> #REF! | ... IJ110: =+'Simulacion prestamo'!IH103 -> 0
A111: Mantenimiento | B111: =+SUM(E111:GG111) -> #REF! | C111: =+B111/$B$114 -> #REF! | D111: =+B111/$B$115 -> #REF! | E111: =+E89 -> 0 | F111: =+F89 -> 0 | G111: =+G89 -> 0 | H111: =+H89 -> #REF! | I111: =+I89 -> 0 | J111: =+J89 -> 0 | K111: =+K89 -> #REF! | L111: =+L89 -> 0 | ... IJ111: =+IJ89 -> 0
...

Sheet Liquidación
A1: Ejemplo
A2: Curva de consumo | C2: Producción Mensual | D2: =+AVERAGE(Producción!E8:P8) -> 2064.8531 | E2: kWh-mes | F2: =+D2/D3 -> 1.1813224
A3: Carga Residencia | C3: Consumo Mensual | D3: =+AVERAGE(Producción!E9:P9) -> 1747.9167 | E3: kWh-mes
A5: Hora | B5: Consumo PU | C5: Producción Solar PU | D5: Consumo horario | E5: Producción Horaria | F5: Importación | G5: Excedentes | H5: Acumulacion energia
A6: 0 | B6: 0.036858089 | C6: 0 | D6: =+($D$3*B6) -> 64.424869 | E6: =+$D$2*C6 -> 0 | F6: =+IF(D6>E6,D6-E6,0) -> 64.424869 | G6: =+IF(D6<E6,E6-D6,0) -> 0 | H6: =+G6 -> 0
A7: 1 | B7: 0.028575373 | C7: 0 | D7: =+($D$3*B7) -> 49.94737 | E7: =+$D$2*C7 -> 0 | F7: =+IF(D7>E7,D7-E7,0) -> 49.94737 | G7: =+IF(D7<E7,E7-D7,0) -> 0 | H7: =+H6+G7 -> 0
A8: 2 | B8: 0.025331309 | C8: 0 | D8: =+($D$3*B8) -> 44.277017 | E8: =+$D$2*C8 -> 0 | F8: =+IF(D8>E8,D8-E8,0) -> 44.277017 | G8: =+IF(D8<E8,E8-D8,0) -> 0 | H8: =+H7+G8 -> 0
A9: 3 | B9: 0.024641082 | C9: 0 | D9: =+($D$3*B9) -> 43.070558 | E9: =+$D$2*C9 -> 0 | F9: =+IF(D9>E9,D9-E9,0) -> 43.070558 | G9: =+IF(D9<E9,E9-D9,0) -> 0 | H9: =+H8+G9 -> 0
A10: 4 | B10: 0.024364992 | C10: 0 | D10: =+($D$3*B10) -> 42.587975 | E10: =+$D$2*C10 -> 0 | F10: =+IF(D10>E10,D10-E10,0) -> 42.587975 | G10: =+IF(D10<E10,E10-D10,0) -> 0 | H10: =+H9+G10 -> 0
A11: 5 | B11: 0.025814467 | C11: 0.001757882 | D11: =+($D$3*B11) -> 45.121537 | E11: =+$D$2*C11 -> 3.6297682 | F11: =+IF(D11>E11,D11-E11,0) -> 41.491769 | G11: =+IF(D11<E11,E11-D11,0) -> 0 | H11: =+H10+G11 -> 0
A12: 6 | B12: 0.038307565 | C12: 0.0076682064 | D12: =+($D$3*B12) -> 66.958431 | E12: =+$D$2*C12 -> 15.83372 | F12: =+IF(D12>E12,D12-E12,0) -> 51.124711 | G12: =+IF(D12<E12,E12-D12,0) -> 0 | H12: =+H11+G12 -> 0
A13: 7 | B13: 0.024088901 | C13: 0.025531144 | D13: =+($D$3*B13) -> 42.105392 | E13: =+$D$2*C13 -> 52.718063 | F13: =+IF(D13>E13,D13-E13,0) -> 0 | G13: =+IF(D13<E13,E13-D13,0) -> 10.612671 | H13: =+H12+G13 -> 10.612671
A14: 8 | B14: 0.011733849 | C14: 0.084841197 | D14: =+($D$3*B14) -> 20.50979 | E14: =+$D$2*C14 -> 175.18461 | F14: =+IF(D14>E14,D14-E14,0) -> 0 | G14: =+IF(D14<E14,E14-D14,0) -> 154.67482 | H14: =+H13+G14 -> 165.28749
A15: 9 | B15: 0.0146328 | C15: 0.086544915 | D15: =+($D$3*B15) -> 25.576914 | E15: =+$D$2*C15 -> 178.70254 | F15: =+IF(D15>E15,D15-E15,0) -> 0 | G15: =+IF(D15<E15,E15-D15,0) -> 153.12563 | H15: =+H14+G15 -> 318.41312
A16: 10 | B16: 0.0099392601 | C16: 0.10217382 | D16: =+($D$3*B16) -> 17.372998 | E16: =+$D$2*C16 -> 210.97392 | F16: =+IF(D16>E16,D16-E16,0) -> 0 | G16: =+IF(D16<E16,E16-D16,0) -> 193.60093 | H16: =+H15+G16 -> 512.01405
A17: 11 | B17: 0.0089729431 | C17: 0.14205853 | D17: =+($D$3*B17) -> 15.683957 | E17: =+$D$2*C17 -> 293.33001 | F17: =+IF(D17>E17,D17-E17,0) -> 0 | G17: =+IF(D17<E17,E17-D17,0) -> 277.64605 | H17: =+H16+G17 -> 789.6601
A18: 12 | B18: 0.0097321922 | C18: 0.14772118 | D18: =+($D$3*B18) -> 17.011061 | E18: =+$D$2*C18 -> 305.02254 | F18: =+IF(D18>E18,D18-E18,0) -> 0 | G18: =+IF(D18<E18,E18-D18,0) -> 288.01148 | H18: =+H17+G18 -> 1077.6716
... A27: 21 | B27: 0.053837659 | C27: 0 | D27: =+($D$3*B27) -> 94.103741 | E27: =+$D$2*C27 -> 0 | F27: =+IF(D27>E27,D27-E27,0) -> 94.103741 | G27: =+IF(D27<E27,E27-D27,0) -> 0 | H27: =+H26+G27 -> 1471.2478
A28: 22 | B28: 0.042586969 | C28: 0 | D28: =+($D$3*B28) -> 74.438472 | E28: =+$D$2*C28 -> 0 | F28: =+IF(D28>E28,D28-E28,0) -> 74.438472 | G28: =+IF(D28<E28,E28-D28,0) -> 0 | H28: =+H27+G28 -> 1471.2478 | N28: C-P
A29: 23 | B29: 0.032716731 | C29: 0 | D29: =+($D$3*B29) -> 57.18612 | E29: =+$D$2*C29 -> 0 | F29: =+IF(D29>E29,D29-E29,0) -> 57.18612 | G29: =+IF(D29<E29,E29-D29,0) -> 0 | H29: =+H28+G29 -> 1471.2478
A30: Total | B30: =+SUM(B6:B29) -> 1 | C30: =+SUM(C6:C29) -> 1 | D30: =+SUM(D6:D29) -> 1747.9167 | E30: =+SUM(E6:E29) -> 2064.8531 | F30: =+SUM(F6:F29) -> 1154.3113 | G30: =+SUM(G6:G29) -> 1471.2478
J31: kWh-mes | K31: Tarifa | M31: Total | P31: Case Base | Q31: =+Q33*621.54 -> 159182.61
E32: Excedentes | F32: =+G30 -> 1471.2478 | G32: kWh-mes | H32: =+F32/E30 -> 0.71251935 | Q32: Caso 1 | R32: Caso 2 | S32: Caso 3
E33: Tipo 1 | F33: =+F32+F34 -> 1154.3113 | G33: kWh-mes | H33: =+F33/F32 -> 0.78457981 | I33: Con crédito | J33: =+F33 -> 1154.3113 | K33: C | L33: =+Tarifas!S8 -> 125.95 | M33: =+J33*L33 -> 145385.51 | P33: Consumo | Q33: 256.11 | R33: 256.11 | S33: 256.11
E34: Tipo 2 | F34: =+IF(F30>G30,0,F30-G30) -> -316.93648 | G34: kWh-mes | H34: =+-1*F34/F32 -> 0.21542019 | K34: Precio Bolsa | L34: =Tarifas!U11 -> 572.95334 | M34: =+F34*L34 -> -181589.82 | P34: Producido | Q34: 80.33 | R34: 160.65 | S34: 321.3
E35: Autoconsumo | F35: =+E30-G30 -> 593.60533 | G35: kWh-mes | H35: =+F35/E30 -> 0.28748065 | P35: Importación | Q35: =+Q33-Q34 -> 175.78 | R35: =+R33-R36 -> 131.39 | S35: 112.68
P36: Auto consumo | Q36: =+Q33-Q35 -> 80.33 | R36: =+R34-R37 -> 124.72 | S36: =+S34-S37 -> 143.42
E37: Importación | F37: =+F30 -> 1154.3113 | G37: kWh-mes | H37: =+F37/D30 -> 0.66039266 | I37: Sin Crédito | J37: =+F37-J33 -> 0 | K37: CUt | L37: =+Tarifas!S7 -> 807.28 | M37: =+J37*L37 -> 0 | P37: Inyección a red | Q37: 0 | R37: 35.93 | S37: 177.88
E38: Autoconsumo | F38: =+D30-F37 -> 593.60533 | H38: =+F38/D30 -> 0.33960734 | M38: =+M37+M33+M34 -> -36204.303 | P38: Total | Q38: =+Q35*621.54 -> 109254.3 | R38: =+((R35-R37)*621.54)+(R37*55.92) -> 61341.414
F39: =+F32-F37 -> 316.93648
A40: Liquidación Horaria | P40: Ahorro | Q40: =+Q31-Q38 -> 49928.308 | R40: =+Q31-R38 -> 97841.195
D43: Agosto | H43: Septiembre | L43: Octubre | P43: Noviembre | T43: Diciembre | X43: Enero | AB43: Febrero | AF43: Marzo | AJ43: Abril | AN43: Mayo | AR43: Junio | AV43: Julio
A44: Hora | B44: Consumo PU | C44: Producción Solar PU | D44: Consumo horario | E44: Producción Horaria | F44: Importación | G44: Excedentes | H44: Consumo horario | I44: Producción Horaria | J44: Importación | K44: Excedentes | L44: Consumo horario | M44: Producción Horaria | N44: Importación | O44: Excedentes | P44: Consumo horario | Q44: Producción Horaria | R44: Importación | S44: Excedentes | T44: Consumo horario | U44: Producción Horaria | V44: Importación | W44: Excedentes | X44: Consumo horario | Y44: Producción Horaria | Z44: Importación | AA44: Excedentes | AB44: Consumo horario | AC44: Producción Horaria | AD44: Importación | AE44: Excedentes | AF44: Consumo horario | AG44: Producción Horaria | AH44: Importación | AI44: Excedentes | AJ44: Consumo horario | AK44: Producción Horaria | AL44: Importación | AM44: Excedentes | AN44: Consumo horario | AO44: Producción Horaria | AP44: Importación | AQ44: Excedentes | AR44: Consumo horario | AS44: Producción Horaria | AT44: Importación | AU44: Excedentes | AV44: Consumo horario | AW44: Producción Horaria | AX44: Importación | AY44: Excedentes
A45: 0 | B45: 0.020227317 | C45: 0 | D45: =+($D$69*B45) -> 27.529378 | E45: =+$E$69*C45 -> 0 | F45: =+IF(D45>E45,D45-E45,0) -> 27.529378 | G45: =+IF(D45<E45,E45-D45,0) -> 0 | H45: =+($H$69*B45) -> 34.629166 | I45: =+$I$69*C45 -> 0 | J45: =+IF(H45>I45,H45-I45,0) -> 34.629166 | K45: =+IF(H45<I45,I45-H45,0) -> 0 | L45: =+($L$69*B45) -> 31.65575 | M45: =+$M$69*C45 -> 0 | N45: =+IF(L45>M45,L45-M45,0) -> 31.65575 | O45: =+IF(L45<M45,M45-L45,0) -> 0 | P45: =+($P$69*B45) -> 43.347139 | Q45: =+$Q$69*C45 -> 0 | R45: =+IF(P45>Q45,P45-Q45,0) -> 43.347139 | S45: =+IF(P45<Q45,Q45-P45,0) -> 0 | T45: =+($T$69*B45) -> 43.104411 | U45: =+$U$69*C45 -> 0 | V45: =+IF(T45>U45,T45-U45,0) -> 43.104411 | W45: =+IF(T45<U45,U45-T45,0) -> 0 | X45: =+($X$69*B45) -> 48.727605 | Y45: =+$Y$69*C45 -> 0 | Z45: =+IF(X45>Y45,X45-Y45,0) -> 48.727605 | AA45: =+IF(X45<Y45,Y45-X45,0) -> 0 | AB45: =+($AB$69*B45) -> 41.728954 | AC45: =+$AC$69*C45 -> 0 | AD45: =+IF(AB45>AC45,AB45-AC45,0) -> 41.728954 | AE45: =+IF(AB45<AC45,AC45-AB45,0) -> 0 | AF45: =+($AF$69*B45) -> 39.058948 | AG45: =+$AG$69*C45 -> 0 | AH45: =+IF(AF45>AG45,AF45-AG45,0) -> 39.058948 | AI45: =+IF(AF45<AG45,AG45-AF45,0) -> 0 | AJ45: =+($AJ$69*B45) -> 29.107108 | AK45: =+$AK$69*C45 -> 0 | AL45: =+IF(AJ45>AK45,AJ45-AK45,0) -> 29.107108 | AM45: =+IF(AJ45<AK45,AK45-AJ45,0) -> 0 | AN45: =+($AN$69*B45) -> 28.884608 | AO45: =+$AO$69*C45 -> 0 | AP45: =+IF(AN45>AO45,AN45-AO45,0) -> 28.884608 | AQ45: =+IF(AN45<AO45,AO45-AN45,0) -> 0 | AR45: =+($AR$69*B45) -> 31.595068 | AS45: =+$AS$69*C45 -> 0 | AT45: =+IF(AR45>AS45,AR45-AS45,0) -> 31.595068 | AU45: =+IF(AR45<AS45,AS45-AR45,0) -> 0 | AV45: =+($AV$69*B45) -> 24.899827 | AW45: =+$AW$69*C45 -> 0 | AX45: =+IF(AV45>AW45,AV45-AW45,0) -> 24.899827 | AY45: =+IF(AV45<AW45,AW45-AV45,0) -> 0
